Workbook

Sheet 00_Leia-me
B2: EXECUTAR — HUB Control Plane
B4: Fonte primária de verdade (Release 1): esta planilha Google Sheets. O GitHub é espelho estrutural versionado (Release 2).
B6: COMO PREENCHER:
B7: 1. As abas 01_Formulario_<MACROAREA_ID> são a ÚNICA superfície de preenchimento humano.
B8: 2. A coluna 'Resposta' (fill amarelo-claro) é a ÚNICA célula editável em toda a planilha.
B9: 3. Todas as demais abas (02–09) são saídas derivadas — não editar diretamente.
B10: 4. As abas 10–24 (REG_*) são o registro normalizado — fonte estrutural, não editar diretamente.
B12: CONVENÇÃO DE COR:
B13: Preto + texto branco = cabeçalho de domínio (estrutura)
B14: Cinza claro = sub-cabeçalho de artefato
B15: Amarelo claro (fill) = input humano editável (só coluna Resposta)
B16: Azul (texto) = fórmula / referência viva a outra aba
... B22: Fontes: EXECUTAR_projetosaasentrypoint_EXPANDIDO.xlsx (referência de UX), EXECUTAR_CHECKLIST_D01-D23_GRANULAR.yaml, Progama_Master_index.docx, ecossistema_operacional.yaml

Sheet 01_Formulario_A00
F2: Progresso de preenchimento | G2: =COUNTA(D7:D328)&" / 307"
A4: A00 — Governança, Estratégia e Gestão
A5: ID | B5: Campo | C5: O que preencher | D5: Resposta | E5: Exemplo (referência)
A6: Domínio D0 — Pmbook Governança e Operação
A7: Domínio D01 — Gestão Empresarial
A8: Artefato D01-DOC-DDE-001 — Documento de Direção Empresarial
A9: D01-DOC-DDE-001.IDENTITY.NOME_DO_ECOSSISTEMA | B9: nome_do_ecossistema | C9: Definir, validar e manter: Nome Do Ecossistema | E9: alta
A10: D01-DOC-DDE-001.IDENTITY.DESCRICAO_EXECUTIVA | B10: descricao_executiva | C10: Definir, validar e manter: Descricao Executiva | E10: baixa
A11: D01-DOC-DDE-001.IDENTITY.CONTEXTO | B11: contexto | C11: Definir, validar e manter: Contexto | E11: baixa
A12: D01-DOC-DDE-001.IDENTITY.RAZAO_DE_EXISTENCIA | B12: razao_de_existencia | C12: Definir, validar e manter: Razao De Existencia | E12: baixa
A13: D01-DOC-DDE-001.IDENTITY.FASE_ATUAL | B13: fase_atual | C13: Definir, validar e manter: Fase Atual | E13: baixa
A14: D01-DOC-DDE-001.PROBLEM_AND_OPPORTUNITY.PROBLEMA_CENTRAL | B14: problema_central | C14: Definir, validar e manter: Problema Central | E14: baixa
A15: D01-DOC-DDE-001.PROBLEM_AND_OPPORTUNITY.PROBLEMAS_SECUNDARIOS | B15: problemas_secundarios | C15: Definir, validar e manter: Problemas Secundarios | E15: baixa
A16: D01-DOC-DDE-001.PROBLEM_AND_OPPORTUNITY.OPORTUNIDADE | B16: oportunidade | C16: Definir, validar e manter: Oportunidade | E16: baixa
A17: D01-DOC-DDE-001.PROBLEM_AND_OPPORTUNITY.EVIDENCIAS_DO_PROBLEMA | B17: evidencias_do_problema | C17: Definir, validar e manter: Evidencias Do Problema | E17: baixa
A18: D01-DOC-DDE-001.PURPOSE.PROPOSITO | B18: proposito | C18: Definir, validar e manter: Proposito | E18: baixa
A19: D01-DOC-DDE-001.PURPOSE.MISSAO | B19: missao | C19: Definir, validar e manter: Missao | E19: baixa
A20: D01-DOC-DDE-001.PURPOSE.VISAO | B20: visao | C20: Definir, validar e manter: Visao | E20: baixa
... A52: D01-DOC-DDE-001.DECISIONS.DECISOES_PENDENTES | B52: decisoes_pendentes | C52: Definir, validar e manter: Decisoes Pendentes | E52: baixa
A53: Artefato D01-DOC-TAP-001 — Termo de Abertura do Ecossistema
A54: D01-DOC-TAP-001.IDENTIFICATION.TITULO | B54: titulo | C54: Definir, validar e manter: Titulo | E54: baixa
A55: D01-DOC-TAP-001.IDENTIFICATION.JUSTIFICATIVA | B55: justificativa | C55: Definir, validar e manter: Justificativa | E55: baixa
A56: D01-DOC-TAP-001.IDENTIFICATION.CONTEXTO | B56: contexto | C56: Definir, validar e manter: Contexto | E56: baixa
A57: D01-DOC-TAP-001.IDENTIFICATION.SPONSOR | B57: sponsor | C57: Definir, validar e manter: Sponsor | E57: baixa
A58: D01-DOC-TAP-001.IDENTIFICATION.OWNER | B58: owner | C58: Definir, validar e manter: Owner | E58: baixa
A59: D01-DOC-TAP-001.OBJECTIVE.OBJETIVO_GERAL | B59: objetivo_geral | C59: Definir, validar e manter: Objetivo Geral | E59: baixa
A60: D01-DOC-TAP-001.OBJECTIVE.OBJETIVOS_ESPECIFICOS | B60: objetivos_especificos | C60: Definir, validar e manter: Objetivos Especificos | E60: baixa
A61: D01-DOC-TAP-001.OBJECTIVE.RESULTADO_FINAL_ESPERADO | B61: resultado_final_esperado | C61: Definir, validar e manter: Resultado Final Esperado | E61: baixa
A62: D01-DOC-TAP-001.SCOPE.ESCOPO_INCLUIDO | B62: escopo_incluido | C62: Definir, validar e manter: Escopo Incluido | E62: baixa
A63: D01-DOC-TAP-001.SCOPE.ESCOPO_EXCLUIDO | B63: escopo_excluido | C63: Definir, validar e manter: Escopo Excluido | E63: baixa
A64: D01-DOC-TAP-001.SCOPE.FRONTEIRAS | B64: fronteiras | C64: Definir, validar e manter: Fronteiras | E64: baixa
A65: D01-DOC-TAP-001.DELIVERABLES.ENTREGAVEIS_PRINCIPAIS | B65: entregaveis_principais | C65: Definir, validar e manter: Entregaveis Principais | E65: baixa
... A82: D01-DOC-TAP-001.APPROVALS.STATUS_APROVACAO | B82: status_aprovacao | C82: Definir, validar e manter: Status Aprovacao | E82: baixa
A83: Artefato D01-DOC-MNE-001 — Modelo de Negócio do Ecossistema
A84: D01-DOC-MNE-001.CUSTOMER.SEGMENTOS | B84: segmentos | C84: Definir, validar e manter: Segmentos | E84: baixa
A85: D01-DOC-MNE-001.CUSTOMER.USUARIOS | B85: usuarios | C85: Definir, validar e manter: Usuarios | E85: baixa
A86: D01-DOC-MNE-001.CUSTOMER.CLIENTES | B86: clientes | C86: Definir, validar e manter: Clientes | E86: baixa
A87: D01-DOC-MNE-001.CUSTOMER.PROBLEMAS | B87: problemas | C87: Definir, validar e manter: Problemas | E87: baixa
A88: D01-DOC-MNE-001.CUSTOMER.JTBD | B88: jtbd | C88: Definir, validar e manter: JTBD | E88: baixa
A89: D01-DOC-MNE-001.VALUE.PROPOSTAS_DE_VALOR | B89: propostas_de_valor | C89: Definir, validar e manter: Propostas De Valor | E89: baixa
A90: D01-DOC-MNE-001.VALUE.BENEFICIOS | B90: beneficios | C90: Definir, validar e manter: Beneficios | E90: baixa
A91: D01-DOC-MNE-001.VALUE.DIFERENCIADORES | B91: diferenciadores | C91: Definir, validar e manter: Diferenciadores | E91: baixa
A92: D01-DOC-MNE-001.VALUE.ALTERNATIVAS_EXISTENTES | B92: alternativas_existentes | C92: Definir, validar e manter: Alternativas Existentes | E92: baixa
A93: D01-DOC-MNE-001.OFFERINGS.PRODUTOS | B93: produtos | C93: Definir, validar e manter: Produtos | E93: baixa
A94: D01-DOC-MNE-001.OFFERINGS.SERVICOS | B94: servicos | C94: Definir, validar e manter: Servicos | E94: baixa
A95: D01-DOC-MNE-001.OFFERINGS.PLANOS | B95: planos | C95: Definir, validar e manter: Planos | E95: baixa
... A119: D01-DOC-MNE-001.ASSUMPTIONS.VALIDACOES_PENDENTES | B119: validacoes_pendentes | C119: Definir, validar e manter: Validacoes Pendentes | E119: baixa
A120: Artefato D01-DOC-MRE-001 — Mapa de Relações do Ecossistema
A121: D01-DOC-MRE-001.NODES.COMPONENTES | B121: componentes | C121: Definir, validar e manter: Componentes | E121: baixa
A122: D01-DOC-MRE-001.NODES.PRODUTOS | B122: produtos | C122: Definir, validar e manter: Produtos | E122: baixa
A123: D01-DOC-MRE-001.NODES.SERVICOS | B123: servicos | C123: Definir, validar e manter: Servicos | E123: baixa
A124: D01-DOC-MRE-001.NODES.AGENTES | B124: agentes | C124: Definir, validar e manter: Agentes | E124: baixa
A125: D01-DOC-MRE-001.NODES.PLATAFORMAS | B125: plataformas | C125: Definir, validar e manter: Plataformas | E125: baixa
A126: D01-DOC-MRE-001.RELATIONSHIPS.ORIGEM | B126: origem | C126: Definir, validar e manter: Origem | E126: baixa
A127: D01-DOC-MRE-001.RELATIONSHIPS.DESTINO | B127: destino | C127: Definir, validar e manter: Destino | E127: baixa
A128: D01-DOC-MRE-001.RELATIONSHIPS.TIPO_DE_RELACAO | B128: tipo_de_relacao | C128: Definir, validar e manter: Tipo De Relacao | E128: baixa
A129: D01-DOC-MRE-001.RELATIONSHIPS.OBJETIVO | B129: objetivo | C129: Definir, validar e manter: Objetivo | E129: baixa
A130: D01-DOC-MRE-001.FLOWS.FLUXO_DE_VALOR | B130: fluxo_de_valor | C130: Definir, validar e manter: Fluxo De Valor | E130: baixa
A131: D01-DOC-MRE-001.FLOWS.FLUXO_DE_DADOS | B131: fluxo_de_dados | C131: Definir, validar e manter: Fluxo De Dados | E131: baixa
A132: D01-DOC-MRE-001.FLOWS.FLUXO_DE_CONHECIMENTO | B132: fluxo_de_conhecimento | C132: Definir, validar e manter: Fluxo De Conhecimento | E132: baixa
... A143: D01-DOC-MRE-001.RISKS.PONTOS_UNICOS_DE_FALHA | B143: pontos_unicos_de_falha | C143: Definir, validar e manter: Pontos Unicos De Falha | E143: baixa
A144: Domínio D02 — Jurídico, Riscos e Conformidade
A145: Artefato D02-DOC-DGRC-001 — Documento de Governança, Riscos e Conformidade
A146: D02-DOC-DGRC-001.GOVERNANCE.ESTRUTURA_JURIDICA | B146: estrutura_juridica | C146: Definir, validar e manter: Estrutura Juridica | E146: baixa
A147: D02-DOC-DGRC-001.GOVERNANCE.PAPEIS | B147: papeis | C147: Definir, validar e manter: Papeis | E147: baixa
A148: D02-DOC-DGRC-001.GOVERNANCE.AUTORIDADES | B148: autoridades | C148: Definir, validar e manter: Autoridades | E148: baixa
A149: D02-DOC-DGRC-001.GOVERNANCE.POLITICAS | B149: politicas | C149: Definir, validar e manter: Politicas | E149: baixa
A150: D02-DOC-DGRC-001.OBLIGATIONS.LEIS_APLICAVEIS | B150: leis_aplicaveis | C150: Definir, validar e manter: Leis Aplicaveis | E150: baixa
A151: D02-DOC-DGRC-001.OBLIGATIONS.REGULAMENTOS | B151: regulamentos | C151: Definir, validar e manter: Regulamentos | E151: baixa
A152: D02-DOC-DGRC-001.OBLIGATIONS.OBRIGACOES | B152: obrigacoes | C152: Definir, validar e manter: Obrigacoes | E152: baixa
A153: D02-DOC-DGRC-001.OBLIGATIONS.LICENCAS | B153: licencas | C153: Definir, validar e manter: Licencas | E153: baixa
A154: D02-DOC-DGRC-001.CONTRACTS.CONTRATOS_EXISTENTES | B154: contratos_existentes | C154: Definir, validar e manter: Contratos Existentes | E154: baixa
A155: D02-DOC-DGRC-001.CONTRACTS.CONTRATOS_NECESSARIOS | B155: contratos_necessarios | C155: Definir, validar e manter: Contratos Necessarios | E155: baixa
A156: D02-DOC-DGRC-001.CONTRACTS.OBRIGACOES_CONTRATUAIS | B156: obrigacoes_contratuais | C156: Definir, validar e manter: Obrigacoes Contratuais | E156: baixa
A157: D02-DOC-DGRC-001.PRIVACY.DADOS_PESSOAIS | B157: dados_pessoais | C157: Definir, validar e manter: Dados Pessoais | E157: media
... A178: D02-DOC-DGRC-001.APPROVALS.GATES_JURIDICOS | B178: gates_juridicos | C178: Definir, validar e manter: Gates Juridicos | E178: baixa
A179: Artefato D02-DOC-MRC-001 — Matriz de Riscos e Controles
A180: D02-DOC-MRC-001.SCHEMA.RISK_ID | B180: risk_id | C180: Definir, validar e manter: Risk ID | E180: baixa
A181: D02-DOC-MRC-001.SCHEMA.CATEGORIA | B181: categoria | C181: Definir, validar e manter: Categoria | E181: baixa
A182: D02-DOC-MRC-001.SCHEMA.ATIVO_PROCESSO_AFETADO | B182: ativo_processo_afetado | C182: Definir, validar e manter: Ativo Processo Afetado | E182: baixa
A183: D02-DOC-MRC-001.SCHEMA.EVENTO_DE_RISCO | B183: evento_de_risco | C183: Definir, validar e manter: Evento De Risco | E183: baixa
A184: D02-DOC-MRC-001.SCHEMA.CAUSA | B184: causa | C184: Definir, validar e manter: Causa | E184: baixa
A185: D02-DOC-MRC-001.SCHEMA.IMPACTO | B185: impacto | C185: Definir, validar e manter: Impacto | E185: baixa
A186: D02-DOC-MRC-001.SCHEMA.PROBABILIDADE | B186: probabilidade | C186: Definir, validar e manter: Probabilidade | E186: baixa
A187: D02-DOC-MRC-001.SCHEMA.SEVERIDADE | B187: severidade | C187: Definir, validar e manter: Severidade | E187: baixa
A188: D02-DOC-MRC-001.SCHEMA.RISCO_INERENTE | B188: risco_inerente | C188: Definir, validar e manter: Risco Inerente | E188: baixa
A189: D02-DOC-MRC-001.SCHEMA.CONTROLES_EXISTENTES | B189: controles_existentes | C189: Definir, validar e manter: Controles Existentes | E189: baixa
A190: D02-DOC-MRC-001.SCHEMA.EFETIVIDADE_CONTROLE | B190: efetividade_controle | C190: Definir, validar e manter: Efetividade Controle | E190: baixa
A191: D02-DOC-MRC-001.SCHEMA.RISCO_RESIDUAL | B191: risco_residual | C191: Definir, validar e manter: Risco Residual | E191: baixa
... A197: D02-DOC-MRC-001.SCHEMA.STATUS | B197: status | C197: Definir, validar e manter: Status | E197: baixa
A198: Artefato D02-DOC-PPT-001 — Política de Privacidade e Termos
A199: D02-DOC-PPT-001.ORGANIZATION.CONTROLADOR | B199: controlador | C199: Definir, validar e manter: Controlador | E199: baixa
A200: D02-DOC-PPT-001.ORGANIZATION.OPERADOR | B200: operador | C200: Definir, validar e manter: Operador | E200: baixa
A201: D02-DOC-PPT-001.ORGANIZATION.CONTATO | B201: contato | C201: Definir, validar e manter: Contato | E201: baixa
A202: D02-DOC-PPT-001.COLLECTED_DATA.CATEGORIAS_DE_DADOS | B202: categorias_de_dados | C202: Definir, validar e manter: Categorias De Dados | E202: baixa
A203: D02-DOC-PPT-001.COLLECTED_DATA.ORIGEM | B203: origem | C203: Definir, validar e manter: Origem | E203: baixa
A204: D02-DOC-PPT-001.PURPOSES.FINALIDADE | B204: finalidade | C204: Definir, validar e manter: Finalidade | E204: baixa
A205: D02-DOC-PPT-001.PURPOSES.BASE_LEGAL | B205: base_legal | C205: Definir, validar e manter: Base Legal | E205: media
A206: D02-DOC-PPT-001.SHARING.TERCEIROS | B206: terceiros | C206: Definir, validar e manter: Terceiros | E206: baixa
A207: D02-DOC-PPT-001.SHARING.OPERADORES | B207: operadores | C207: Definir, validar e manter: Operadores | E207: baixa
...

Sheet 01_Formulario_A01
F2: Progresso de preenchimento | G2: =COUNTA(D7:D143)&" / 130"
A4: A01 — Negócio e Go-to-Market
A5: ID | B5: Campo | C5: O que preencher | D5: Resposta | E5: Exemplo (referência)
A6: Domínio D13 — Mercado e Geração de Demanda
A7: Artefato D13-DOC-DRM-001 — Documento de Requisitos de Mercado
A8: D13-DOC-DRM-001.MARKET.DEFINICAO | B8: definicao | C8: Definir, validar e manter: Definicao | E8: baixa
A9: D13-DOC-DRM-001.MARKET.TAMANHO | B9: tamanho | C9: Definir, validar e manter: Tamanho | E9: baixa
A10: D13-DOC-DRM-001.MARKET.TENDENCIA | B10: tendencia | C10: Definir, validar e manter: Tendencia | E10: baixa
A11: D13-DOC-DRM-001.SEGMENTS.SEGMENTO | B11: segmento | C11: Definir, validar e manter: Segmento | E11: baixa
A12: D13-DOC-DRM-001.SEGMENTS.NECESSIDADE | B12: necessidade | C12: Definir, validar e manter: Necessidade | E12: baixa
A13: D13-DOC-DRM-001.ICP.PERFIL | B13: perfil | C13: Definir, validar e manter: Perfil | E13: baixa
A14: D13-DOC-DRM-001.ICP.CRITERIOS | B14: criterios | C14: Definir, validar e manter: Criterios | E14: baixa
A15: D13-DOC-DRM-001.ICP.EXCLUSOES | B15: exclusoes | C15: Definir, validar e manter: Exclusoes | E15: baixa
A16: D13-DOC-DRM-001.DEMAND.SINAIS | B16: sinais | C16: Definir, validar e manter: Sinais | E16: baixa
A17: D13-DOC-DRM-001.DEMAND.PROBLEMAS | B17: problemas | C17: Definir, validar e manter: Problemas | E17: baixa
A18: D13-DOC-DRM-001.DEMAND.PROCURA | B18: procura | C18: Definir, validar e manter: Procura | E18: baixa
A19: D13-DOC-DRM-001.ALTERNATIVES.CONCORRENTES | B19: concorrentes | C19: Definir, validar e manter: Concorrentes | E19: baixa
... A34: D13-DOC-DRM-001.RISKS.RISCOS_DE_MERCADO | B34: riscos_de_mercado | C34: Definir, validar e manter: Riscos De Mercado | E34: baixa
A35: Artefato D13-DOC-GTM-001 — Plano de Entrada no Mercado e Lançamento
A36: D13-DOC-GTM-001.OBJECTIVES.OBJETIVO_DE_LANCAMENTO | B36: objetivo_de_lancamento | C36: Definir, validar e manter: Objetivo De Lancamento | E36: baixa
A37: D13-DOC-GTM-001.AUDIENCE.ICP | B37: icp | C37: Definir, validar e manter: Icp | E37: baixa
A38: D13-DOC-GTM-001.AUDIENCE.SEGMENTOS | B38: segmentos | C38: Definir, validar e manter: Segmentos | E38: baixa
A39: D13-DOC-GTM-001.POSITIONING.POSICIONAMENTO | B39: posicionamento | C39: Definir, validar e manter: Posicionamento | E39: baixa
A40: D13-DOC-GTM-001.POSITIONING.MENSAGEM | B40: mensagem | C40: Definir, validar e manter: Mensagem | E40: baixa
A41: D13-DOC-GTM-001.OFFER.PRODUTO | B41: produto | C41: Definir, validar e manter: Produto | E41: baixa
A42: D13-DOC-GTM-001.OFFER.PLANO | B42: plano | C42: Definir, validar e manter: Plano | E42: baixa
A43: D13-DOC-GTM-001.OFFER.PRECO | B43: preco | C43: Definir, validar e manter: Preco | E43: baixa
A44: D13-DOC-GTM-001.CHANNELS.CANAL | B44: canal | C44: Definir, validar e manter: Canal | E44: baixa
A45: D13-DOC-GTM-001.CHANNELS.FUNCAO | B45: funcao | C45: Definir, validar e manter: Funcao | E45: baixa
A46: D13-DOC-GTM-001.CONTENT.ATIVOS | B46: ativos | C46: Definir, validar e manter: Ativos | E46: alta
A47: D13-DOC-GTM-001.CONTENT.CAMPANHA | B47: campanha | C47: Definir, validar e manter: Campanha | E47: baixa
... A67: D13-DOC-GTM-001.GATES.CRITERIO | B67: criterio | C67: Definir, validar e manter: Criterio | E67: baixa
A68: Domínio D14 — Vendas
A69: Artefato D14-DOC-PCV-001 — Plano Comercial e de Vendas
A70: D14-DOC-PCV-001.CUSTOMER.ICP | B70: icp | C70: Definir, validar e manter: Icp | E70: baixa
A71: D14-DOC-PCV-001.CUSTOMER.SEGMENTOS | B71: segmentos | C71: Definir, validar e manter: Segmentos | E71: baixa
A72: D14-DOC-PCV-001.OFFERS.PRODUTO | B72: produto | C72: Definir, validar e manter: Produto | E72: baixa
A73: D14-DOC-PCV-001.OFFERS.PACOTE | B73: pacote | C73: Definir, validar e manter: Pacote | E73: alta
A74: D14-DOC-PCV-001.PRICING.PRECO | B74: preco | C74: Definir, validar e manter: Preco | E74: alta
A75: D14-DOC-PCV-001.PRICING.DESCONTO | B75: desconto | C75: Definir, validar e manter: Desconto | E75: baixa
A76: D14-DOC-PCV-001.QUALIFICATION.CRITERIOS | B76: criterios | C76: Definir, validar e manter: Criterios | E76: baixa
A77: D14-DOC-PCV-001.QUALIFICATION.SCORING | B77: scoring | C77: Definir, validar e manter: Scoring | E77: baixa
A78: D14-DOC-PCV-001.FUNNEL.LEAD | B78: lead | C78: Definir, validar e manter: Lead | E78: baixa
A79: D14-DOC-PCV-001.FUNNEL.MQL | B79: mql | C79: Definir, validar e manter: Mql | E79: baixa
A80: D14-DOC-PCV-001.FUNNEL.SQL | B80: sql | C80: Definir, validar e manter: Sql | E80: baixa
A81: D14-DOC-PCV-001.FUNNEL.PROPOSTA | B81: proposta | C81: Definir, validar e manter: Proposta | E81: baixa
... A108: D14-DOC-PCV-001.METRICS.TICKET | B108: ticket | C108: Definir, validar e manter: Ticket | E108: baixa
A109: Domínio D15 — Atendimento e Sucesso do Cliente
A110: Artefato D15-DOC-PASC-001 — Plano de Atendimento e Sucesso do Cliente
A111: D15-DOC-PASC-001.SERVICE_MODEL.MODELO | B111: modelo | C111: Definir, validar e manter: Modelo | E111: baixa
A112: D15-DOC-PASC-001.SERVICE_MODEL.SEGMENTOS | B112: segmentos | C112: Definir, validar e manter: Segmentos | E112: baixa
A113: D15-DOC-PASC-001.ONBOARDING.ETAPAS | B113: etapas | C113: Definir, validar e manter: Etapas | E113: baixa
A114: D15-DOC-PASC-001.ONBOARDING.OBJETIVO | B114: objetivo | C114: Definir, validar e manter: Objetivo | E114: baixa
A115: D15-DOC-PASC-001.CHANNELS.EMAIL | B115: email | C115: Definir, validar e manter: Email | E115: baixa
A116: D15-DOC-PASC-001.CHANNELS.CHAT | B116: chat | C116: Definir, validar e manter: Chat | E116: baixa
A117: D15-DOC-PASC-001.CHANNELS.OUTROS | B117: outros | C117: Definir, validar e manter: Outros | E117: baixa
A118: D15-DOC-PASC-001.SERVICE_HOURS.HORARIOS | B118: horarios | C118: Definir, validar e manter: Horarios | E118: baixa
A119: D15-DOC-PASC-001.SLA.PRIORIDADE | B119: prioridade | C119: Definir, validar e manter: Prioridade | E119: media
A120: D15-DOC-PASC-001.SLA.PRAZO | B120: prazo | C120: Definir, validar e manter: Prazo | E120: baixa
A121: D15-DOC-PASC-001.KNOWLEDGE_BASE.ARTIGOS | B121: artigos | C121: Definir, validar e manter: Artigos | E121: baixa
A122: D15-DOC-PASC-001.KNOWLEDGE_BASE.FAQ | B122: faq | C122: Definir, validar e manter: Faq | E122: baixa
... A142: D15-DOC-PASC-001.METRICS.CHURN | B142: churn | C142: Definir, validar e manter: Churn | E142: media

Sheet 01_Formulario_A02
F2: Progresso de preenchimento | G2: =COUNTA(D7:D125)&" / 113"
A4: A02 — Produto e Experiência
A5: ID | B5: Campo | C5: O que preencher | D5: Resposta | E5: Exemplo (referência)
A6: Domínio D10 — Gestão de Produto
A7: Artefato D10-DOC-DRP-001 — Documento de Requisitos de Produto
A8: D10-DOC-DRP-001.PROBLEM.PROBLEMA | B8: problema | C8: Definir, validar e manter: Problema | E8: baixa
A9: D10-DOC-DRP-001.PROBLEM.EVIDENCIA | B9: evidencia | C9: Definir, validar e manter: Evidencia | E9: baixa
A10: D10-DOC-DRP-001.PROBLEM.IMPACTO | B10: impacto | C10: Definir, validar e manter: Impacto | E10: baixa
A11: D10-DOC-DRP-001.AUDIENCE.USUARIOS | B11: usuarios | C11: Definir, validar e manter: Usuarios | E11: baixa
A12: D10-DOC-DRP-001.AUDIENCE.CLIENTES | B12: clientes | C12: Definir, validar e manter: Clientes | E12: baixa
A13: D10-DOC-DRP-001.AUDIENCE.ICP | B13: icp | C13: Definir, validar e manter: Icp | E13: baixa
A14: D10-DOC-DRP-001.JTBD.SITUACAO | B14: situacao | C14: Definir, validar e manter: Situacao | E14: baixa
A15: D10-DOC-DRP-001.JTBD.TRABALHO | B15: trabalho | C15: Definir, validar e manter: Trabalho | E15: baixa
A16: D10-DOC-DRP-001.JTBD.OUTCOME | B16: outcome | C16: Definir, validar e manter: Outcome | E16: baixa
A17: D10-DOC-DRP-001.VALUE.PROPOSTA_DE_VALOR | B17: proposta_de_valor | C17: Definir, validar e manter: Proposta De Valor | E17: baixa
A18: D10-DOC-DRP-001.GOALS.OBJETIVOS | B18: objetivos | C18: Definir, validar e manter: Objetivos | E18: baixa
A19: D10-DOC-DRP-001.GOALS.METRICAS | B19: metricas | C19: Definir, validar e manter: Metricas | E19: baixa
... A35: D10-DOC-DRP-001.RISKS.MITIGACAO | B35: mitigacao | C35: Definir, validar e manter: Mitigacao | E35: baixa
A36: Artefato D10-DOC-PRD-001 — Requisitos Integrados dos Produtos
A37: D10-DOC-PRD-001.SCHEMA.PRODUCT_ID | B37: product_id | C37: Definir, validar e manter: Product ID | E37: baixa
A38: D10-DOC-PRD-001.SCHEMA.PRODUCT_NAME | B38: product_name | C38: Definir, validar e manter: Product Name | E38: baixa
A39: D10-DOC-PRD-001.SCHEMA.PROBLEM | B39: problem | C39: Definir, validar e manter: Problem | E39: baixa
A40: D10-DOC-PRD-001.SCHEMA.TARGET_USER | B40: target_user | C40: Definir, validar e manter: Target User | E40: baixa
A41: D10-DOC-PRD-001.SCHEMA.JTBD | B41: jtbd | C41: Definir, validar e manter: JTBD | E41: baixa
A42: D10-DOC-PRD-001.SCHEMA.GOALS | B42: goals | C42: Definir, validar e manter: Goals | E42: baixa
A43: D10-DOC-PRD-001.SCHEMA.NON_GOALS | B43: non_goals | C43: Definir, validar e manter: Non Goals | E43: baixa
A44: D10-DOC-PRD-001.SCHEMA.USE_CASES | B44: use_cases | C44: Definir, validar e manter: Use Cases | E44: baixa
A45: D10-DOC-PRD-001.SCHEMA.USER_STORIES | B45: user_stories | C45: Definir, validar e manter: User Stories | E45: baixa
A46: D10-DOC-PRD-001.SCHEMA.FUNCTIONAL_REQUIREMENTS | B46: functional_requirements | C46: Definir, validar e manter: Functional Requirements | E46: baixa
A47: D10-DOC-PRD-001.SCHEMA.NON_FUNCTIONAL_REQUIREMENTS | B47: non_functional_requirements | C47: Definir, validar e manter: Non Functional Requirements | E47: baixa
A48: D10-DOC-PRD-001.SCHEMA.USER_FLOWS | B48: user_flows | C48: Definir, validar e manter: User Flows | E48: baixa
... A59: D10-DOC-PRD-001.SCHEMA.RELEASE_CRITERIA | B59: release_criteria | C59: Definir, validar e manter: Release Criteria | E59: baixa
A60: Domínio D11 — Experiência e Projeto
A61: Artefato D11-DOC-EEP-001 — Especificação de Experiência e Projeto
A62: D11-DOC-EEP-001.USER_RESEARCH.EVIDENCIAS | B62: evidencias | C62: Definir, validar e manter: Evidencias | E62: baixa
A63: D11-DOC-EEP-001.USER_RESEARCH.NECESSIDADES | B63: necessidades | C63: Definir, validar e manter: Necessidades | E63: baixa
A64: D11-DOC-EEP-001.PERSONAS.PERFIL | B64: perfil | C64: Definir, validar e manter: Perfil | E64: baixa
A65: D11-DOC-EEP-001.PERSONAS.CONTEXTO | B65: contexto | C65: Definir, validar e manter: Contexto | E65: baixa
A66: D11-DOC-EEP-001.JOURNEYS.ETAPA | B66: etapa | C66: Definir, validar e manter: Etapa | E66: baixa
A67: D11-DOC-EEP-001.JOURNEYS.ACAO | B67: acao | C67: Definir, validar e manter: Acao | E67: baixa
A68: D11-DOC-EEP-001.JOURNEYS.FRICCAO | B68: friccao | C68: Definir, validar e manter: Friccao | E68: baixa
A69: D11-DOC-EEP-001.INFORMATION_ARCHITECTURE.NAVEGACAO | B69: navegacao | C69: Definir, validar e manter: Navegacao | E69: baixa
A70: D11-DOC-EEP-001.INFORMATION_ARCHITECTURE.HIERARQUIA | B70: hierarquia | C70: Definir, validar e manter: Hierarquia | E70: baixa
A71: D11-DOC-EEP-001.FLOWS.ENTRADA | B71: entrada | C71: Definir, validar e manter: Entrada | E71: baixa
A72: D11-DOC-EEP-001.FLOWS.DECISAO | B72: decisao | C72: Definir, validar e manter: Decisao | E72: baixa
A73: D11-DOC-EEP-001.FLOWS.SAIDA | B73: saida | C73: Definir, validar e manter: Saida | E73: baixa
... A92: D11-DOC-EEP-001.VALIDATION.RESULTADO | B92: resultado | C92: Definir, validar e manter: Resultado | E92: baixa
A93: Artefato D11-DOC-DSI-001 — Sistema de Design e Interface
A94: D11-DOC-DSI-001.FOUNDATIONS.PRINCIPIOS | B94: principios | C94: Definir, validar e manter: Principios | E94: baixa
A95: D11-DOC-DSI-001.TOKENS.COR | B95: cor | C95: Definir, validar e manter: Cor | E95: baixa
A96: D11-DOC-DSI-001.TOKENS.TIPOGRAFIA | B96: tipografia | C96: Definir, validar e manter: Tipografia | E96: baixa
A97: D11-DOC-DSI-001.TOKENS.ESPACAMENTO | B97: espacamento | C97: Definir, validar e manter: Espacamento | E97: baixa
A98: D11-DOC-DSI-001.TOKENS.RAIO | B98: raio | C98: Definir, validar e manter: Raio | E98: baixa
A99: D11-DOC-DSI-001.TOKENS.SOMBRA | B99: sombra | C99: Definir, validar e manter: Sombra | E99: baixa
A100: D11-DOC-DSI-001.GRID.BREAKPOINTS | B100: breakpoints | C100: Definir, validar e manter: Breakpoints | E100: baixa
A101: D11-DOC-DSI-001.GRID.COLUNAS | B101: colunas | C101: Definir, validar e manter: Colunas | E101: baixa
A102: D11-DOC-DSI-001.COMPONENTS.COMPONENTE | B102: componente | C102: Definir, validar e manter: Componente | E102: baixa
A103: D11-DOC-DSI-001.COMPONENTS.VARIANTE | B103: variante | C103: Definir, validar e manter: Variante | E103: baixa
A104: D11-DOC-DSI-001.COMPONENTS.ESTADO | B104: estado | C104: Definir, validar e manter: Estado | E104: baixa
A105: D11-DOC-DSI-001.PATTERNS.NAVEGACAO | B105: navegacao | C105: Definir, validar e manter: Navegacao | E105: baixa
... A124: D11-DOC-DSI-001.ENGINEERING_HANDOFF.STORYBOOK | B124: storybook | C124: Definir, validar e manter: Storybook | E124: baixa

Sheet 01_Formulario_A03
F2: Progresso de preenchimento | G2: =COUNTA(D7:D6)&" / 0"
A4: A03 — Handoff Produto → Engenharia
A5: ID | B5: Campo | C5: O que preencher | D5: Resposta | E5: Exemplo (referência)

Sheet 01_Formulario_A04
F2: Progresso de preenchimento | G2: =COUNTA(D7:D56)&" / 48"
A4: A04 — Arquitetura, Engenharia e Implementação
A5: ID | B5: Campo | C5: O que preencher | D5: Resposta | E5: Exemplo (referência)
A6: Domínio D12 — Engenharia
A7: Artefato D12-DOC-ETE-001 — Especificação Técnica de Engenharia
A8: D12-DOC-ETE-001.ARCHITECTURE.VISAO_GERAL | B8: visao_geral | C8: Definir, validar e manter: Visao Geral | E8: baixa
A9: D12-DOC-ETE-001.ARCHITECTURE.DIAGRAMAS | B9: diagramas | C9: Definir, validar e manter: Diagramas | E9: baixa
A10: D12-DOC-ETE-001.REPOSITORIES.REPOSITORIO | B10: repositorio | C10: Definir, validar e manter: Repositorio | E10: baixa
A11: D12-DOC-ETE-001.REPOSITORIES.BRANCH | B11: branch | C11: Definir, validar e manter: Branch | E11: baixa
A12: D12-DOC-ETE-001.REPOSITORIES.FINALIDADE | B12: finalidade | C12: Definir, validar e manter: Finalidade | E12: baixa
A13: D12-DOC-ETE-001.STACK.FRAMEWORKS | B13: frameworks | C13: Definir, validar e manter: Frameworks | E13: alta
A14: D12-DOC-ETE-001.STACK.LINGUAGENS | B14: linguagens | C14: Definir, validar e manter: Linguagens | E14: baixa
A15: D12-DOC-ETE-001.STACK.RUNTIME | B15: runtime | C15: Definir, validar e manter: Runtime | E15: baixa
A16: D12-DOC-ETE-001.APPLICATIONS.APP | B16: app | C16: Definir, validar e manter: App | E16: baixa
A17: D12-DOC-ETE-001.APPLICATIONS.RESPONSABILIDADE | B17: responsabilidade | C17: Definir, validar e manter: Responsabilidade | E17: baixa
A18: D12-DOC-ETE-001.PACKAGES.PACKAGE | B18: package | C18: Definir, validar e manter: Package | E18: alta
A19: D12-DOC-ETE-001.PACKAGES.RESPONSABILIDADE | B19: responsabilidade | C19: Definir, validar e manter: Responsabilidade | E19: baixa
... A55: D12-DOC-ETE-001.ADR_LINKS.DECISOES_ARQUITETURAIS | B55: decisoes_arquiteturais | C55: Definir, validar e manter: Decisoes Arquiteturais | E55: alta

Sheet 01_Formulario_A05
F2: Progresso de preenchimento | G2: =COUNTA(D7:D52)&" / 43"
A4: A05 — Operações, Plataforma, Deploy e Segurança
A5: ID | B5: Campo | C5: O que preencher | D5: Resposta | E5: Exemplo (referência)
A6: Domínio D08 — Operações
A7: Artefato D08-DOC-MOP-001 — Manual de Operações
A8: D08-DOC-MOP-001.OPERATING_MODEL.SERVICOS | B8: servicos | C8: Definir, validar e manter: Servicos | E8: baixa
A9: D08-DOC-MOP-001.OPERATING_MODEL.PROCESSOS | B9: processos | C9: Definir, validar e manter: Processos | E9: alta
A10: D08-DOC-MOP-001.PROCESS_INVENTORY.PROCESSO | B10: processo | C10: Definir, validar e manter: Processo | E10: alta
A11: D08-DOC-MOP-001.PROCESS_INVENTORY.OBJETIVO | B11: objetivo | C11: Definir, validar e manter: Objetivo | E11: baixa
A12: D08-DOC-MOP-001.PROCESS_INVENTORY.OWNER | B12: owner | C12: Definir, validar e manter: Owner | E12: baixa
A13: D08-DOC-MOP-001.INPUTS.ENTRADA | B13: entrada | C13: Definir, validar e manter: Entrada | E13: baixa
A14: D08-DOC-MOP-001.INPUTS.ORIGEM | B14: origem | C14: Definir, validar e manter: Origem | E14: baixa
A15: D08-DOC-MOP-001.PROCEDURES.ETAPAS | B15: etapas | C15: Definir, validar e manter: Etapas | E15: baixa
A16: D08-DOC-MOP-001.PROCEDURES.REGRA | B16: regra | C16: Definir, validar e manter: Regra | E16: baixa
A17: D08-DOC-MOP-001.OUTPUTS.SAIDA | B17: saida | C17: Definir, validar e manter: Saida | E17: baixa
A18: D08-DOC-MOP-001.OUTPUTS.CONSUMIDOR | B18: consumidor | C18: Definir, validar e manter: Consumidor | E18: baixa
A19: D08-DOC-MOP-001.ROLES.EXECUTOR | B19: executor | C19: Definir, validar e manter: Executor | E19: baixa
... A34: D08-DOC-MOP-001.METRICS.QUALIDADE | B34: qualidade | C34: Definir, validar e manter: Qualidade | E34: alta
A35: Artefato D08-DOC-RUN-001 — Runbook Operacional do Ecossistema
A36: D08-DOC-RUN-001.SCHEMA.RUNBOOK_ID | B36: runbook_id | C36: Definir, validar e manter: Runbook ID | E36: baixa
A37: D08-DOC-RUN-001.SCHEMA.NOME | B37: nome | C37: Definir, validar e manter: Nome | E37: baixa
A38: D08-DOC-RUN-001.SCHEMA.OBJETIVO | B38: objetivo | C38: Definir, validar e manter: Objetivo | E38: baixa
A39: D08-DOC-RUN-001.SCHEMA.TRIGGER | B39: trigger | C39: Definir, validar e manter: Trigger | E39: baixa
A40: D08-DOC-RUN-001.SCHEMA.PRECONDICOES | B40: precondicoes | C40: Definir, validar e manter: Precondicoes | E40: baixa
A41: D08-DOC-RUN-001.SCHEMA.SISTEMAS | B41: sistemas | C41: Definir, validar e manter: Sistemas | E41: baixa
A42: D08-DOC-RUN-001.SCHEMA.CREDENCIAIS_NECESSARIAS | B42: credenciais_necessarias | C42: Definir, validar e manter: Credenciais Necessarias | E42: baixa
A43: D08-DOC-RUN-001.SCHEMA.PASSOS | B43: passos | C43: Definir, validar e manter: Passos | E43: baixa
A44: D08-DOC-RUN-001.SCHEMA.RESULTADO_ESPERADO | B44: resultado_esperado | C44: Definir, validar e manter: Resultado Esperado | E44: baixa
A45: D08-DOC-RUN-001.SCHEMA.VERIFICACAO | B45: verificacao | C45: Definir, validar e manter: Verificacao | E45: media
A46: D08-DOC-RUN-001.SCHEMA.EVIDENCIA | B46: evidencia | C46: Definir, validar e manter: Evidencia | E46: baixa
A47: D08-DOC-RUN-001.SCHEMA.EXCECOES | B47: excecoes | C47: Definir, validar e manter: Excecoes | E47: alta
... A51: D08-DOC-RUN-001.SCHEMA.FREQUENCIA | B51: frequencia | C51: Definir, validar e manter: Frequencia | E51: baixa

Sheet 01_Formulario_A06
F2: Progresso de preenchimento | G2: =COUNTA(D7:D157)&" / 142"
A4: A06 — Dados, Pesquisa e Conhecimento
A5: ID | B5: Campo | C5: O que preencher | D5: Resposta | E5: Exemplo (referência)
A6: Domínio D05 — Dados
A7: Artefato D05-DOC-EPGD-001 — Estratégia e Plano de Gestão de Dados
A8: D05-DOC-EPGD-001.DATA_DOMAINS.DOMINIO | B8: dominio | C8: Definir, validar e manter: Dominio | E8: baixa
A9: D05-DOC-EPGD-001.DATA_DOMAINS.DESCRICAO | B9: descricao | C9: Definir, validar e manter: Descricao | E9: baixa
A10: D05-DOC-EPGD-001.DATA_DOMAINS.OWNER | B10: owner | C10: Definir, validar e manter: Owner | E10: baixa
A11: D05-DOC-EPGD-001.SOURCES.FONTE | B11: fonte | C11: Definir, validar e manter: Fonte | E11: baixa
A12: D05-DOC-EPGD-001.SOURCES.SISTEMA | B12: sistema | C12: Definir, validar e manter: Sistema | E12: baixa
A13: D05-DOC-EPGD-001.SOURCES.ORIGEM | B13: origem | C13: Definir, validar e manter: Origem | E13: baixa
A14: D05-DOC-EPGD-001.INGESTION.METODO | B14: metodo | C14: Definir, validar e manter: Metodo | E14: baixa
A15: D05-DOC-EPGD-001.INGESTION.FREQUENCIA | B15: frequencia | C15: Definir, validar e manter: Frequencia | E15: baixa
A16: D05-DOC-EPGD-001.STORAGE.BANCO | B16: banco | C16: Definir, validar e manter: Banco | E16: baixa
A17: D05-DOC-EPGD-001.STORAGE.REPOSITORIO | B17: repositorio | C17: Definir, validar e manter: Repositorio | E17: baixa
A18: D05-DOC-EPGD-001.STORAGE.FORMATO | B18: formato | C18: Definir, validar e manter: Formato | E18: baixa
A19: D05-DOC-EPGD-001.SCHEMAS.SCHEMA | B19: schema | C19: Definir, validar e manter: Schema | E19: baixa
... A43: D05-DOC-EPGD-001.GOVERNANCE.APROVACAO | B43: aprovacao | C43: Definir, validar e manter: Aprovacao | E43: baixa
A44: Artefato D05-DOC-DCM-001 — Dicionário de Dados e Catálogo de Métricas
A45: D05-DOC-DCM-001.SCHEMA.METRIC_OR_FIELD_ID | B45: metric_or_field_id | C45: Definir, validar e manter: Metric Or Field ID | E45: baixa
A46: D05-DOC-DCM-001.SCHEMA.NOME | B46: nome | C46: Definir, validar e manter: Nome | E46: baixa
A47: D05-DOC-DCM-001.SCHEMA.TIPO | B47: tipo | C47: Definir, validar e manter: Tipo | E47: baixa
A48: D05-DOC-DCM-001.SCHEMA.DEFINICAO | B48: definicao | C48: Definir, validar e manter: Definicao | E48: baixa
A49: D05-DOC-DCM-001.SCHEMA.FORMULA | B49: formula | C49: Definir, validar e manter: Formula | E49: baixa
A50: D05-DOC-DCM-001.SCHEMA.UNIDADE | B50: unidade | C50: Definir, validar e manter: Unidade | E50: baixa
A51: D05-DOC-DCM-001.SCHEMA.GRANULARIDADE | B51: granularidade | C51: Definir, validar e manter: Granularidade | E51: baixa
A52: D05-DOC-DCM-001.SCHEMA.FONTE | B52: fonte | C52: Definir, validar e manter: Fonte | E52: baixa
A53: D05-DOC-DCM-001.SCHEMA.TABELA_DATASET | B53: tabela_dataset | C53: Definir, validar e manter: Tabela Dataset | E53: baixa
A54: D05-DOC-DCM-001.SCHEMA.CAMPO_EVENTO | B54: campo_evento | C54: Definir, validar e manter: Campo Evento | E54: baixa
A55: D05-DOC-DCM-001.SCHEMA.DIMENSOES | B55: dimensoes | C55: Definir, validar e manter: Dimensoes | E55: baixa
A56: D05-DOC-DCM-001.SCHEMA.OWNER | B56: owner | C56: Definir, validar e manter: Owner | E56: baixa
... A62: D05-DOC-DCM-001.SCHEMA.CONSUMIDORES | B62: consumidores | C62: Definir, validar e manter: Consumidores | E62: baixa
A63: Domínio D06 — Conhecimento e Busca Corporativa
A64: Artefato D06-DOC-EGC-001 — Estratégia de Gestão do Conhecimento
A65: D06-DOC-EGC-001.TAXONOMY.DOMINIOS | B65: dominios | C65: Definir, validar e manter: Dominios | E65: alta
A66: D06-DOC-EGC-001.TAXONOMY.SUBAREAS | B66: subareas | C66: Definir, validar e manter: Subareas | E66: baixa
A67: D06-DOC-EGC-001.TAXONOMY.CLASSES_DOCUMENTAIS | B67: classes_documentais | C67: Definir, validar e manter: Classes Documentais | E67: baixa
A68: D06-DOC-EGC-001.ONTOLOGY.OBJETOS | B68: objetos | C68: Definir, validar e manter: Objetos | E68: baixa
A69: D06-DOC-EGC-001.ONTOLOGY.RELACOES | B69: relacoes | C69: Definir, validar e manter: Relacoes | E69: baixa
A70: D06-DOC-EGC-001.REPOSITORIES.REPOSITORIO | B70: repositorio | C70: Definir, validar e manter: Repositorio | E70: baixa
A71: D06-DOC-EGC-001.REPOSITORIES.FINALIDADE | B71: finalidade | C71: Definir, validar e manter: Finalidade | E71: baixa
A72: D06-DOC-EGC-001.REPOSITORIES.OWNER | B72: owner | C72: Definir, validar e manter: Owner | E72: baixa
A73: D06-DOC-EGC-001.SOURCES_OF_TRUTH.OBJETO | B73: objeto | C73: Definir, validar e manter: Objeto | E73: alta
A74: D06-DOC-EGC-001.SOURCES_OF_TRUTH.FONTE_CANONICA | B74: fonte_canonica | C74: Definir, validar e manter: Fonte Canonica | E74: baixa
A75: D06-DOC-EGC-001.IDENTITY.PADRAO_DE_IDS | B75: padrao_de_ids | C75: Definir, validar e manter: Padrao De Ids | E75: alta
A76: D06-DOC-EGC-001.IDENTITY.NAMING | B76: naming | C76: Definir, validar e manter: Naming | E76: baixa
... A93: D06-DOC-EGC-001.GOVERNANCE.EVIDENCIA | B93: evidencia | C93: Definir, validar e manter: Evidencia | E93: baixa
A94: Artefato D06-DOC-RMI-001 — Registro Mestre de Identidades
A95: D06-DOC-RMI-001.SCHEMA.CANONICAL_ID | B95: canonical_id | C95: Definir, validar e manter: Canonical ID | E95: baixa
A96: D06-DOC-RMI-001.SCHEMA.OBJECT_TYPE | B96: object_type | C96: Definir, validar e manter: Object Type | E96: baixa
A97: D06-DOC-RMI-001.SCHEMA.DOMAIN_ID | B97: domain_id | C97: Definir, validar e manter: Domain ID | E97: baixa
A98: D06-DOC-RMI-001.SCHEMA.SUBAREA_ID | B98: subarea_id | C98: Definir, validar e manter: Subarea ID | E98: baixa
A99: D06-DOC-RMI-001.SCHEMA.PARENT_ID | B99: parent_id | C99: Definir, validar e manter: Parent ID | E99: baixa
A100: D06-DOC-RMI-001.SCHEMA.CANONICAL_NAME | B100: canonical_name | C100: Definir, validar e manter: Canonical Name | E100: baixa
A101: D06-DOC-RMI-001.SCHEMA.ALIASES | B101: aliases | C101: Definir, validar e manter: Aliases | E101: baixa
A102: D06-DOC-RMI-001.SCHEMA.VERSION | B102: version | C102: Definir, validar e manter: Version | E102: baixa
A103: D06-DOC-RMI-001.SCHEMA.STATUS | B103: status | C103: Definir, validar e manter: Status | E103: baixa
A104: D06-DOC-RMI-001.SCHEMA.OWNER | B104: owner | C104: Definir, validar e manter: Owner | E104: baixa
A105: D06-DOC-RMI-001.SCHEMA.SOURCE | B105: source | C105: Definir, validar e manter: Source | E105: baixa
A106: D06-DOC-RMI-001.SCHEMA.EVIDENCE | B106: evidence | C106: Definir, validar e manter: Evidence | E106: baixa
... A113: D06-DOC-RMI-001.SCHEMA.UPDATED_AT | B113: updated_at | C113: Definir, validar e manter: Updated At | E113: baixa
A114: Domínio D09 — Pesquisa e Inovação
A115: Artefato D09-DOC-PPE-001 — Plano de Pesquisa e Experimentação
A116: D09-DOC-PPE-001.QUESTION.PERGUNTA_DE_PESQUISA | B116: pergunta_de_pesquisa | C116: Definir, validar e manter: Pergunta De Pesquisa | E116: baixa
A117: D09-DOC-PPE-001.HYPOTHESIS.HIPOTESE | B117: hipotese | C117: Definir, validar e manter: Hipotese | E117: alta
A118: D09-DOC-PPE-001.HYPOTHESIS.PRESSUPOSTOS | B118: pressupostos | C118: Definir, validar e manter: Pressupostos | E118: baixa
A119: D09-DOC-PPE-001.EVIDENCE_REVIEW.FONTES_EXISTENTES | B119: fontes_existentes | C119: Definir, validar e manter: Fontes Existentes | E119: baixa
A120: D09-DOC-PPE-001.EVIDENCE_REVIEW.LACUNAS | B120: lacunas | C120: Definir, validar e manter: Lacunas | E120: baixa
A121: D09-DOC-PPE-001.METHOD.METODO | B121: metodo | C121: Definir, validar e manter: Metodo | E121: baixa
A122: D09-DOC-PPE-001.METHOD.DESENHO | B122: desenho | C122: Definir, validar e manter: Desenho | E122: baixa
A123: D09-DOC-PPE-001.POPULATION.PUBLICO | B123: publico | C123: Definir, validar e manter: Publico | E123: baixa
A124: D09-DOC-PPE-001.POPULATION.AMOSTRA | B124: amostra | C124: Definir, validar e manter: Amostra | E124: baixa
A125: D09-DOC-PPE-001.VARIABLES.INDEPENDENTE | B125: independente | C125: Definir, validar e manter: Independente | E125: baixa
A126: D09-DOC-PPE-001.VARIABLES.DEPENDENTE | B126: dependente | C126: Definir, validar e manter: Dependente | E126: baixa
A127: D09-DOC-PPE-001.VARIABLES.CONTROLE | B127: controle | C127: Definir, validar e manter: Controle | E127: baixa
... A139: D09-DOC-PPE-001.DECISION.DECISAO_DERIVADA | B139: decisao_derivada | C139: Definir, validar e manter: Decisao Derivada | E139: baixa
A140: Artefato D09-DOC-DEB-001 — Dossiê de Evidências e Base Científica
A141: D09-DOC-DEB-001.SCHEMA.CLAIM_ID | B141: claim_id | C141: Definir, validar e manter: Claim ID | E141: baixa
A142: D09-DOC-DEB-001.SCHEMA.CLAIM | B142: claim | C142: Definir, validar e manter: Claim | E142: alta
A143: D09-DOC-DEB-001.SCHEMA.DOMAIN | B143: domain | C143: Definir, validar e manter: Domain | E143: baixa
A144: D09-DOC-DEB-001.SCHEMA.EVIDENCE_CLASS | B144: evidence_class | C144: Definir, validar e manter: Evidence Class | E144: baixa
A145: D09-DOC-DEB-001.SCHEMA.SOURCE_ID | B145: source_id | C145: Definir, validar e manter: Source ID | E145: baixa
A146: D09-DOC-DEB-001.SCHEMA.SOURCE_TYPE | B146: source_type | C146: Definir, validar e manter: Source Type | E146: baixa
A147: D09-DOC-DEB-001.SCHEMA.CITATION | B147: citation | C147: Definir, validar e manter: Citation | E147: baixa
A148: D09-DOC-DEB-001.SCHEMA.LOCATOR | B148: locator | C148: Definir, validar e manter: Locator | E148: baixa
A149: D09-DOC-DEB-001.SCHEMA.PUBLICATION_DATE | B149: publication_date | C149: Definir, validar e manter: Publication Date | E149: baixa
A150: D09-DOC-DEB-001.SCHEMA.POPULATION | B150: population | C150: Definir, validar e manter: Population | E150: baixa
A151: D09-DOC-DEB-001.SCHEMA.FINDING | B151: finding | C151: Definir, validar e manter: Finding | E151: baixa
A152: D09-DOC-DEB-001.SCHEMA.LIMITATION | B152: limitation | C152: Definir, validar e manter: Limitation | E152: baixa
... A156: D09-DOC-DEB-001.SCHEMA.STATUS | B156: status | C156: Definir, validar e manter: Status | E156: baixa

Sheet 01_Formulario_A07
F2: Progresso de preenchimento | G2: =COUNTA(D7:D47)&" / 39"
A4: A07 — Corporativo e Suporte
A5: ID | B5: Campo | C5: O que preencher | D5: Resposta | E5: Exemplo (referência)
A6: Domínio D04 — Pessoas e Recursos Humanos
A7: Artefato D04-DOC-PPC-001 — Plano de Pessoas e Capacidade
A8: D04-DOC-PPC-001.ORGANIZATION.ESTRUTURA | B8: estrutura | C8: Definir, validar e manter: Estrutura | E8: baixa
A9: D04-DOC-PPC-001.ORGANIZATION.EQUIPES | B9: equipes | C9: Definir, validar e manter: Equipes | E9: baixa
A10: D04-DOC-PPC-001.ORGANIZATION.FUNCOES | B10: funcoes | C10: Definir, validar e manter: Funcoes | E10: baixa
A11: D04-DOC-PPC-001.ROLES.PAPEL | B11: papel | C11: Definir, validar e manter: Papel | E11: baixa
A12: D04-DOC-PPC-001.ROLES.RESPONSABILIDADES | B12: responsabilidades | C12: Definir, validar e manter: Responsabilidades | E12: baixa
A13: D04-DOC-PPC-001.ROLES.AUTORIDADE | B13: autoridade | C13: Definir, validar e manter: Autoridade | E13: baixa
A14: D04-DOC-PPC-001.RACI.ATIVIDADE | B14: atividade | C14: Definir, validar e manter: Atividade | E14: baixa
A15: D04-DOC-PPC-001.RACI.RESPONSAVEL | B15: responsavel | C15: Definir, validar e manter: Responsavel | E15: media
A16: D04-DOC-PPC-001.RACI.APROVADOR | B16: aprovador | C16: Definir, validar e manter: Aprovador | E16: media
A17: D04-DOC-PPC-001.RACI.CONSULTADO | B17: consultado | C17: Definir, validar e manter: Consultado | E17: media
A18: D04-DOC-PPC-001.RACI.INFORMADO | B18: informado | C18: Definir, validar e manter: Informado | E18: media
A19: D04-DOC-PPC-001.PEOPLE.PESSOA | B19: pessoa | C19: Definir, validar e manter: Pessoa | E19: media
... A46: D04-DOC-PPC-001.METRICS.GAPS | B46: gaps | C46: Definir, validar e manter: Gaps | E46: baixa

Sheet 01_Formulario_A08
F2: Progresso de preenchimento | G2: =COUNTA(D7:D44)&" / 36"
A4: A08 — Conteúdo, Comunicação e Growth
A5: ID | B5: Campo | C5: O que preencher | D5: Resposta | E5: Exemplo (referência)
A6: Domínio D16 — Mídias Sociais e Distribuição Digital (alias: Mídias Sociais e Estratégias)
A7: Artefato D16-DOC-PEM-001 — Plano Estratégico de Mídias Sociais
A8: D16-DOC-PEM-001.OBJECTIVES.OBJETIVOS | B8: objetivos | C8: Definir, validar e manter: Objetivos | E8: baixa
A9: D16-DOC-PEM-001.AUDIENCE.PUBLICOS | B9: publicos | C9: Definir, validar e manter: Publicos | E9: baixa
A10: D16-DOC-PEM-001.CHANNELS.CANAL | B10: canal | C10: Definir, validar e manter: Canal | E10: baixa
A11: D16-DOC-PEM-001.CHANNELS.FUNCAO | B11: funcao | C11: Definir, validar e manter: Funcao | E11: baixa
A12: D16-DOC-PEM-001.CONTENT_PILLARS.PILAR | B12: pilar | C12: Definir, validar e manter: Pilar | E12: alta
A13: D16-DOC-PEM-001.CONTENT_PILLARS.TESE | B13: tese | C13: Definir, validar e manter: Tese | E13: baixa
A14: D16-DOC-PEM-001.FORMATS.ARTIGO | B14: artigo | C14: Definir, validar e manter: Artigo | E14: baixa
A15: D16-DOC-PEM-001.FORMATS.VIDEO | B15: video | C15: Definir, validar e manter: Video | E15: baixa
A16: D16-DOC-PEM-001.FORMATS.CARROSSEL | B16: carrossel | C16: Definir, validar e manter: Carrossel | E16: baixa
A17: D16-DOC-PEM-001.FORMATS.STORY | B17: story | C17: Definir, validar e manter: Story | E17: baixa
A18: D16-DOC-PEM-001.FORMATS.NEWSLETTER | B18: newsletter | C18: Definir, validar e manter: Newsletter | E18: baixa
A19: D16-DOC-PEM-001.EDITORIAL_CALENDAR.DATA | B19: data | C19: Definir, validar e manter: Data | E19: baixa
... A43: D16-DOC-PEM-001.BRAND_COMPLIANCE.CLAIMS | B43: claims | C43: Definir, validar e manter: Claims | E43: baixa

Sheet 01_Formulario_A09
F2: Progresso de preenchimento | G2: =COUNTA(D7:D68)&" / 59"
A4: A09 — Execução e Planejamento do Trabalho
A5: ID | B5: Campo | C5: O que preencher | D5: Resposta | E5: Exemplo (referência)
A6: Domínio D07 — Produtividade e Execução
A7: Artefato D07-DOC-PEX-001 — Plano de Execução
A8: D07-DOC-PEX-001.OBJECTIVES.OBJETIVO | B8: objetivo | C8: Definir, validar e manter: Objetivo | E8: baixa
A9: D07-DOC-PEX-001.OBJECTIVES.RESULTADO | B9: resultado | C9: Definir, validar e manter: Resultado | E9: baixa
A10: D07-DOC-PEX-001.DELIVERABLES.ENTREGAVEL | B10: entregavel | C10: Definir, validar e manter: Entregavel | E10: baixa
A11: D07-DOC-PEX-001.DELIVERABLES.DOD | B11: dod | C11: Definir, validar e manter: Dod | E11: baixa
A12: D07-DOC-PEX-001.DELIVERABLES.EVIDENCIA | B12: evidencia | C12: Definir, validar e manter: Evidencia | E12: baixa
A13: D07-DOC-PEX-001.PORTFOLIO.PROJETO | B13: projeto | C13: Definir, validar e manter: Projeto | E13: baixa
A14: D07-DOC-PEX-001.PORTFOLIO.PRIORIDADE | B14: prioridade | C14: Definir, validar e manter: Prioridade | E14: media
A15: D07-DOC-PEX-001.PORTFOLIO.ESTADO | B15: estado | C15: Definir, validar e manter: Estado | E15: baixa
A16: D07-DOC-PEX-001.DEPENDENCIES.UPSTREAM | B16: upstream | C16: Definir, validar e manter: Upstream | E16: baixa
A17: D07-DOC-PEX-001.DEPENDENCIES.DOWNSTREAM | B17: downstream | C17: Definir, validar e manter: Downstream | E17: baixa
A18: D07-DOC-PEX-001.CAPACITY.CAPACIDADE_BRUTA | B18: capacidade_bruta | C18: Definir, validar e manter: Capacidade Bruta | E18: alta
A19: D07-DOC-PEX-001.CAPACITY.FIXA | B19: fixa | C19: Definir, validar e manter: Fixa | E19: baixa
... A39: D07-DOC-PEX-001.PROGRESS.RESTANTE | B39: restante | C39: Definir, validar e manter: Restante | E39: baixa
A40: Artefato D07-DOC-PIM-001 — Plano de Implementação e Marcos
A41: D07-DOC-PIM-001.IMPLEMENTATION_STRATEGY.ABORDAGEM | B41: abordagem | C41: Definir, validar e manter: Abordagem | E41: baixa
A42: D07-DOC-PIM-001.IMPLEMENTATION_STRATEGY.ONDAS | B42: ondas | C42: Definir, validar e manter: Ondas | E42: baixa
A43: D07-DOC-PIM-001.MILESTONES.MARCO | B43: marco | C43: Definir, validar e manter: Marco | E43: alta
A44: D07-DOC-PIM-001.MILESTONES.RESULTADO | B44: resultado | C44: Definir, validar e manter: Resultado | E44: baixa
A45: D07-DOC-PIM-001.MILESTONES.CRITERIO | B45: criterio | C45: Definir, validar e manter: Criterio | E45: baixa
A46: D07-DOC-PIM-001.WORK_PACKAGES.PACOTE | B46: pacote | C46: Definir, validar e manter: Pacote | E46: baixa
A47: D07-DOC-PIM-001.WORK_PACKAGES.ENTREGAVEL | B47: entregavel | C47: Definir, validar e manter: Entregavel | E47: baixa
A48: D07-DOC-PIM-001.DEPENDENCIES.DEPENDENCIA | B48: dependencia | C48: Definir, validar e manter: Dependencia | E48: baixa
A49: D07-DOC-PIM-001.DEPENDENCIES.PRECONDICAO | B49: precondicao | C49: Definir, validar e manter: Precondicao | E49: baixa
A50: D07-DOC-PIM-001.RESOURCES.PESSOA | B50: pessoa | C50: Definir, validar e manter: Pessoa | E50: baixa
A51: D07-DOC-PIM-001.RESOURCES.SISTEMA | B51: sistema | C51: Definir, validar e manter: Sistema | E51: baixa
A52: D07-DOC-PIM-001.RESOURCES.RECURSO | B52: recurso | C52: Definir, validar e manter: Recurso | E52: baixa
... A67: D07-DOC-PIM-001.ROLLBACK.PROCEDIMENTO | B67: procedimento | C67: Definir, validar e manter: Procedimento | E67: baixa

Sheet 01_Formulario_A10
F2: Progresso de preenchimento | G2: =COUNTA(D7:D105)&" / 93"
A4: A10 — Documentação e Governança do Conhecimento
A5: ID | B5: Campo | C5: O que preencher | D5: Resposta | E5: Exemplo (referência)
A6: Domínio D21 — Workbook
A7: Artefato D21-DOC-PWB-001 — Plano de Workbooks
A8: D21-DOC-PWB-001.WORKBOOK_CATALOG.WORKBOOK_ID | B8: workbook_id | C8: Definir, validar e manter: Workbook ID | E8: alta
A9: D21-DOC-PWB-001.WORKBOOK_CATALOG.NOME | B9: nome | C9: Definir, validar e manter: Nome | E9: baixa
A10: D21-DOC-PWB-001.PURPOSE.OBJETIVO | B10: objetivo | C10: Definir, validar e manter: Objetivo | E10: baixa
A11: D21-DOC-PWB-001.PURPOSE.USUARIO | B11: usuario | C11: Definir, validar e manter: Usuario | E11: baixa
A12: D21-DOC-PWB-001.SOURCE_DATA.FONTE | B12: fonte | C12: Definir, validar e manter: Fonte | E12: baixa
A13: D21-DOC-PWB-001.SOURCE_DATA.ATUALIZACAO | B13: atualizacao | C13: Definir, validar e manter: Atualizacao | E13: baixa
A14: D21-DOC-PWB-001.SHEETS.ABA | B14: aba | C14: Definir, validar e manter: Aba | E14: baixa
A15: D21-DOC-PWB-001.SHEETS.FINALIDADE | B15: finalidade | C15: Definir, validar e manter: Finalidade | E15: baixa
A16: D21-DOC-PWB-001.FIELDS.CAMPO | B16: campo | C16: Definir, validar e manter: Campo | E16: baixa
A17: D21-DOC-PWB-001.FIELDS.DEFINICAO | B17: definicao | C17: Definir, validar e manter: Definicao | E17: baixa
A18: D21-DOC-PWB-001.FORMULAS.FORMULA | B18: formula | C18: Definir, validar e manter: Formula | E18: baixa
A19: D21-DOC-PWB-001.FORMULAS.LOGICA | B19: logica | C19: Definir, validar e manter: Logica | E19: baixa
... A37: D21-DOC-PWB-001.EVIDENCE.RASTREABILIDADE | B37: rastreabilidade | C37: Definir, validar e manter: Rastreabilidade | E37: baixa
A38: Domínio D22 — Decision and Register Log
A39: Artefato D22-DOC-DRL-001 — Decision and Register Log do Ecossistema
A40: D22-DOC-DRL-001.SCHEMA.DECISION_ID | B40: decision_id | C40: Definir, validar e manter: Decision ID | E40: baixa
A41: D22-DOC-DRL-001.SCHEMA.TITLE | B41: title | C41: Definir, validar e manter: Title | E41: baixa
A42: D22-DOC-DRL-001.SCHEMA.DOMAIN | B42: domain | C42: Definir, validar e manter: Domain | E42: baixa
A43: D22-DOC-DRL-001.SCHEMA.CONTEXT | B43: context | C43: Definir, validar e manter: Context | E43: baixa
A44: D22-DOC-DRL-001.SCHEMA.PROBLEM | B44: problem | C44: Definir, validar e manter: Problem | E44: baixa
A45: D22-DOC-DRL-001.SCHEMA.DECISION_REQUIRED | B45: decision_required | C45: Definir, validar e manter: Decision Required | E45: baixa
A46: D22-DOC-DRL-001.SCHEMA.OPTIONS_CONSIDERED | B46: options_considered | C46: Definir, validar e manter: Options Considered | E46: baixa
A47: D22-DOC-DRL-001.SCHEMA.EVALUATION_CRITERIA | B47: evaluation_criteria | C47: Definir, validar e manter: Evaluation Criteria | E47: baixa
A48: D22-DOC-DRL-001.SCHEMA.SELECTED_OPTION | B48: selected_option | C48: Definir, validar e manter: Selected Option | E48: baixa
A49: D22-DOC-DRL-001.SCHEMA.RATIONALE | B49: rationale | C49: Definir, validar e manter: Rationale | E49: baixa
A50: D22-DOC-DRL-001.SCHEMA.EVIDENCE | B50: evidence | C50: Definir, validar e manter: Evidence | E50: baixa
A51: D22-DOC-DRL-001.SCHEMA.OWNER | B51: owner | C51: Definir, validar e manter: Owner | E51: baixa
... A62: D22-DOC-DRL-001.SCHEMA.SUPERSEDED_BY | B62: superseded_by | C62: Definir, validar e manter: Superseded By | E62: baixa
A63: Domínio D23 — Blueprints
A64: Artefato D23-DOC-PBL-001 — Plano de Blueprints
A65: D23-DOC-PBL-001.BLUEPRINT_CATALOG.BLUEPRINT_ID | B65: blueprint_id | C65: Definir, validar e manter: Blueprint ID | E65: baixa
A66: D23-DOC-PBL-001.BLUEPRINT_CATALOG.NOME | B66: nome | C66: Definir, validar e manter: Nome | E66: baixa
A67: D23-DOC-PBL-001.BLUEPRINT_CATALOG.DOMINIO | B67: dominio | C67: Definir, validar e manter: Dominio | E67: baixa
A68: D23-DOC-PBL-001.PROBLEM.PROBLEMA | B68: problema | C68: Definir, validar e manter: Problema | E68: baixa
A69: D23-DOC-PBL-001.PROBLEM.EVIDENCIA | B69: evidencia | C69: Definir, validar e manter: Evidencia | E69: baixa
A70: D23-DOC-PBL-001.OBJECTIVE.RESULTADO_ESPERADO | B70: resultado_esperado | C70: Definir, validar e manter: Resultado Esperado | E70: baixa
A71: D23-DOC-PBL-001.SCOPE.INCLUIDO | B71: incluido | C71: Definir, validar e manter: Incluido | E71: baixa
A72: D23-DOC-PBL-001.SCOPE.EXCLUIDO | B72: excluido | C72: Definir, validar e manter: Excluido | E72: baixa
A73: D23-DOC-PBL-001.ARCHITECTURE.COMPONENTES | B73: componentes | C73: Definir, validar e manter: Componentes | E73: baixa
A74: D23-DOC-PBL-001.ARCHITECTURE.RELACOES | B74: relacoes | C74: Definir, validar e manter: Relacoes | E74: baixa
A75: D23-DOC-PBL-001.WORKFLOW.ENTRADA | B75: entrada | C75: Definir, validar e manter: Entrada | E75: baixa
A76: D23-DOC-PBL-001.WORKFLOW.ETAPAS | B76: etapas | C76: Definir, validar e manter: Etapas | E76: baixa
... A104: D23-DOC-PBL-001.EVIDENCE.REGISTROS | B104: registros | C104: Definir, validar e manter: Registros | E104: baixa

Sheet 01_Formulario_A11
F2: Progresso de preenchimento | G2: =COUNTA(D7:D86)&" / 76"
A4: A11 — Ferramentas, IA e Ativos Reutilizáveis
A5: ID | B5: Campo | C5: O que preencher | D5: Resposta | E5: Exemplo (referência)
A6: Domínio D19 — Assets e CTAs
A7: Artefato D19-DOC-PAC-001 — Plano de Assets e CTAs
A8: D19-DOC-PAC-001.ASSET_INVENTORY.ASSET_ID | B8: asset_id | C8: Definir, validar e manter: Asset ID | E8: baixa
A9: D19-DOC-PAC-001.ASSET_INVENTORY.NOME | B9: nome | C9: Definir, validar e manter: Nome | E9: baixa
A10: D19-DOC-PAC-001.ASSET_INVENTORY.TIPO | B10: tipo | C10: Definir, validar e manter: Tipo | E10: alta
A11: D19-DOC-PAC-001.PURPOSE.OBJETIVO | B11: objetivo | C11: Definir, validar e manter: Objetivo | E11: baixa
A12: D19-DOC-PAC-001.PURPOSE.CAMPANHA | B12: campanha | C12: Definir, validar e manter: Campanha | E12: baixa
A13: D19-DOC-PAC-001.PURPOSE.PRODUTO | B13: produto | C13: Definir, validar e manter: Produto | E13: baixa
A14: D19-DOC-PAC-001.SOURCE.ORIGEM | B14: origem | C14: Definir, validar e manter: Origem | E14: baixa
A15: D19-DOC-PAC-001.SOURCE.DOCUMENTO_FONTE | B15: documento_fonte | C15: Definir, validar e manter: Documento Fonte | E15: baixa
A16: D19-DOC-PAC-001.FORMAT.ARQUIVO | B16: arquivo | C16: Definir, validar e manter: Arquivo | E16: baixa
A17: D19-DOC-PAC-001.FORMAT.DIMENSAO | B17: dimensao | C17: Definir, validar e manter: Dimensao | E17: baixa
A18: D19-DOC-PAC-001.FORMAT.CANAL | B18: canal | C18: Definir, validar e manter: Canal | E18: baixa
A19: D19-DOC-PAC-001.CONTENT.HEADLINE | B19: headline | C19: Definir, validar e manter: Headline | E19: baixa
... A44: D19-DOC-PAC-001.REUSE.DERIVADOS | B44: derivados | C44: Definir, validar e manter: Derivados | E44: baixa
A45: Domínio D20 — Plataformas e Repositórios
A46: Artefato D20-DOC-PPR-001 — Plano de Plataformas e Repositórios
A47: D20-DOC-PPR-001.SYSTEMS.PLATAFORMA | B47: plataforma | C47: Definir, validar e manter: Plataforma | E47: alta
A48: D20-DOC-PPR-001.SYSTEMS.FINALIDADE | B48: finalidade | C48: Definir, validar e manter: Finalidade | E48: baixa
A49: D20-DOC-PPR-001.ACCOUNTS.CONTA | B49: conta | C49: Definir, validar e manter: Conta | E49: baixa
A50: D20-DOC-PPR-001.ACCOUNTS.ORGANIZACAO | B50: organizacao | C50: Definir, validar e manter: Organizacao | E50: baixa
A51: D20-DOC-PPR-001.REPOSITORIES.REPO | B51: repo | C51: Definir, validar e manter: Repo | E51: baixa
A52: D20-DOC-PPR-001.REPOSITORIES.OWNER | B52: owner | C52: Definir, validar e manter: Owner | E52: baixa
A53: D20-DOC-PPR-001.REPOSITORIES.FINALIDADE | B53: finalidade | C53: Definir, validar e manter: Finalidade | E53: baixa
A54: D20-DOC-PPR-001.BRANCHES.BRANCH | B54: branch | C54: Definir, validar e manter: Branch | E54: baixa
A55: D20-DOC-PPR-001.BRANCHES.FUNCAO | B55: funcao | C55: Definir, validar e manter: Funcao | E55: baixa
A56: D20-DOC-PPR-001.BRANCHES.PROTECAO | B56: protecao | C56: Definir, validar e manter: Protecao | E56: baixa
A57: D20-DOC-PPR-001.DIRECTORIES.PATH | B57: path | C57: Definir, validar e manter: Path | E57: baixa
A58: D20-DOC-PPR-001.DIRECTORIES.RESPONSABILIDADE | B58: responsabilidade | C58: Definir, validar e manter: Responsabilidade | E58: baixa
... A85: D20-DOC-PPR-001.MAINTENANCE.OWNER | B85: owner | C85: Definir, validar e manter: Owner | E85: baixa

Sheet 01_Formulario_A12
F2: Progresso de preenchimento | G2: =COUNTA(D7:D47)&" / 39"
A4: A12 — Stakeholders e Ecossistema
A5: ID | B5: Campo | C5: O que preencher | D5: Resposta | E5: Exemplo (referência)
A6: Domínio D17 — Emprego e Portfólio
A7: Artefato D17-DOC-PEP-001 — Plano de Emprego e Portfólio
A8: D17-DOC-PEP-001.OBJECTIVE.OBJETIVO_PROFISSIONAL | B8: objetivo_profissional | C8: Definir, validar e manter: Objetivo Profissional | E8: baixa
A9: D17-DOC-PEP-001.OBJECTIVE.HORIZONTE | B9: horizonte | C9: Definir, validar e manter: Horizonte | E9: baixa
A10: D17-DOC-PEP-001.POSITIONING.PROPOSTA_PROFISSIONAL | B10: proposta_profissional | C10: Definir, validar e manter: Proposta Profissional | E10: baixa
A11: D17-DOC-PEP-001.POSITIONING.ESPECIALIDADES | B11: especialidades | C11: Definir, validar e manter: Especialidades | E11: baixa
A12: D17-DOC-PEP-001.TARGET.CARGOS | B12: cargos | C12: Definir, validar e manter: Cargos | E12: baixa
A13: D17-DOC-PEP-001.TARGET.EMPRESAS | B13: empresas | C13: Definir, validar e manter: Empresas | E13: baixa
A14: D17-DOC-PEP-001.TARGET.CLIENTES | B14: clientes | C14: Definir, validar e manter: Clientes | E14: baixa
A15: D17-DOC-PEP-001.TARGET.MERCADOS | B15: mercados | C15: Definir, validar e manter: Mercados | E15: baixa
A16: D17-DOC-PEP-001.COMPETENCIES.COMPETENCIAS | B16: competencias | C16: Definir, validar e manter: Competencias | E16: baixa
A17: D17-DOC-PEP-001.COMPETENCIES.NIVEL | B17: nivel | C17: Definir, validar e manter: Nivel | E17: baixa
A18: D17-DOC-PEP-001.COMPETENCIES.EVIDENCIA | B18: evidencia | C18: Definir, validar e manter: Evidencia | E18: baixa
A19: D17-DOC-PEP-001.GAPS.LACUNA | B19: lacuna | C19: Definir, validar e manter: Lacuna | E19: baixa
... A46: D17-DOC-PEP-001.METRICS.CONVERSAO | B46: conversao | C46: Definir, validar e manter: Conversao | E46: baixa

Sheet 02_Visao_Programa
B2: Visão Programa — EXECUTAR
B4: Macroáreas | C4: =COUNTA('10_REG_Macroareas'!A2:A1000)
B5: Domínios | C5: =COUNTA('11_REG_Dominios'!A2:A1000)
B6: Itens de Portfólio | C6: =COUNTA('12_REG_Portfolio'!A2:A1000)
B7: Templates | C7: =COUNTA('13_REG_Templates'!A2:A1000)
B8: Artefatos | C8: =COUNTA('14_REG_Artefatos'!A2:A1000)
B9: Campos | C9: =COUNTA('15_REG_Campos'!A2:A2000)
B10: Dependências registradas | C10: =COUNTA('16_REG_Dependencias'!A2:A1000)
B11: Gates | C11: =COUNTA('17_REG_Gates'!A2:A1000)
B12: Gaps abertos | C12: =COUNTIFS('21_REG_Gaps'!E2:E1000,"OPEN")
B13: Conflitos abertos | C13: =COUNTIFS('22_REG_Conflitos'!H2:H1000,"ABERTO")

Sheet 03_Visao_Macroareas
B2: Visão Macroáreas — espelho narrativo (não editar; ver 01_Formulario_*)
A4: A00 — Governança, Estratégia e Gestão
A5: D01-DOC-DDE-001.IDENTITY.NOME_DO_ECOSSISTEMA | B5: nome_do_ecossistema | C5: =IFERROR(IF(INDEX('01_Formulario_A00'!$D:$D,MATCH("D01-DOC-DDE-001.IDENTITY.NOME_DO_ECOSSISTEMA",'01_Formulario_A00'!$A:$A,0))="","— (a preencher em 01_Formulario_A00)",INDEX('01_Formulario_A00'!$D:$D,MATCH("D01-DOC-DDE-001.IDENTITY.NOME_DO_ECOSSISTEMA",'01_Formulario_A00'!$A:$A,0))),"— (a preencher em 01_Formulario_A00)")
A6: D01-DOC-DDE-001.IDENTITY.DESCRICAO_EXECUTIVA | B6: descricao_executiva | C6: =IFERROR(IF(INDEX('01_Formulario_A00'!$D:$D,MATCH("D01-DOC-DDE-001.IDENTITY.DESCRICAO_EXECUTIVA",'01_Formulario_A00'!$A:$A,0))="","— (a preencher em 01_Formulario_A00)",INDEX('01_Formulario_A00'!$D:$D,MATCH("D01-DOC-DDE-001.IDENTITY.DESCRICAO_EXECUTIVA",'01_Formulario_A00'!$A:$A,0))),"— (a preencher em 01_Formulario_A00)")
A7: D01-DOC-DDE-001.IDENTITY.CONTEXTO | B7: contexto | C7: =IFERROR(IF(INDEX('01_Formulario_A00'!$D:$D,MATCH("D01-DOC-DDE-001.IDENTITY.CONTEXTO",'01_Formulario_A00'!$A:$A,0))="","— (a preencher em 01_Formulario_A00)",INDEX('01_Formulario_A00'!$D:$D,MATCH("D01-DOC-DDE-001.IDENTITY.CONTEXTO",'01_Formulario_A00'!$A:$A,0))),"— (a preencher em 01_Formulario_A00)")
A8: D01-DOC-DDE-001.IDENTITY.RAZAO_DE_EXISTENCIA | B8: razao_de_existencia | C8: =IFERROR(IF(INDEX('01_Formulario_A00'!$D:$D,MATCH("D01-DOC-DDE-001.IDENTITY.RAZAO_DE_EXISTENCIA",'01_Formulario_A00'!$A:$A,0))="","— (a preencher em 01_Formulario_A00)",INDEX('01_Formulario_A00'!$D:$D,MATCH("D01-DOC-DDE-001.IDENTITY.RAZAO_DE_EXISTENCIA",'01_Formulario_A00'!$A:$A,0))),"— (a preencher em 01_Formulario_A00)")
A9: D01-DOC-DDE-001.IDENTITY.FASE_ATUAL | B9: fase_atual | C9: =IFERROR(IF(INDEX('01_Formulario_A00'!$D:$D,MATCH("D01-DOC-DDE-001.IDENTITY.FASE_ATUAL",'01_Formulario_A00'!$A:$A,0))="","— (a preencher em 01_Formulario_A00)",INDEX('01_Formulario_A00'!$D:$D,MATCH("D01-DOC-DDE-001.IDENTITY.FASE_ATUAL",'01_Formulario_A00'!$A:$A,0))),"— (a preencher em 01_Formulario_A00)")
A10: D01-DOC-DDE-001.PROBLEM_AND_OPPORTUNITY.PROBLEMA_CENTRAL | B10: problema_central | C10: =IFERROR(IF(INDEX('01_Formulario_A00'!$D:$D,MATCH("D01-DOC-DDE-001.PROBLEM_AND_OPPORTUNITY.PROBLEMA_CENTRAL",'01_Formulario_A00'!$A:$A,0))="","— (a preencher em 01_Formulario_A00)",INDEX('01_Formulario_A00'!$D:$D,MATCH("D01-DOC-DDE-001.PROBLEM_AND_OPPORTUNITY.PROBLEMA_CENTRAL",'01_Formulario_A00'!$A:$A,0))),"— (a preencher em 01_Formulario_A00)")
A11: D01-DOC-DDE-001.PROBLEM_AND_OPPORTUNITY.PROBLEMAS_SECUNDARIOS | B11: problemas_secundarios | C11: =IFERROR(IF(INDEX('01_Formulario_A00'!$D:$D,MATCH("D01-DOC-DDE-001.PROBLEM_AND_OPPORTUNITY.PROBLEMAS_SECUNDARIOS",'01_Formulario_A00'!$A:$A,0))="","— (a preencher em 01_Formulario_A00)",INDEX('01_Formulario_A00'!$D:$D,MATCH("D01-DOC-DDE-001.PROBLEM_AND_OPPORTUNITY.PROBLEMAS_SECUNDARIOS",'01_Formulario_A00'!$A:$A,0))),"— (a preencher em 01_Formulario_A00)")
A12: D01-DOC-DDE-001.PROBLEM_AND_OPPORTUNITY.OPORTUNIDADE | B12: oportunidade | C12: =IFERROR(IF(INDEX('01_Formulario_A00'!$D:$D,MATCH("D01-DOC-DDE-001.PROBLEM_AND_OPPORTUNITY.OPORTUNIDADE",'01_Formulario_A00'!$A:$A,0))="","— (a preencher em 01_Formulario_A00)",INDEX('01_Formulario_A00'!$D:$D,MATCH("D01-DOC-DDE-001.PROBLEM_AND_OPPORTUNITY.OPORTUNIDADE",'01_Formulario_A00'!$A:$A,0))),"— (a preencher em 01_Formulario_A00)")
A13: D01-DOC-DDE-001.PROBLEM_AND_OPPORTUNITY.EVIDENCIAS_DO_PROBLEMA | B13: evidencias_do_problema | C13: =IFERROR(IF(INDEX('01_Formulario_A00'!$D:$D,MATCH("D01-DOC-DDE-001.PROBLEM_AND_OPPORTUNITY.EVIDENCIAS_DO_PROBLEMA",'01_Formulario_A00'!$A:$A,0))="","— (a preencher em 01_Formulario_A00)",INDEX('01_Formulario_A00'!$D:$D,MATCH("D01-DOC-DDE-001.PROBLEM_AND_OPPORTUNITY.EVIDENCIAS_DO_PROBLEMA",'01_Formulario_A00'!$A:$A,0))),"— (a preencher em 01_Formulario_A00)")
A14: D01-DOC-DDE-001.PURPOSE.PROPOSITO | B14: proposito | C14: =IFERROR(IF(INDEX('01_Formulario_A00'!$D:$D,MATCH("D01-DOC-DDE-001.PURPOSE.PROPOSITO",'01_Formulario_A00'!$A:$A,0))="","— (a preencher em 01_Formulario_A00)",INDEX('01_Formulario_A00'!$D:$D,MATCH("D01-DOC-DDE-001.PURPOSE.PROPOSITO",'01_Formulario_A00'!$A:$A,0))),"— (a preencher em 01_Formulario_A00)")
A15: D01-DOC-DDE-001.PURPOSE.MISSAO | B15: missao | C15: =IFERROR(IF(INDEX('01_Formulario_A00'!$D:$D,MATCH("D01-DOC-DDE-001.PURPOSE.MISSAO",'01_Formulario_A00'!$A:$A,0))="","— (a preencher em 01_Formulario_A00)",INDEX('01_Formulario_A00'!$D:$D,MATCH("D01-DOC-DDE-001.PURPOSE.MISSAO",'01_Formulario_A00'!$A:$A,0))),"— (a preencher em 01_Formulario_A00)")
A16: D01-DOC-DDE-001.PURPOSE.VISAO | B16: visao | C16: =IFERROR(IF(INDEX('01_Formulario_A00'!$D:$D,MATCH("D01-DOC-DDE-001.PURPOSE.VISAO",'01_Formulario_A00'!$A:$A,0))="","— (a preencher em 01_Formulario_A00)",INDEX('01_Formulario_A00'!$D:$D,MATCH("D01-DOC-DDE-001.PURPOSE.VISAO",'01_Formulario_A00'!$A:$A,0))),"— (a preencher em 01_Formulario_A00)")
A17: D01-DOC-DDE-001.PURPOSE.PRINCIPIOS | B17: principios | C17: =IFERROR(IF(INDEX('01_Formulario_A00'!$D:$D,MATCH("D01-DOC-DDE-001.PURPOSE.PRINCIPIOS",'01_Formulario_A00'!$A:$A,0))="","— (a preencher em 01_Formulario_A00)",INDEX('01_Formulario_A00'!$D:$D,MATCH("D01-DOC-DDE-001.PURPOSE.PRINCIPIOS",'01_Formulario_A00'!$A:$A,0))),"— (a preencher em 01_Formulario_A00)")
A18: D01-DOC-DDE-001.PURPOSE.VALORES | B18: valores | C18: =IFERROR(IF(INDEX('01_Formulario_A00'!$D:$D,MATCH("D01-DOC-DDE-001.PURPOSE.VALORES",'01_Formulario_A00'!$A:$A,0))="","— (a preencher em 01_Formulario_A00)",INDEX('01_Formulario_A00'!$D:$D,MATCH("D01-DOC-DDE-001.PURPOSE.VALORES",'01_Formulario_A00'!$A:$A,0))),"— (a preencher em 01_Formulario_A00)")
A19: D01-DOC-DDE-001.STRATEGIC_DIRECTION.OBJETIVOS_ESTRATEGICOS | B19: objetivos_estrategicos | C19: =IFERROR(IF(INDEX('01_Formulario_A00'!$D:$D,MATCH("D01-DOC-DDE-001.STRATEGIC_DIRECTION.OBJETIVOS_ESTRATEGICOS",'01_Formulario_A00'!$A:$A,0))="","— (a preencher em 01_Formulario_A00)",INDEX('01_Formulario_A00'!$D:$D,MATCH("D01-DOC-DDE-001.STRATEGIC_DIRECTION.OBJETIVOS_ESTRATEGICOS",'01_Formulario_A00'!$A:$A,0))),"— (a preencher em 01_Formulario_A00)")
A20: D01-DOC-DDE-001.STRATEGIC_DIRECTION.RESULTADOS_ESPERADOS | B20: resultados_esperados | C20: =IFERROR(IF(INDEX('01_Formulario_A00'!$D:$D,MATCH("D01-DOC-DDE-001.STRATEGIC_DIRECTION.RESULTADOS_ESPERADOS",'01_Formulario_A00'!$A:$A,0))="","— (a preencher em 01_Formulario_A00)",INDEX('01_Formulario_A00'!$D:$D,MATCH("D01-DOC-DDE-001.STRATEGIC_DIRECTION.RESULTADOS_ESPERADOS",'01_Formulario_A00'!$A:$A,0))),"— (a preencher em 01_Formulario_A00)")
A21: D01-DOC-DDE-001.STRATEGIC_DIRECTION.PRIORIDADES | B21: prioridades | C21: =IFERROR(IF(INDEX('01_Formulario_A00'!$D:$D,MATCH("D01-DOC-DDE-001.STRATEGIC_DIRECTION.PRIORIDADES",'01_Formulario_A00'!$A:$A,0))="","— (a preencher em 01_Formulario_A00)",INDEX('01_Formulario_A00'!$D:$D,MATCH("D01-DOC-DDE-001.STRATEGIC_DIRECTION.PRIORIDADES",'01_Formulario_A00'!$A:$A,0))),"— (a preencher em 01_Formulario_A00)")
A22: D01-DOC-DDE-001.STRATEGIC_DIRECTION.NAO_OBJETIVOS | B22: nao_objetivos | C22: =IFERROR(IF(INDEX('01_Formulario_A00'!$D:$D,MATCH("D01-DOC-DDE-001.STRATEGIC_DIRECTION.NAO_OBJETIVOS",'01_Formulario_A00'!$A:$A,0))="","— (a preencher em 01_Formulario_A00)",INDEX('01_Formulario_A00'!$D:$D,MATCH("D01-DOC-DDE-001.STRATEGIC_DIRECTION.NAO_OBJETIVOS",'01_Formulario_A00'!$A:$A,0))),"— (a preencher em 01_Formulario_A00)")
A23: D01-DOC-DDE-001.STRATEGIC_DIRECTION.HORIZONTE_TEMPORAL | B23: horizonte_temporal | C23: =IFERROR(IF(INDEX('01_Formulario_A00'!$D:$D,MATCH("D01-DOC-DDE-001.STRATEGIC_DIRECTION.HORIZONTE_TEMPORAL",'01_Formulario_A00'!$A:$A,0))="","— (a preencher em 01_Formulario_A00)",INDEX('01_Formulario_A00'!$D:$D,MATCH("D01-DOC-DDE-001.STRATEGIC_DIRECTION.HORIZONTE_TEMPORAL",'01_Formulario_A00'!$A:$A,0))),"— (a preencher em 01_Formulario_A00)")
A24: D01-DOC-DDE-001.ECOSYSTEM.PRODUTOS | B24: produtos | C24: =IFERROR(IF(INDEX('01_Formulario_A00'!$D:$D,MATCH("D01-DOC-DDE-001.ECOSYSTEM.PRODUTOS",'01_Formulario_A00'!$A:$A,0))="","— (a preencher em 01_Formulario_A00)",INDEX('01_Formulario_A00'!$D:$D,MATCH("D01-DOC-DDE-001.ECOSYSTEM.PRODUTOS",'01_Formulario_A00'!$A:$A,0))),"— (a preencher em 01_Formulario_A00)")
A25: D01-DOC-DDE-001.ECOSYSTEM.SERVICOS | B25: servicos | C25: =IFERROR(IF(INDEX('01_Formulario_A00'!$D:$D,MATCH("D01-DOC-DDE-001.ECOSYSTEM.SERVICOS",'01_Formulario_A00'!$A:$A,0))="","— (a preencher em 01_Formulario_A00)",INDEX('01_Formulario_A00'!$D:$D,MATCH("D01-DOC-DDE-001.ECOSYSTEM.SERVICOS",'01_Formulario_A00'!$A:$A,0))),"— (a preencher em 01_Formulario_A00)")
A26: D01-DOC-DDE-001.ECOSYSTEM.MARCAS | B26: marcas | C26: =IFERROR(IF(INDEX('01_Formulario_A00'!$D:$D,MATCH("D01-DOC-DDE-001.ECOSYSTEM.MARCAS",'01_Formulario_A00'!$A:$A,0))="","— (a preencher em 01_Formulario_A00)",INDEX('01_Formulario_A00'!$D:$D,MATCH("D01-DOC-DDE-001.ECOSYSTEM.MARCAS",'01_Formulario_A00'!$A:$A,0))),"— (a preencher em 01_Formulario_A00)")
A27: D01-DOC-DDE-001.ECOSYSTEM.AGENTES | B27: agentes | C27: =IFERROR(IF(INDEX('01_Formulario_A00'!$D:$D,MATCH("D01-DOC-DDE-001.ECOSYSTEM.AGENTES",'01_Formulario_A00'!$A:$A,0))="","— (a preencher em 01_Formulario_A00)",INDEX('01_Formulario_A00'!$D:$D,MATCH("D01-DOC-DDE-001.ECOSYSTEM.AGENTES",'01_Formulario_A00'!$A:$A,0))),"— (a preencher em 01_Formulario_A00)")
A28: D01-DOC-DDE-001.ECOSYSTEM.PLATAFORMAS | B28: plataformas | C28: =IFERROR(IF(INDEX('01_Formulario_A00'!$D:$D,MATCH("D01-DOC-DDE-001.ECOSYSTEM.PLATAFORMAS",'01_Formulario_A00'!$A:$A,0))="","— (a preencher em 01_Formulario_A00)",INDEX('01_Formulario_A00'!$D:$D,MATCH("D01-DOC-DDE-001.ECOSYSTEM.PLATAFORMAS",'01_Formulario_A00'!$A:$A,0))),"— (a preencher em 01_Formulario_A00)")
A29: D01-DOC-DDE-001.ECOSYSTEM.UNIDADES_DE_NEGOCIO | B29: unidades_de_negocio | C29: =IFERROR(IF(INDEX('01_Formulario_A00'!$D:$D,MATCH("D01-DOC-DDE-001.ECOSYSTEM.UNIDADES_DE_NEGOCIO",'01_Formulario_A00'!$A:$A,0))="","— (a preencher em 01_Formulario_A00)",INDEX('01_Formulario_A00'!$D:$D,MATCH("D01-DOC-DDE-001.ECOSYSTEM.UNIDADES_DE_NEGOCIO",'01_Formulario_A00'!$A:$A,0))),"— (a preencher em 01_Formulario_A00)")
A30: D01-DOC-DDE-001.GOVERNANCE.MODELO_DE_GOVERNANCA | B30: modelo_de_governanca | C30: =IFERROR(IF(INDEX('01_Formulario_A00'!$D:$D,MATCH("D01-DOC-DDE-001.GOVERNANCE.MODELO_DE_GOVERNANCA",'01_Formulario_A00'!$A:$A,0))="","— (a preencher em 01_Formulario_A00)",INDEX('01_Formulario_A00'!$D:$D,MATCH("D01-DOC-DDE-001.GOVERNANCE.MODELO_DE_GOVERNANCA",'01_Formulario_A00'!$A:$A,0))),"— (a preencher em 01_Formulario_A00)")
A31: D01-DOC-DDE-001.GOVERNANCE.PAPEIS_DECISORIOS | B31: papeis_decisorios | C31: =IFERROR(IF(INDEX('01_Formulario_A00'!$D:$D,MATCH("D01-DOC-DDE-001.GOVERNANCE.PAPEIS_DECISORIOS",'01_Formulario_A00'!$A:$A,0))="","— (a preencher em 01_Formulario_A00)",INDEX('01_Formulario_A00'!$D:$D,MATCH("D01-DOC-DDE-001.GOVERNANCE.PAPEIS_DECISORIOS",'01_Formulario_A00'!$A:$A,0))),"— (a preencher em 01_Formulario_A00)")
A32: D01-DOC-DDE-001.GOVERNANCE.DIREITOS_DE_DECISAO | B32: direitos_de_decisao | C32: =IFERROR(IF(INDEX('01_Formulario_A00'!$D:$D,MATCH("D01-DOC-DDE-001.GOVERNANCE.DIREITOS_DE_DECISAO",'01_Formulario_A00'!$A:$A,0))="","— (a preencher em 01_Formulario_A00)",INDEX('01_Formulario_A00'!$D:$D,MATCH("D01-DOC-DDE-001.GOVERNANCE.DIREITOS_DE_DECISAO",'01_Formulario_A00'!$A:$A,0))),"— (a preencher em 01_Formulario_A00)")
A33: D01-DOC-DDE-001.GOVERNANCE.GATES | B33: gates | C33: =IFERROR(IF(INDEX('01_Formulario_A00'!$D:$D,MATCH("D01-DOC-DDE-001.GOVERNANCE.GATES",'01_Formulario_A00'!$A:$A,0))="","— (a preencher em 01_Formulario_A00)",INDEX('01_Formulario_A00'!$D:$D,MATCH("D01-DOC-DDE-001.GOVERNANCE.GATES",'01_Formulario_A00'!$A:$A,0))),"— (a preencher em 01_Formulario_A00)")
A34: D01-DOC-DDE-001.GOVERNANCE.MECANISMOS_DE_CONTROLE | B34: mecanismos_de_controle | C34: =IFERROR(IF(INDEX('01_Formulario_A00'!$D:$D,MATCH("D01-DOC-DDE-001.GOVERNANCE.MECANISMOS_DE_CONTROLE",'01_Formulario_A00'!$A:$A,0))="","— (a preencher em 01_Formulario_A00)",INDEX('01_Formulario_A00'!$D:$D,MATCH("D01-DOC-DDE-001.GOVERNANCE.MECANISMOS_DE_CONTROLE",'01_Formulario_A00'!$A:$A,0))),"— (a preencher em 01_Formulario_A00)")
A35: D01-DOC-DDE-001.STAKEHOLDERS.STAKEHOLDERS | B35: stakeholders | C35: =IFERROR(IF(INDEX('01_Formulario_A00'!$D:$D,MATCH("D01-DOC-DDE-001.STAKEHOLDERS.STAKEHOLDERS",'01_Formulario_A00'!$A:$A,0))="","— (a preencher em 01_Formulario_A00)",INDEX('01_Formulario_A00'!$D:$D,MATCH("D01-DOC-DDE-001.STAKEHOLDERS.STAKEHOLDERS",'01_Formulario_A00'!$A:$A,0))),"— (a preencher em 01_Formulario_A00)")
A36: D01-DOC-DDE-001.STAKEHOLDERS.INTERESSE | B36: interesse | C36: =IFERROR(IF(INDEX('01_Formulario_A00'!$D:$D,MATCH("D01-DOC-DDE-001.STAKEHOLDERS.INTERESSE",'01_Formulario_A00'!$A:$A,0))="","— (a preencher em 01_Formulario_A00)",INDEX('01_Formulario_A00'!$D:$D,MATCH("D01-DOC-DDE-001.STAKEHOLDERS.INTERESSE",'01_Formulario_A00'!$A:$A,0))),"— (a preencher em 01_Formulario_A00)")
A37: D01-DOC-DDE-001.STAKEHOLDERS.INFLUENCIA | B37: influencia | C37: =IFERROR(IF(INDEX('01_Formulario_A00'!$D:$D,MATCH("D01-DOC-DDE-001.STAKEHOLDERS.INFLUENCIA",'01_Formulario_A00'!$A:$A,0))="","— (a preencher em 01_Formulario_A00)",INDEX('01_Formulario_A00'!$D:$D,MATCH("D01-DOC-DDE-001.STAKEHOLDERS.INFLUENCIA",'01_Formulario_A00'!$A:$A,0))),"— (a preencher em 01_Formulario_A00)")
A38: D01-DOC-DDE-001.STAKEHOLDERS.RELACIONAMENTO | B38: relacionamento | C38: =IFERROR(IF(INDEX('01_Formulario_A00'!$D:$D,MATCH("D01-DOC-DDE-001.STAKEHOLDERS.RELACIONAMENTO",'01_Formulario_A00'!$A:$A,0))="","— (a preencher em 01_Formulario_A00)",INDEX('01_Formulario_A00'!$D:$D,MATCH("D01-DOC-DDE-001.STAKEHOLDERS.RELACIONAMENTO",'01_Formulario_A00'!$A:$A,0))),"— (a preencher em 01_Formulario_A00)")
A39: D01-DOC-DDE-001.STRATEGIC_DEPENDENCIES.DEPENDENCIAS | B39: dependencias | C39: =IFERROR(IF(INDEX('01_Formulario_A00'!$D:$D,MATCH("D01-DOC-DDE-001.STRATEGIC_DEPENDENCIES.DEPENDENCIAS",'01_Formulario_A00'!$A:$A,0))="","— (a preencher em 01_Formulario_A00)",INDEX('01_Formulario_A00'!$D:$D,MATCH("D01-DOC-DDE-001.STRATEGIC_DEPENDENCIES.DEPENDENCIAS",'01_Formulario_A00'!$A:$A,0))),"— (a preencher em 01_Formulario_A00)")
A40: D01-DOC-DDE-001.STRATEGIC_DEPENDENCIES.RESTRICOES | B40: restricoes | C40: =IFERROR(IF(INDEX('01_Formulario_A00'!$D:$D,MATCH("D01-DOC-DDE-001.STRATEGIC_DEPENDENCIES.RESTRICOES",'01_Formulario_A00'!$A:$A,0))="","— (a preencher em 01_Formulario_A00)",INDEX('01_Formulario_A00'!$D:$D,MATCH("D01-DOC-DDE-001.STRATEGIC_DEPENDENCIES.RESTRICOES",'01_Formulario_A00'!$A:$A,0))),"— (a preencher em 01_Formulario_A00)")
A41: D01-DOC-DDE-001.STRATEGIC_DEPENDENCIES.PREMISSAS | B41: premissas | C41: =IFERROR(IF(INDEX('01_Formulario_A00'!$D:$D,MATCH("D01-DOC-DDE-001.STRATEGIC_DEPENDENCIES.PREMISSAS",'01_Formulario_A00'!$A:$A,0))="","— (a preencher em 01_Formulario_A00)",INDEX('01_Formulario_A00'!$D:$D,MATCH("D01-DOC-DDE-001.STRATEGIC_DEPENDENCIES.PREMISSAS",'01_Formulario_A00'!$A:$A,0))),"— (a preencher em 01_Formulario_A00)")
A42: D01-DOC-DDE-001.RISKS.RISCOS_ESTRATEGICOS | B42: riscos_estrategicos | C42: =IFERROR(IF(INDEX('01_Formulario_A00'!$D:$D,MATCH("D01-DOC-DDE-001.RISKS.RISCOS_ESTRATEGICOS",'01_Formulario_A00'!$A:$A,0))="","— (a preencher em 01_Formulario_A00)",INDEX('01_Formulario_A00'!$D:$D,MATCH("D01-DOC-DDE-001.RISKS.RISCOS_ESTRATEGICOS",'01_Formulario_A00'!$A:$A,0))),"— (a preencher em 01_Formulario_A00)")
A43: D01-DOC-DDE-001.RISKS.MITIGACOES_EXISTENTES | B43: mitigacoes_existentes | C43: =IFERROR(IF(INDEX('01_Formulario_A00'!$D:$D,MATCH("D01-DOC-DDE-001.RISKS.MITIGACOES_EXISTENTES",'01_Formulario_A00'!$A:$A,0))="","— (a preencher em 01_Formulario_A00)",INDEX('01_Formulario_A00'!$D:$D,MATCH("D01-DOC-DDE-001.RISKS.MITIGACOES_EXISTENTES",'01_Formulario_A00'!$A:$A,0))),"— (a preencher em 01_Formulario_A00)")
A44: D01-DOC-DDE-001.MEASUREMENT.INDICADORES | B44: indicadores | C44: =IFERROR(IF(INDEX('01_Formulario_A00'!$D:$D,MATCH("D01-DOC-DDE-001.MEASUREMENT.INDICADORES",'01_Formulario_A00'!$A:$A,0))="","— (a preencher em 01_Formulario_A00)",INDEX('01_Formulario_A00'!$D:$D,MATCH("D01-DOC-DDE-001.MEASUREMENT.INDICADORES",'01_Formulario_A00'!$A:$A,0))),"— (a preencher em 01_Formulario_A00)")
A45: D01-DOC-DDE-001.MEASUREMENT.METAS | B45: metas | C45: =IFERROR(IF(INDEX('01_Formulario_A00'!$D:$D,MATCH("D01-DOC-DDE-001.MEASUREMENT.METAS",'01_Formulario_A00'!$A:$A,0))="","— (a preencher em 01_Formulario_A00)",INDEX('01_Formulario_A00'!$D:$D,MATCH("D01-DOC-DDE-001.MEASUREMENT.METAS",'01_Formulario_A00'!$A:$A,0))),"— (a preencher em 01_Formulario_A00)")
A46: D01-DOC-DDE-001.MEASUREMENT.CRITERIOS_DE_SUCESSO | B46: criterios_de_sucesso | C46: =IFERROR(IF(INDEX('01_Formulario_A00'!$D:$D,MATCH("D01-DOC-DDE-001.MEASUREMENT.CRITERIOS_DE_SUCESSO",'01_Formulario_A00'!$A:$A,0))="","— (a preencher em 01_Formulario_A00)",INDEX('01_Formulario_A00'!$D:$D,MATCH("D01-DOC-DDE-001.MEASUREMENT.CRITERIOS_DE_SUCESSO",'01_Formulario_A00'!$A:$A,0))),"— (a preencher em 01_Formulario_A00)")
A47: D01-DOC-DDE-001.DECISIONS.DECISOES_VIGENTES | B47: decisoes_vigentes | C47: =IFERROR(IF(INDEX('01_Formulario_A00'!$D:$D,MATCH("D01-DOC-DDE-001.DECISIONS.DECISOES_VIGENTES",'01_Formulario_A00'!$A:$A,0))="","— (a preencher em 01_Formulario_A00)",INDEX('01_Formulario_A00'!$D:$D,MATCH("D01-DOC-DDE-001.DECISIONS.DECISOES_VIGENTES",'01_Formulario_A00'!$A:$A,0))),"— (a preencher em 01_Formulario_A00)")
A48: D01-DOC-DDE-001.DECISIONS.DECISOES_PENDENTES | B48: decisoes_pendentes | C48: =IFERROR(IF(INDEX('01_Formulario_A00'!$D:$D,MATCH("D01-DOC-DDE-001.DECISIONS.DECISOES_PENDENTES",'01_Formulario_A00'!$A:$A,0))="","— (a preencher em 01_Formulario_A00)",INDEX('01_Formulario_A00'!$D:$D,MATCH("D01-DOC-DDE-001.DECISIONS.DECISOES_PENDENTES",'01_Formulario_A00'!$A:$A,0))),"— (a preencher em 01_Formulario_A00)")
A49: D01-DOC-TAP-001.IDENTIFICATION.TITULO | B49: titulo | C49: =IFERROR(IF(INDEX('01_Formulario_A00'!$D:$D,MATCH("D01-DOC-TAP-001.IDENTIFICATION.TITULO",'01_Formulario_A00'!$A:$A,0))="","— (a preencher em 01_Formulario_A00)",INDEX('01_Formulario_A00'!$D:$D,MATCH("D01-DOC-TAP-001.IDENTIFICATION.TITULO",'01_Formulario_A00'!$A:$A,0))),"— (a preencher em 01_Formulario_A00)")
A50: D01-DOC-TAP-001.IDENTIFICATION.JUSTIFICATIVA | B50: justificativa | C50: =IFERROR(IF(INDEX('01_Formulario_A00'!$D:$D,MATCH("D01-DOC-TAP-001.IDENTIFICATION.JUSTIFICATIVA",'01_Formulario_A00'!$A:$A,0))="","— (a preencher em 01_Formulario_A00)",INDEX('01_Formulario_A00'!$D:$D,MATCH("D01-DOC-TAP-001.IDENTIFICATION.JUSTIFICATIVA",'01_Formulario_A00'!$A:$A,0))),"— (a preencher em 01_Formulario_A00)")
A51: D01-DOC-TAP-001.IDENTIFICATION.CONTEXTO | B51: contexto | C51: =IFERROR(IF(INDEX('01_Formulario_A00'!$D:$D,MATCH("D01-DOC-TAP-001.IDENTIFICATION.CONTEXTO",'01_Formulario_A00'!$A:$A,0))="","— (a preencher em 01_Formulario_A00)",INDEX('01_Formulario_A00'!$D:$D,MATCH("D01-DOC-TAP-001.IDENTIFICATION.CONTEXTO",'01_Formulario_A00'!$A:$A,0))),"— (a preencher em 01_Formulario_A00)")
A52: D01-DOC-TAP-001.IDENTIFICATION.SPONSOR | B52: sponsor | C52: =IFERROR(IF(INDEX('01_Formulario_A00'!$D:$D,MATCH("D01-DOC-TAP-001.IDENTIFICATION.SPONSOR",'01_Formulario_A00'!$A:$A,0))="","— (a preencher em 01_Formulario_A00)",INDEX('01_Formulario_A00'!$D:$D,MATCH("D01-DOC-TAP-001.IDENTIFICATION.SPONSOR",'01_Formulario_A00'!$A:$A,0))),"— (a preencher em 01_Formulario_A00)")
A53: D01-DOC-TAP-001.IDENTIFICATION.OWNER | B53: owner | C53: =IFERROR(IF(INDEX('01_Formulario_A00'!$D:$D,MATCH("D01-DOC-TAP-001.IDENTIFICATION.OWNER",'01_Formulario_A00'!$A:$A,0))="","— (a preencher em 01_Formulario_A00)",INDEX('01_Formulario_A00'!$D:$D,MATCH("D01-DOC-TAP-001.IDENTIFICATION.OWNER",'01_Formulario_A00'!$A:$A,0))),"— (a preencher em 01_Formulario_A00)")
A54: D01-DOC-TAP-001.OBJECTIVE.OBJETIVO_GERAL | B54: objetivo_geral | C54: =IFERROR(IF(INDEX('01_Formulario_A00'!$D:$D,MATCH("D01-DOC-TAP-001.OBJECTIVE.OBJETIVO_GERAL",'01_Formulario_A00'!$A:$A,0))="","— (a preencher em 01_Formulario_A00)",INDEX('01_Formulario_A00'!$D:$D,MATCH("D01-DOC-TAP-001.OBJECTIVE.OBJETIVO_GERAL",'01_Formulario_A00'!$A:$A,0))),"— (a preencher em 01_Formulario_A00)")
A55: D01-DOC-TAP-001.OBJECTIVE.OBJETIVOS_ESPECIFICOS | B55: objetivos_especificos | C55: =IFERROR(IF(INDEX('01_Formulario_A00'!$D:$D,MATCH("D01-DOC-TAP-001.OBJECTIVE.OBJETIVOS_ESPECIFICOS",'01_Formulario_A00'!$A:$A,0))="","— (a preencher em 01_Formulario_A00)",INDEX('01_Formulario_A00'!$D:$D,MATCH("D01-DOC-TAP-001.OBJECTIVE.OBJETIVOS_ESPECIFICOS",'01_Formulario_A00'!$A:$A,0))),"— (a preencher em 01_Formulario_A00)")
A56: D01-DOC-TAP-001.OBJECTIVE.RESULTADO_FINAL_ESPERADO | B56: resultado_final_esperado | C56: =IFERROR(IF(INDEX('01_Formulario_A00'!$D:$D,MATCH("D01-DOC-TAP-001.OBJECTIVE.RESULTADO_FINAL_ESPERADO",'01_Formulario_A00'!$A:$A,0))="","— (a preencher em 01_Formulario_A00)",INDEX('01_Formulario_A00'!$D:$D,MATCH("D01-DOC-TAP-001.OBJECTIVE.RESULTADO_FINAL_ESPERADO",'01_Formulario_A00'!$A:$A,0))),"— (a preencher em 01_Formulario_A00)")
A57: D01-DOC-TAP-001.SCOPE.ESCOPO_INCLUIDO | B57: escopo_incluido | C57: =IFERROR(IF(INDEX('01_Formulario_A00'!$D:$D,MATCH("D01-DOC-TAP-001.SCOPE.ESCOPO_INCLUIDO",'01_Formulario_A00'!$A:$A,0))="","— (a preencher em 01_Formulario_A00)",INDEX('01_Formulario_A00'!$D:$D,MATCH("D01-DOC-TAP-001.SCOPE.ESCOPO_INCLUIDO",'01_Formulario_A00'!$A:$A,0))),"— (a preencher em 01_Formulario_A00)")
A58: D01-DOC-TAP-001.SCOPE.ESCOPO_EXCLUIDO | B58: escopo_excluido | C58: =IFERROR(IF(INDEX('01_Formulario_A00'!$D:$D,MATCH("D01-DOC-TAP-001.SCOPE.ESCOPO_EXCLUIDO",'01_Formulario_A00'!$A:$A,0))="","— (a preencher em 01_Formulario_A00)",INDEX('01_Formulario_A00'!$D:$D,MATCH("D01-DOC-TAP-001.SCOPE.ESCOPO_EXCLUIDO",'01_Formulario_A00'!$A:$A,0))),"— (a preencher em 01_Formulario_A00)")
A59: D01-DOC-TAP-001.SCOPE.FRONTEIRAS | B59: fronteiras | C59: =IFERROR(IF(INDEX('01_Formulario_A00'!$D:$D,MATCH("D01-DOC-TAP-001.SCOPE.FRONTEIRAS",'01_Formulario_A00'!$A:$A,0))="","— (a preencher em 01_Formulario_A00)",INDEX('01_Formulario_A00'!$D:$D,MATCH("D01-DOC-TAP-001.SCOPE.FRONTEIRAS",'01_Formulario_A00'!$A:$A,0))),"— (a preencher em 01_Formulario_A00)")
A60: D01-DOC-TAP-001.DELIVERABLES.ENTREGAVEIS_PRINCIPAIS | B60: entregaveis_principais | C60: =IFERROR(IF(INDEX('01_Formulario_A00'!$D:$D,MATCH("D01-DOC-TAP-001.DELIVERABLES.ENTREGAVEIS_PRINCIPAIS",'01_Formulario_A00'!$A:$A,0))="","— (a preencher em 01_Formulario_A00)",INDEX('01_Formulario_A00'!$D:$D,MATCH("D01-DOC-TAP-001.DELIVERABLES.ENTREGAVEIS_PRINCIPAIS",'01_Formulario_A00'!$A:$A,0))),"— (a preencher em 01_Formulario_A00)")
A61: D01-DOC-TAP-001.DELIVERABLES.DEFINITION_OF_DONE | B61: definition_of_done | C61: =IFERROR(IF(INDEX('01_Formulario_A00'!$D:$D,MATCH("D01-DOC-TAP-001.DELIVERABLES.DEFINITION_OF_DONE",'01_Formulario_A00'!$A:$A,0))="","— (a preencher em 01_Formulario_A00)",INDEX('01_Formulario_A00'!$D:$D,MATCH("D01-DOC-TAP-001.DELIVERABLES.DEFINITION_OF_DONE",'01_Formulario_A00'!$A:$A,0))),"— (a preencher em 01_Formulario_A00)")
A62: D01-DOC-TAP-001.MILESTONES.MARCOS | B62: marcos | C62: =IFERROR(IF(INDEX('01_Formulario_A00'!$D:$D,MATCH("D01-DOC-TAP-001.MILESTONES.MARCOS",'01_Formulario_A00'!$A:$A,0))="","— (a preencher em 01_Formulario_A00)",INDEX('01_Formulario_A00'!$D:$D,MATCH("D01-DOC-TAP-001.MILESTONES.MARCOS",'01_Formulario_A00'!$A:$A,0))),"— (a preencher em 01_Formulario_A00)")
A63: D01-DOC-TAP-001.MILESTONES.DATAS_EXISTENTES | B63: datas_existentes | C63: =IFERROR(IF(INDEX('01_Formulario_A00'!$D:$D,MATCH("D01-DOC-TAP-001.MILESTONES.DATAS_EXISTENTES",'01_Formulario_A00'!$A:$A,0))="","— (a preencher em 01_Formulario_A00)",INDEX('01_Formulario_A00'!$D:$D,MATCH("D01-DOC-TAP-001.MILESTONES.DATAS_EXISTENTES",'01_Formulario_A00'!$A:$A,0))),"— (a preencher em 01_Formulario_A00)")
A64: D01-DOC-TAP-001.STAKEHOLDERS.PARTICIPANTES | B64: participantes | C64: =IFERROR(IF(INDEX('01_Formulario_A00'!$D:$D,MATCH("D01-DOC-TAP-001.STAKEHOLDERS.PARTICIPANTES",'01_Formulario_A00'!$A:$A,0))="","— (a preencher em 01_Formulario_A00)",INDEX('01_Formulario_A00'!$D:$D,MATCH("D01-DOC-TAP-001.STAKEHOLDERS.PARTICIPANTES",'01_Formulario_A00'!$A:$A,0))),"— (a preencher em 01_Formulario_A00)")
A65: D01-DOC-TAP-001.STAKEHOLDERS.PAPEIS | B65: papeis | C65: =IFERROR(IF(INDEX('01_Formulario_A00'!$D:$D,MATCH("D01-DOC-TAP-001.STAKEHOLDERS.PAPEIS",'01_Formulario_A00'!$A:$A,0))="","— (a preencher em 01_Formulario_A00)",INDEX('01_Formulario_A00'!$D:$D,MATCH("D01-DOC-TAP-001.STAKEHOLDERS.PAPEIS",'01_Formulario_A00'!$A:$A,0))),"— (a preencher em 01_Formulario_A00)")
A66: D01-DOC-TAP-001.STAKEHOLDERS.RESPONSABILIDADES | B66: responsabilidades | C66: =IFERROR(IF(INDEX('01_Formulario_A00'!$D:$D,MATCH("D01-DOC-TAP-001.STAKEHOLDERS.RESPONSABILIDADES",'01_Formulario_A00'!$A:$A,0))="","— (a preencher em 01_Formulario_A00)",INDEX('01_Formulario_A00'!$D:$D,MATCH("D01-DOC-TAP-001.STAKEHOLDERS.RESPONSABILIDADES",'01_Formulario_A00'!$A:$A,0))),"— (a preencher em 01_Formulario_A00)")
A67: D01-DOC-TAP-001.CONSTRAINTS.RESTRICOES | B67: restricoes | C67: =IFERROR(IF(INDEX('01_Formulario_A00'!$D:$D,MATCH("D01-DOC-TAP-001.CONSTRAINTS.RESTRICOES",'01_Formulario_A00'!$A:$A,0))="","— (a preencher em 01_Formulario_A00)",INDEX('01_Formulario_A00'!$D:$D,MATCH("D01-DOC-TAP-001.CONSTRAINTS.RESTRICOES",'01_Formulario_A00'!$A:$A,0))),"— (a preencher em 01_Formulario_A00)")
A68: D01-DOC-TAP-001.CONSTRAINTS.PREMISSAS | B68: premissas | C68: =IFERROR(IF(INDEX('01_Formulario_A00'!$D:$D,MATCH("D01-DOC-TAP-001.CONSTRAINTS.PREMISSAS",'01_Formulario_A00'!$A:$A,0))="","— (a preencher em 01_Formulario_A00)",INDEX('01_Formulario_A00'!$D:$D,MATCH("D01-DOC-TAP-001.CONSTRAINTS.PREMISSAS",'01_Formulario_A00'!$A:$A,0))),"— (a preencher em 01_Formulario_A00)")
A69: D01-DOC-TAP-001.CONSTRAINTS.DEPENDENCIAS | B69: dependencias | C69: =IFERROR(IF(INDEX('01_Formulario_A00'!$D:$D,MATCH("D01-DOC-TAP-001.CONSTRAINTS.DEPENDENCIAS",'01_Formulario_A00'!$A:$A,0))="","— (a preencher em 01_Formulario_A00)",INDEX('01_Formulario_A00'!$D:$D,MATCH("D01-DOC-TAP-001.CONSTRAINTS.DEPENDENCIAS",'01_Formulario_A00'!$A:$A,0))),"— (a preencher em 01_Formulario_A00)")
A70: D01-DOC-TAP-001.RESOURCES.CAPACIDADE | B70: capacidade | C70: =IFERROR(IF(INDEX('01_Formulario_A00'!$D:$D,MATCH("D01-DOC-TAP-001.RESOURCES.CAPACIDADE",'01_Formulario_A00'!$A:$A,0))="","— (a preencher em 01_Formulario_A00)",INDEX('01_Formulario_A00'!$D:$D,MATCH("D01-DOC-TAP-001.RESOURCES.CAPACIDADE",'01_Formulario_A00'!$A:$A,0))),"— (a preencher em 01_Formulario_A00)")
A71: D01-DOC-TAP-001.RESOURCES.RECURSOS | B71: recursos | C71: =IFERROR(IF(INDEX('01_Formulario_A00'!$D:$D,MATCH("D01-DOC-TAP-001.RESOURCES.RECURSOS",'01_Formulario_A00'!$A:$A,0))="","— (a preencher em 01_Formulario_A00)",INDEX('01_Formulario_A00'!$D:$D,MATCH("D01-DOC-TAP-001.RESOURCES.RECURSOS",'01_Formulario_A00'!$A:$A,0))),"— (a preencher em 01_Formulario_A00)")
A72: D01-DOC-TAP-001.RESOURCES.ORCAMENTO | B72: orcamento | C72: =IFERROR(IF(INDEX('01_Formulario_A00'!$D:$D,MATCH("D01-DOC-TAP-001.RESOURCES.ORCAMENTO",'01_Formulario_A00'!$A:$A,0))="","— (a preencher em 01_Formulario_A00)",INDEX('01_Formulario_A00'!$D:$D,MATCH("D01-DOC-TAP-001.RESOURCES.ORCAMENTO",'01_Formulario_A00'!$A:$A,0))),"— (a preencher em 01_Formulario_A00)")
A73: D01-DOC-TAP-001.SUCCESS.CRITERIOS_DE_ACEITE | B73: criterios_de_aceite | C73: =IFERROR(IF(INDEX('01_Formulario_A00'!$D:$D,MATCH("D01-DOC-TAP-001.SUCCESS.CRITERIOS_DE_ACEITE",'01_Formulario_A00'!$A:$A,0))="","— (a preencher em 01_Formulario_A00)",INDEX('01_Formulario_A00'!$D:$D,MATCH("D01-DOC-TAP-001.SUCCESS.CRITERIOS_DE_ACEITE",'01_Formulario_A00'!$A:$A,0))),"— (a preencher em 01_Formulario_A00)")
A74: D01-DOC-TAP-001.SUCCESS.INDICADORES_DE_SUCESSO | B74: indicadores_de_sucesso | C74: =IFERROR(IF(INDEX('01_Formulario_A00'!$D:$D,MATCH("D01-DOC-TAP-001.SUCCESS.INDICADORES_DE_SUCESSO",'01_Formulario_A00'!$A:$A,0))="","— (a preencher em 01_Formulario_A00)",INDEX('01_Formulario_A00'!$D:$D,MATCH("D01-DOC-TAP-001.SUCCESS.INDICADORES_DE_SUCESSO",'01_Formulario_A00'!$A:$A,0))),"— (a preencher em 01_Formulario_A00)")
A75: D01-DOC-TAP-001.RISKS.RISCOS_INICIAIS | B75: riscos_iniciais | C75: =IFERROR(IF(INDEX('01_Formulario_A00'!$D:$D,MATCH("D01-DOC-TAP-001.RISKS.RISCOS_INICIAIS",'01_Formulario_A00'!$A:$A,0))="","— (a preencher em 01_Formulario_A00)",INDEX('01_Formulario_A00'!$D:$D,MATCH("D01-DOC-TAP-001.RISKS.RISCOS_INICIAIS",'01_Formulario_A00'!$A:$A,0))),"— (a preencher em 01_Formulario_A00)")
A76: D01-DOC-TAP-001.APPROVALS.APROVADORES | B76: aprovadores | C76: =IFERROR(IF(INDEX('01_Formulario_A00'!$D:$D,MATCH("D01-DOC-TAP-001.APPROVALS.APROVADORES",'01_Formulario_A00'!$A:$A,0))="","— (a preencher em 01_Formulario_A00)",INDEX('01_Formulario_A00'!$D:$D,MATCH("D01-DOC-TAP-001.APPROVALS.APROVADORES",'01_Formulario_A00'!$A:$A,0))),"— (a preencher em 01_Formulario_A00)")
A77: D01-DOC-TAP-001.APPROVALS.STATUS_APROVACAO | B77: status_aprovacao | C77: =IFERROR(IF(INDEX('01_Formulario_A00'!$D:$D,MATCH("D01-DOC-TAP-001.APPROVALS.STATUS_APROVACAO",'01_Formulario_A00'!$A:$A,0))="","— (a preencher em 01_Formulario_A00)",INDEX('01_Formulario_A00'!$D:$D,MATCH("D01-DOC-TAP-001.APPROVALS.STATUS_APROVACAO",'01_Formulario_A00'!$A:$A,0))),"— (a preencher em 01_Formulario_A00)")
A78: D01-DOC-MNE-001.CUSTOMER.SEGMENTOS | B78: segmentos | C78: =IFERROR(IF(INDEX('01_Formulario_A00'!$D:$D,MATCH("D01-DOC-MNE-001.CUSTOMER.SEGMENTOS",'01_Formulario_A00'!$A:$A,0))="","— (a preencher em 01_Formulario_A00)",INDEX('01_Formulario_A00'!$D:$D,MATCH("D01-DOC-MNE-001.CUSTOMER.SEGMENTOS",'01_Formulario_A00'!$A:$A,0))),"— (a preencher em 01_Formulario_A00)")
A79: D01-DOC-MNE-001.CUSTOMER.USUARIOS | B79: usuarios | C79: =IFERROR(IF(INDEX('01_Formulario_A00'!$D:$D,MATCH("D01-DOC-MNE-001.CUSTOMER.USUARIOS",'01_Formulario_A00'!$A:$A,0))="","— (a preencher em 01_Formulario_A00)",INDEX('01_Formulario_A00'!$D:$D,MATCH("D01-DOC-MNE-001.CUSTOMER.USUARIOS",'01_Formulario_A00'!$A:$A,0))),"— (a preencher em 01_Formulario_A00)")
A80: D01-DOC-MNE-001.CUSTOMER.CLIENTES | B80: clientes | C80: =IFERROR(IF(INDEX('01_Formulario_A00'!$D:$D,MATCH("D01-DOC-MNE-001.CUSTOMER.CLIENTES",'01_Formulario_A00'!$A:$A,0))="","— (a preencher em 01_Formulario_A00)",INDEX('01_Formulario_A00'!$D:$D,MATCH("D01-DOC-MNE-001.CUSTOMER.CLIENTES",'01_Formulario_A00'!$A:$A,0))),"— (a preencher em 01_Formulario_A00)")
A81: D01-DOC-MNE-001.CUSTOMER.PROBLEMAS | B81: problemas | C81: =IFERROR(IF(INDEX('01_Formulario_A00'!$D:$D,MATCH("D01-DOC-MNE-001.CUSTOMER.PROBLEMAS",'01_Formulario_A00'!$A:$A,0))="","— (a preencher em 01_Formulario_A00)",INDEX('01_Formulario_A00'!$D:$D,MATCH("D01-DOC-MNE-001.CUSTOMER.PROBLEMAS",'01_Formulario_A00'!$A:$A,0))),"— (a preencher em 01_Formulario_A00)")
A82: D01-DOC-MNE-001.CUSTOMER.JTBD | B82: jtbd | C82: =IFERROR(IF(INDEX('01_Formulario_A00'!$D:$D,MATCH("D01-DOC-MNE-001.CUSTOMER.JTBD",'01_Formulario_A00'!$A:$A,0))="","— (a preencher em 01_Formulario_A00)",INDEX('01_Formulario_A00'!$D:$D,MATCH("D01-DOC-MNE-001.CUSTOMER.JTBD",'01_Formulario_A00'!$A:$A,0))),"— (a preencher em 01_Formulario_A00)")
A83: D01-DOC-MNE-001.VALUE.PROPOSTAS_DE_VALOR | B83: propostas_de_valor | C83: =IFERROR(IF(INDEX('01_Formulario_A00'!$D:$D,MATCH("D01-DOC-MNE-001.VALUE.PROPOSTAS_DE_VALOR",'01_Formulario_A00'!$A:$A,0))="","— (a preencher em 01_Formulario_A00)",INDEX('01_Formulario_A00'!$D:$D,MATCH("D01-DOC-MNE-001.VALUE.PROPOSTAS_DE_VALOR",'01_Formulario_A00'!$A:$A,0))),"— (a preencher em 01_Formulario_A00)")
A84: D01-DOC-MNE-001.VALUE.BENEFICIOS | B84: beneficios | C84: =IFERROR(IF(INDEX('01_Formulario_A00'!$D:$D,MATCH("D01-DOC-MNE-001.VALUE.BENEFICIOS",'01_Formulario_A00'!$A:$A,0))="","— (a preencher em 01_Formulario_A00)",INDEX('01_Formulario_A00'!$D:$D,MATCH("D01-DOC-MNE-001.VALUE.BENEFICIOS",'01_Formulario_A00'!$A:$A,0))),"— (a preencher em 01_Formulario_A00)")
A85: D01-DOC-MNE-001.VALUE.DIFERENCIADORES | B85: diferenciadores | C85: =IFERROR(IF(INDEX('01_Formulario_A00'!$D:$D,MATCH("D01-DOC-MNE-001.VALUE.DIFERENCIADORES",'01_Formulario_A00'!$A:$A,0))="","— (a preencher em 01_Formulario_A00)",INDEX('01_Formulario_A00'!$D:$D,MATCH("D01-DOC-MNE-001.VALUE.DIFERENCIADORES",'01_Formulario_A00'!$A:$A,0))),"— (a preencher em 01_Formulario_A00)")
A86: D01-DOC-MNE-001.VALUE.ALTERNATIVAS_EXISTENTES | B86: alternativas_existentes | C86: =IFERROR(IF(INDEX('01_Formulario_A00'!$D:$D,MATCH("D01-DOC-MNE-001.VALUE.ALTERNATIVAS_EXISTENTES",'01_Formulario_A00'!$A:$A,0))="","— (a preencher em 01_Formulario_A00)",INDEX('01_Formulario_A00'!$D:$D,MATCH("D01-DOC-MNE-001.VALUE.ALTERNATIVAS_EXISTENTES",'01_Formulario_A00'!$A:$A,0))),"— (a preencher em 01_Formulario_A00)")
A87: D01-DOC-MNE-001.OFFERINGS.PRODUTOS | B87: produtos | C87: =IFERROR(IF(INDEX('01_Formulario_A00'!$D:$D,MATCH("D01-DOC-MNE-001.OFFERINGS.PRODUTOS",'01_Formulario_A00'!$A:$A,0))="","— (a preencher em 01_Formulario_A00)",INDEX('01_Formulario_A00'!$D:$D,MATCH("D01-DOC-MNE-001.OFFERINGS.PRODUTOS",'01_Formulario_A00'!$A:$A,0))),"— (a preencher em 01_Formulario_A00)")
A88: D01-DOC-MNE-001.OFFERINGS.SERVICOS | B88: servicos | C88: =IFERROR(IF(INDEX('01_Formulario_A00'!$D:$D,MATCH("D01-DOC-MNE-001.OFFERINGS.SERVICOS",'01_Formulario_A00'!$A:$A,0))="","— (a preencher em 01_Formulario_A00)",INDEX('01_Formulario_A00'!$D:$D,MATCH("D01-DOC-MNE-001.OFFERINGS.SERVICOS",'01_Formulario_A00'!$A:$A,0))),"— (a preencher em 01_Formulario_A00)")
A89: D01-DOC-MNE-001.OFFERINGS.PLANOS | B89: planos | C89: =IFERROR(IF(INDEX('01_Formulario_A00'!$D:$D,MATCH("D01-DOC-MNE-001.OFFERINGS.PLANOS",'01_Formulario_A00'!$A:$A,0))="","— (a preencher em 01_Formulario_A00)",INDEX('01_Formulario_A00'!$D:$D,MATCH("D01-DOC-MNE-001.OFFERINGS.PLANOS",'01_Formulario_A00'!$A:$A,0))),"— (a preencher em 01_Formulario_A00)")
A90: D01-DOC-MNE-001.OFFERINGS.OFERTAS | B90: ofertas | C90: =IFERROR(IF(INDEX('01_Formulario_A00'!$D:$D,MATCH("D01-DOC-MNE-001.OFFERINGS.OFERTAS",'01_Formulario_A00'!$A:$A,0))="","— (a preencher em 01_Formulario_A00)",INDEX('01_Formulario_A00'!$D:$D,MATCH("D01-DOC-MNE-001.OFFERINGS.OFERTAS",'01_Formulario_A00'!$A:$A,0))),"— (a preencher em 01_Formulario_A00)")
A91: D01-DOC-MNE-001.CHANNELS.AQUISICAO | B91: aquisicao | C91: =IFERROR(IF(INDEX('01_Formulario_A00'!$D:$D,MATCH("D01-DOC-MNE-001.CHANNELS.AQUISICAO",'01_Formulario_A00'!$A:$A,0))="","— (a preencher em 01_Formulario_A00)",INDEX('01_Formulario_A00'!$D:$D,MATCH("D01-DOC-MNE-001.CHANNELS.AQUISICAO",'01_Formulario_A00'!$A:$A,0))),"— (a preencher em 01_Formulario_A00)")
A92: D01-DOC-MNE-001.CHANNELS.DISTRIBUICAO | B92: distribuicao | C92: =IFERROR(IF(INDEX('01_Formulario_A00'!$D:$D,MATCH("D01-DOC-MNE-001.CHANNELS.DISTRIBUICAO",'01_Formulario_A00'!$A:$A,0))="","— (a preencher em 01_Formulario_A00)",INDEX('01_Formulario_A00'!$D:$D,MATCH("D01-DOC-MNE-001.CHANNELS.DISTRIBUICAO",'01_Formulario_A00'!$A:$A,0))),"— (a preencher em 01_Formulario_A00)")
A93: D01-DOC-MNE-001.CHANNELS.ENTREGA | B93: entrega | C93: =IFERROR(IF(INDEX('01_Formulario_A00'!$D:$D,MATCH("D01-DOC-MNE-001.CHANNELS.ENTREGA",'01_Formulario_A00'!$A:$A,0))="","— (a preencher em 01_Formulario_A00)",INDEX('01_Formulario_A00'!$D:$D,MATCH("D01-DOC-MNE-001.CHANNELS.ENTREGA",'01_Formulario_A00'!$A:$A,0))),"— (a preencher em 01_Formulario_A00)")
A94: D01-DOC-MNE-001.RELATIONSHIPS.RELACIONAMENTO_COM_CLIENTE | B94: relacionamento_com_cliente | C94: =IFERROR(IF(INDEX('01_Formulario_A00'!$D:$D,MATCH("D01-DOC-MNE-001.RELATIONSHIPS.RELACIONAMENTO_COM_CLIENTE",'01_Formulario_A00'!$A:$A,0))="","— (a preencher em 01_Formulario_A00)",INDEX('01_Formulario_A00'!$D:$D,MATCH("D01-DOC-MNE-001.RELATIONSHIPS.RELACIONAMENTO_COM_CLIENTE",'01_Formulario_A00'!$A:$A,0))),"— (a preencher em 01_Formulario_A00)")
A95: D01-DOC-MNE-001.RELATIONSHIPS.COMUNIDADE | B95: comunidade | C95: =IFERROR(IF(INDEX('01_Formulario_A00'!$D:$D,MATCH("D01-DOC-MNE-001.RELATIONSHIPS.COMUNIDADE",'01_Formulario_A00'!$A:$A,0))="","— (a preencher em 01_Formulario_A00)",INDEX('01_Formulario_A00'!$D:$D,MATCH("D01-DOC-MNE-001.RELATIONSHIPS.COMUNIDADE",'01_Formulario_A00'!$A:$A,0))),"— (a preencher em 01_Formulario_A00)")
A96: D01-DOC-MNE-001.RELATIONSHIPS.SUPORTE | B96: suporte | C96: =IFERROR(IF(INDEX('01_Formulario_A00'!$D:$D,MATCH("D01-DOC-MNE-001.RELATIONSHIPS.SUPORTE",'01_Formulario_A00'!$A:$A,0))="","— (a preencher em 01_Formulario_A00)",INDEX('01_Formulario_A00'!$D:$D,MATCH("D01-DOC-MNE-001.RELATIONSHIPS.SUPORTE",'01_Formulario_A00'!$A:$A,0))),"— (a preencher em 01_Formulario_A00)")
A97: D01-DOC-MNE-001.REVENUE.FONTES_DE_RECEITA | B97: fontes_de_receita | C97: =IFERROR(IF(INDEX('01_Formulario_A00'!$D:$D,MATCH("D01-DOC-MNE-001.REVENUE.FONTES_DE_RECEITA",'01_Formulario_A00'!$A:$A,0))="","— (a preencher em 01_Formulario_A00)",INDEX('01_Formulario_A00'!$D:$D,MATCH("D01-DOC-MNE-001.REVENUE.FONTES_DE_RECEITA",'01_Formulario_A00'!$A:$A,0))),"— (a preencher em 01_Formulario_A00)")
A98: D01-DOC-MNE-001.REVENUE.PRECIFICACAO | B98: precificacao | C98: =IFERROR(IF(INDEX('01_Formulario_A00'!$D:$D,MATCH("D01-DOC-MNE-001.REVENUE.PRECIFICACAO",'01_Formulario_A00'!$A:$A,0))="","— (a preencher em 01_Formulario_A00)",INDEX('01_Formulario_A00'!$D:$D,MATCH("D01-DOC-MNE-001.REVENUE.PRECIFICACAO",'01_Formulario_A00'!$A:$A,0))),"— (a preencher em 01_Formulario_A00)")
A99: D01-DOC-MNE-001.REVENUE.RECORRENCIA | B99: recorrencia | C99: =IFERROR(IF(INDEX('01_Formulario_A00'!$D:$D,MATCH("D01-DOC-MNE-001.REVENUE.RECORRENCIA",'01_Formulario_A00'!$A:$A,0))="","— (a preencher em 01_Formulario_A00)",INDEX('01_Formulario_A00'!$D:$D,MATCH("D01-DOC-MNE-001.REVENUE.RECORRENCIA",'01_Formulario_A00'!$A:$A,0))),"— (a preencher em 01_Formulario_A00)")
A100: D01-DOC-MNE-001.COSTS.ESTRUTURA_DE_CUSTOS | B100: estrutura_de_custos | C100: =IFERROR(IF(INDEX('01_Formulario_A00'!$D:$D,MATCH("D01-DOC-MNE-001.COSTS.ESTRUTURA_DE_CUSTOS",'01_Formulario_A00'!$A:$A,0))="","— (a preencher em 01_Formulario_A00)",INDEX('01_Formulario_A00'!$D:$D,MATCH("D01-DOC-MNE-001.COSTS.ESTRUTURA_DE_CUSTOS",'01_Formulario_A00'!$A:$A,0))),"— (a preencher em 01_Formulario_A00)")
A101: D01-DOC-MNE-001.COSTS.CAPEX | B101: capex | C101: =IFERROR(IF(INDEX('01_Formulario_A00'!$D:$D,MATCH("D01-DOC-MNE-001.COSTS.CAPEX",'01_Formulario_A00'!$A:$A,0))="","— (a preencher em 01_Formulario_A00)",INDEX('01_Formulario_A00'!$D:$D,MATCH("D01-DOC-MNE-001.COSTS.CAPEX",'01_Formulario_A00'!$A:$A,0))),"— (a preencher em 01_Formulario_A00)")
A102: D01-DOC-MNE-001.COSTS.OPEX | B102: opex | C102: =IFERROR(IF(INDEX('01_Formulario_A00'!$D:$D,MATCH("D01-DOC-MNE-001.COSTS.OPEX",'01_Formulario_A00'!$A:$A,0))="","— (a preencher em 01_Formulario_A00)",INDEX('01_Formulario_A00'!$D:$D,MATCH("D01-DOC-MNE-001.COSTS.OPEX",'01_Formulario_A00'!$A:$A,0))),"— (a preencher em 01_Formulario_A00)")
...

Sheet 04_Visao_Portfolio
A1: portfolio_id | B1: name | C1: type | D1: status | E1: owner
A2: S0 | B2: Executar programa governança e operações. | C2: PROGRAM_OPS | D2: ACTIVE | E2: A_DEFINIR
A3: M0 | B3: Executar Institucional | C3: PRODUCT_INITIATIVE | D3: ACTIVE | E3: A_DEFINIR
A4: M1 | B4: Executar App | C4: PRODUCT_INITIATIVE | D4: ACTIVE | E4: A_DEFINIR
A5: M2 | B5: Executar Blog | C5: PRODUCT_INITIATIVE | D5: ACTIVE | E5: A_DEFINIR
A6: M2.1 | B6: Risco cognitivo Blog | C6: PRODUCT_INITIATIVE | D6: ACTIVE | E6: A_DEFINIR
A7: M3 | B7: Executar Oficina | C7: PRODUCT_INITIATIVE | D7: ACTIVE | E7: A_DEFINIR
A8: M4 | B8: Executar Mapa Cognitivo | C8: PRODUCT_INITIATIVE | D8: ACTIVE | E8: A_DEFINIR
A9: M5 | B9: Executar Agente Copiloto | C9: PRODUCT_INITIATIVE | D9: ACTIVE | E9: A_DEFINIR
A10: M6 | B10: Executar Agente Maestro | C10: PRODUCT_INITIATIVE | D10: ACTIVE | E10: A_DEFINIR
A11: M7 | B11: Executar Agente Vera | C11: PRODUCT_INITIATIVE | D11: ACTIVE | E11: A_DEFINIR
A12: M7.1 | B12: Executar emprego e portfólio | C12: PRODUCT_INITIATIVE | D12: ACTIVE | E12: A_DEFINIR
... A21: M16 | B21: Executar lead business creator strategy launch | C21: PRODUCT_INITIATIVE | D21: ACTIVE | E21: A_DEFINIR

Sheet 05_Visao_Artefatos
B2: Visão Artefatos — espelho narrativo (não editar; ver 01_Formulario_*)
A4: D01-DOC-DDE-001 — Documento de Direção Empresarial [PRE_PREENCHIDO/PENDENTE]
A5: D01-DOC-DDE-001.IDENTITY.NOME_DO_ECOSSISTEMA | B5: nome_do_ecossistema | C5: =IFERROR(IF(INDEX('01_Formulario_A00'!$D:$D,MATCH("D01-DOC-DDE-001.IDENTITY.NOME_DO_ECOSSISTEMA",'01_Formulario_A00'!$A:$A,0))="","— (a preencher em 01_Formulario_A00)",INDEX('01_Formulario_A00'!$D:$D,MATCH("D01-DOC-DDE-001.IDENTITY.NOME_DO_ECOSSISTEMA",'01_Formulario_A00'!$A:$A,0))),"— (a preencher em 01_Formulario_A00)")
A6: D01-DOC-DDE-001.IDENTITY.DESCRICAO_EXECUTIVA | B6: descricao_executiva | C6: =IFERROR(IF(INDEX('01_Formulario_A00'!$D:$D,MATCH("D01-DOC-DDE-001.IDENTITY.DESCRICAO_EXECUTIVA",'01_Formulario_A00'!$A:$A,0))="","— (a preencher em 01_Formulario_A00)",INDEX('01_Formulario_A00'!$D:$D,MATCH("D01-DOC-DDE-001.IDENTITY.DESCRICAO_EXECUTIVA",'01_Formulario_A00'!$A:$A,0))),"— (a preencher em 01_Formulario_A00)")
A7: D01-DOC-DDE-001.IDENTITY.CONTEXTO | B7: contexto | C7: =IFERROR(IF(INDEX('01_Formulario_A00'!$D:$D,MATCH("D01-DOC-DDE-001.IDENTITY.CONTEXTO",'01_Formulario_A00'!$A:$A,0))="","— (a preencher em 01_Formulario_A00)",INDEX('01_Formulario_A00'!$D:$D,MATCH("D01-DOC-DDE-001.IDENTITY.CONTEXTO",'01_Formulario_A00'!$A:$A,0))),"— (a preencher em 01_Formulario_A00)")
A8: D01-DOC-DDE-001.IDENTITY.RAZAO_DE_EXISTENCIA | B8: razao_de_existencia | C8: =IFERROR(IF(INDEX('01_Formulario_A00'!$D:$D,MATCH("D01-DOC-DDE-001.IDENTITY.RAZAO_DE_EXISTENCIA",'01_Formulario_A00'!$A:$A,0))="","— (a preencher em 01_Formulario_A00)",INDEX('01_Formulario_A00'!$D:$D,MATCH("D01-DOC-DDE-001.IDENTITY.RAZAO_DE_EXISTENCIA",'01_Formulario_A00'!$A:$A,0))),"— (a preencher em 01_Formulario_A00)")
A9: D01-DOC-DDE-001.IDENTITY.FASE_ATUAL | B9: fase_atual | C9: =IFERROR(IF(INDEX('01_Formulario_A00'!$D:$D,MATCH("D01-DOC-DDE-001.IDENTITY.FASE_ATUAL",'01_Formulario_A00'!$A:$A,0))="","— (a preencher em 01_Formulario_A00)",INDEX('01_Formulario_A00'!$D:$D,MATCH("D01-DOC-DDE-001.IDENTITY.FASE_ATUAL",'01_Formulario_A00'!$A:$A,0))),"— (a preencher em 01_Formulario_A00)")
A10: D01-DOC-DDE-001.PROBLEM_AND_OPPORTUNITY.PROBLEMA_CENTRAL | B10: problema_central | C10: =IFERROR(IF(INDEX('01_Formulario_A00'!$D:$D,MATCH("D01-DOC-DDE-001.PROBLEM_AND_OPPORTUNITY.PROBLEMA_CENTRAL",'01_Formulario_A00'!$A:$A,0))="","— (a preencher em 01_Formulario_A00)",INDEX('01_Formulario_A00'!$D:$D,MATCH("D01-DOC-DDE-001.PROBLEM_AND_OPPORTUNITY.PROBLEMA_CENTRAL",'01_Formulario_A00'!$A:$A,0))),"— (a preencher em 01_Formulario_A00)")
A11: D01-DOC-DDE-001.PROBLEM_AND_OPPORTUNITY.PROBLEMAS_SECUNDARIOS | B11: problemas_secundarios | C11: =IFERROR(IF(INDEX('01_Formulario_A00'!$D:$D,MATCH("D01-DOC-DDE-001.PROBLEM_AND_OPPORTUNITY.PROBLEMAS_SECUNDARIOS",'01_Formulario_A00'!$A:$A,0))="","— (a preencher em 01_Formulario_A00)",INDEX('01_Formulario_A00'!$D:$D,MATCH("D01-DOC-DDE-001.PROBLEM_AND_OPPORTUNITY.PROBLEMAS_SECUNDARIOS",'01_Formulario_A00'!$A:$A,0))),"— (a preencher em 01_Formulario_A00)")
A12: D01-DOC-DDE-001.PROBLEM_AND_OPPORTUNITY.OPORTUNIDADE | B12: oportunidade | C12: =IFERROR(IF(INDEX('01_Formulario_A00'!$D:$D,MATCH("D01-DOC-DDE-001.PROBLEM_AND_OPPORTUNITY.OPORTUNIDADE",'01_Formulario_A00'!$A:$A,0))="","— (a preencher em 01_Formulario_A00)",INDEX('01_Formulario_A00'!$D:$D,MATCH("D01-DOC-DDE-001.PROBLEM_AND_OPPORTUNITY.OPORTUNIDADE",'01_Formulario_A00'!$A:$A,0))),"— (a preencher em 01_Formulario_A00)")
A13: D01-DOC-DDE-001.PROBLEM_AND_OPPORTUNITY.EVIDENCIAS_DO_PROBLEMA | B13: evidencias_do_problema | C13: =IFERROR(IF(INDEX('01_Formulario_A00'!$D:$D,MATCH("D01-DOC-DDE-001.PROBLEM_AND_OPPORTUNITY.EVIDENCIAS_DO_PROBLEMA",'01_Formulario_A00'!$A:$A,0))="","— (a preencher em 01_Formulario_A00)",INDEX('01_Formulario_A00'!$D:$D,MATCH("D01-DOC-DDE-001.PROBLEM_AND_OPPORTUNITY.EVIDENCIAS_DO_PROBLEMA",'01_Formulario_A00'!$A:$A,0))),"— (a preencher em 01_Formulario_A00)")
A14: D01-DOC-DDE-001.PURPOSE.PROPOSITO | B14: proposito | C14: =IFERROR(IF(INDEX('01_Formulario_A00'!$D:$D,MATCH("D01-DOC-DDE-001.PURPOSE.PROPOSITO",'01_Formulario_A00'!$A:$A,0))="","— (a preencher em 01_Formulario_A00)",INDEX('01_Formulario_A00'!$D:$D,MATCH("D01-DOC-DDE-001.PURPOSE.PROPOSITO",'01_Formulario_A00'!$A:$A,0))),"— (a preencher em 01_Formulario_A00)")
A15: D01-DOC-DDE-001.PURPOSE.MISSAO | B15: missao | C15: =IFERROR(IF(INDEX('01_Formulario_A00'!$D:$D,MATCH("D01-DOC-DDE-001.PURPOSE.MISSAO",'01_Formulario_A00'!$A:$A,0))="","— (a preencher em 01_Formulario_A00)",INDEX('01_Formulario_A00'!$D:$D,MATCH("D01-DOC-DDE-001.PURPOSE.MISSAO",'01_Formulario_A00'!$A:$A,0))),"— (a preencher em 01_Formulario_A00)")
A16: D01-DOC-DDE-001.PURPOSE.VISAO | B16: visao | C16: =IFERROR(IF(INDEX('01_Formulario_A00'!$D:$D,MATCH("D01-DOC-DDE-001.PURPOSE.VISAO",'01_Formulario_A00'!$A:$A,0))="","— (a preencher em 01_Formulario_A00)",INDEX('01_Formulario_A00'!$D:$D,MATCH("D01-DOC-DDE-001.PURPOSE.VISAO",'01_Formulario_A00'!$A:$A,0))),"— (a preencher em 01_Formulario_A00)")
A17: D01-DOC-DDE-001.PURPOSE.PRINCIPIOS | B17: principios | C17: =IFERROR(IF(INDEX('01_Formulario_A00'!$D:$D,MATCH("D01-DOC-DDE-001.PURPOSE.PRINCIPIOS",'01_Formulario_A00'!$A:$A,0))="","— (a preencher em 01_Formulario_A00)",INDEX('01_Formulario_A00'!$D:$D,MATCH("D01-DOC-DDE-001.PURPOSE.PRINCIPIOS",'01_Formulario_A00'!$A:$A,0))),"— (a preencher em 01_Formulario_A00)")
A18: D01-DOC-DDE-001.PURPOSE.VALORES | B18: valores | C18: =IFERROR(IF(INDEX('01_Formulario_A00'!$D:$D,MATCH("D01-DOC-DDE-001.PURPOSE.VALORES",'01_Formulario_A00'!$A:$A,0))="","— (a preencher em 01_Formulario_A00)",INDEX('01_Formulario_A00'!$D:$D,MATCH("D01-DOC-DDE-001.PURPOSE.VALORES",'01_Formulario_A00'!$A:$A,0))),"— (a preencher em 01_Formulario_A00)")
A19: D01-DOC-DDE-001.STRATEGIC_DIRECTION.OBJETIVOS_ESTRATEGICOS | B19: objetivos_estrategicos | C19: =IFERROR(IF(INDEX('01_Formulario_A00'!$D:$D,MATCH("D01-DOC-DDE-001.STRATEGIC_DIRECTION.OBJETIVOS_ESTRATEGICOS",'01_Formulario_A00'!$A:$A,0))="","— (a preencher em 01_Formulario_A00)",INDEX('01_Formulario_A00'!$D:$D,MATCH("D01-DOC-DDE-001.STRATEGIC_DIRECTION.OBJETIVOS_ESTRATEGICOS",'01_Formulario_A00'!$A:$A,0))),"— (a preencher em 01_Formulario_A00)")
A20: D01-DOC-DDE-001.STRATEGIC_DIRECTION.RESULTADOS_ESPERADOS | B20: resultados_esperados | C20: =IFERROR(IF(INDEX('01_Formulario_A00'!$D:$D,MATCH("D01-DOC-DDE-001.STRATEGIC_DIRECTION.RESULTADOS_ESPERADOS",'01_Formulario_A00'!$A:$A,0))="","— (a preencher em 01_Formulario_A00)",INDEX('01_Formulario_A00'!$D:$D,MATCH("D01-DOC-DDE-001.STRATEGIC_DIRECTION.RESULTADOS_ESPERADOS",'01_Formulario_A00'!$A:$A,0))),"— (a preencher em 01_Formulario_A00)")
A21: D01-DOC-DDE-001.STRATEGIC_DIRECTION.PRIORIDADES | B21: prioridades | C21: =IFERROR(IF(INDEX('01_Formulario_A00'!$D:$D,MATCH("D01-DOC-DDE-001.STRATEGIC_DIRECTION.PRIORIDADES",'01_Formulario_A00'!$A:$A,0))="","— (a preencher em 01_Formulario_A00)",INDEX('01_Formulario_A00'!$D:$D,MATCH("D01-DOC-DDE-001.STRATEGIC_DIRECTION.PRIORIDADES",'01_Formulario_A00'!$A:$A,0))),"— (a preencher em 01_Formulario_A00)")
A22: D01-DOC-DDE-001.STRATEGIC_DIRECTION.NAO_OBJETIVOS | B22: nao_objetivos | C22: =IFERROR(IF(INDEX('01_Formulario_A00'!$D:$D,MATCH("D01-DOC-DDE-001.STRATEGIC_DIRECTION.NAO_OBJETIVOS",'01_Formulario_A00'!$A:$A,0))="","— (a preencher em 01_Formulario_A00)",INDEX('01_Formulario_A00'!$D:$D,MATCH("D01-DOC-DDE-001.STRATEGIC_DIRECTION.NAO_OBJETIVOS",'01_Formulario_A00'!$A:$A,0))),"— (a preencher em 01_Formulario_A00)")
A23: D01-DOC-DDE-001.STRATEGIC_DIRECTION.HORIZONTE_TEMPORAL | B23: horizonte_temporal | C23: =IFERROR(IF(INDEX('01_Formulario_A00'!$D:$D,MATCH("D01-DOC-DDE-001.STRATEGIC_DIRECTION.HORIZONTE_TEMPORAL",'01_Formulario_A00'!$A:$A,0))="","— (a preencher em 01_Formulario_A00)",INDEX('01_Formulario_A00'!$D:$D,MATCH("D01-DOC-DDE-001.STRATEGIC_DIRECTION.HORIZONTE_TEMPORAL",'01_Formulario_A00'!$A:$A,0))),"— (a preencher em 01_Formulario_A00)")
A24: D01-DOC-DDE-001.ECOSYSTEM.PRODUTOS | B24: produtos | C24: =IFERROR(IF(INDEX('01_Formulario_A00'!$D:$D,MATCH("D01-DOC-DDE-001.ECOSYSTEM.PRODUTOS",'01_Formulario_A00'!$A:$A,0))="","— (a preencher em 01_Formulario_A00)",INDEX('01_Formulario_A00'!$D:$D,MATCH("D01-DOC-DDE-001.ECOSYSTEM.PRODUTOS",'01_Formulario_A00'!$A:$A,0))),"— (a preencher em 01_Formulario_A00)")
A25: D01-DOC-DDE-001.ECOSYSTEM.SERVICOS | B25: servicos | C25: =IFERROR(IF(INDEX('01_Formulario_A00'!$D:$D,MATCH("D01-DOC-DDE-001.ECOSYSTEM.SERVICOS",'01_Formulario_A00'!$A:$A,0))="","— (a preencher em 01_Formulario_A00)",INDEX('01_Formulario_A00'!$D:$D,MATCH("D01-DOC-DDE-001.ECOSYSTEM.SERVICOS",'01_Formulario_A00'!$A:$A,0))),"— (a preencher em 01_Formulario_A00)")
A26: D01-DOC-DDE-001.ECOSYSTEM.MARCAS | B26: marcas | C26: =IFERROR(IF(INDEX('01_Formulario_A00'!$D:$D,MATCH("D01-DOC-DDE-001.ECOSYSTEM.MARCAS",'01_Formulario_A00'!$A:$A,0))="","— (a preencher em 01_Formulario_A00)",INDEX('01_Formulario_A00'!$D:$D,MATCH("D01-DOC-DDE-001.ECOSYSTEM.MARCAS",'01_Formulario_A00'!$A:$A,0))),"— (a preencher em 01_Formulario_A00)")
A27: D01-DOC-DDE-001.ECOSYSTEM.AGENTES | B27: agentes | C27: =IFERROR(IF(INDEX('01_Formulario_A00'!$D:$D,MATCH("D01-DOC-DDE-001.ECOSYSTEM.AGENTES",'01_Formulario_A00'!$A:$A,0))="","— (a preencher em 01_Formulario_A00)",INDEX('01_Formulario_A00'!$D:$D,MATCH("D01-DOC-DDE-001.ECOSYSTEM.AGENTES",'01_Formulario_A00'!$A:$A,0))),"— (a preencher em 01_Formulario_A00)")
A28: D01-DOC-DDE-001.ECOSYSTEM.PLATAFORMAS | B28: plataformas | C28: =IFERROR(IF(INDEX('01_Formulario_A00'!$D:$D,MATCH("D01-DOC-DDE-001.ECOSYSTEM.PLATAFORMAS",'01_Formulario_A00'!$A:$A,0))="","— (a preencher em 01_Formulario_A00)",INDEX('01_Formulario_A00'!$D:$D,MATCH("D01-DOC-DDE-001.ECOSYSTEM.PLATAFORMAS",'01_Formulario_A00'!$A:$A,0))),"— (a preencher em 01_Formulario_A00)")
A29: D01-DOC-DDE-001.ECOSYSTEM.UNIDADES_DE_NEGOCIO | B29: unidades_de_negocio | C29: =IFERROR(IF(INDEX('01_Formulario_A00'!$D:$D,MATCH("D01-DOC-DDE-001.ECOSYSTEM.UNIDADES_DE_NEGOCIO",'01_Formulario_A00'!$A:$A,0))="","— (a preencher em 01_Formulario_A00)",INDEX('01_Formulario_A00'!$D:$D,MATCH("D01-DOC-DDE-001.ECOSYSTEM.UNIDADES_DE_NEGOCIO",'01_Formulario_A00'!$A:$A,0))),"— (a preencher em 01_Formulario_A00)")
A30: D01-DOC-DDE-001.GOVERNANCE.MODELO_DE_GOVERNANCA | B30: modelo_de_governanca | C30: =IFERROR(IF(INDEX('01_Formulario_A00'!$D:$D,MATCH("D01-DOC-DDE-001.GOVERNANCE.MODELO_DE_GOVERNANCA",'01_Formulario_A00'!$A:$A,0))="","— (a preencher em 01_Formulario_A00)",INDEX('01_Formulario_A00'!$D:$D,MATCH("D01-DOC-DDE-001.GOVERNANCE.MODELO_DE_GOVERNANCA",'01_Formulario_A00'!$A:$A,0))),"— (a preencher em 01_Formulario_A00)")
A31: D01-DOC-DDE-001.GOVERNANCE.PAPEIS_DECISORIOS | B31: papeis_decisorios | C31: =IFERROR(IF(INDEX('01_Formulario_A00'!$D:$D,MATCH("D01-DOC-DDE-001.GOVERNANCE.PAPEIS_DECISORIOS",'01_Formulario_A00'!$A:$A,0))="","— (a preencher em 01_Formulario_A00)",INDEX('01_Formulario_A00'!$D:$D,MATCH("D01-DOC-DDE-001.GOVERNANCE.PAPEIS_DECISORIOS",'01_Formulario_A00'!$A:$A,0))),"— (a preencher em 01_Formulario_A00)")
A32: D01-DOC-DDE-001.GOVERNANCE.DIREITOS_DE_DECISAO | B32: direitos_de_decisao | C32: =IFERROR(IF(INDEX('01_Formulario_A00'!$D:$D,MATCH("D01-DOC-DDE-001.GOVERNANCE.DIREITOS_DE_DECISAO",'01_Formulario_A00'!$A:$A,0))="","— (a preencher em 01_Formulario_A00)",INDEX('01_Formulario_A00'!$D:$D,MATCH("D01-DOC-DDE-001.GOVERNANCE.DIREITOS_DE_DECISAO",'01_Formulario_A00'!$A:$A,0))),"— (a preencher em 01_Formulario_A00)")
A33: D01-DOC-DDE-001.GOVERNANCE.GATES | B33: gates | C33: =IFERROR(IF(INDEX('01_Formulario_A00'!$D:$D,MATCH("D01-DOC-DDE-001.GOVERNANCE.GATES",'01_Formulario_A00'!$A:$A,0))="","— (a preencher em 01_Formulario_A00)",INDEX('01_Formulario_A00'!$D:$D,MATCH("D01-DOC-DDE-001.GOVERNANCE.GATES",'01_Formulario_A00'!$A:$A,0))),"— (a preencher em 01_Formulario_A00)")
A34: D01-DOC-DDE-001.GOVERNANCE.MECANISMOS_DE_CONTROLE | B34: mecanismos_de_controle | C34: =IFERROR(IF(INDEX('01_Formulario_A00'!$D:$D,MATCH("D01-DOC-DDE-001.GOVERNANCE.MECANISMOS_DE_CONTROLE",'01_Formulario_A00'!$A:$A,0))="","— (a preencher em 01_Formulario_A00)",INDEX('01_Formulario_A00'!$D:$D,MATCH("D01-DOC-DDE-001.GOVERNANCE.MECANISMOS_DE_CONTROLE",'01_Formulario_A00'!$A:$A,0))),"— (a preencher em 01_Formulario_A00)")
A35: D01-DOC-DDE-001.STAKEHOLDERS.STAKEHOLDERS | B35: stakeholders | C35: =IFERROR(IF(INDEX('01_Formulario_A00'!$D:$D,MATCH("D01-DOC-DDE-001.STAKEHOLDERS.STAKEHOLDERS",'01_Formulario_A00'!$A:$A,0))="","— (a preencher em 01_Formulario_A00)",INDEX('01_Formulario_A00'!$D:$D,MATCH("D01-DOC-DDE-001.STAKEHOLDERS.STAKEHOLDERS",'01_Formulario_A00'!$A:$A,0))),"— (a preencher em 01_Formulario_A00)")
A36: D01-DOC-DDE-001.STAKEHOLDERS.INTERESSE | B36: interesse | C36: =IFERROR(IF(INDEX('01_Formulario_A00'!$D:$D,MATCH("D01-DOC-DDE-001.STAKEHOLDERS.INTERESSE",'01_Formulario_A00'!$A:$A,0))="","— (a preencher em 01_Formulario_A00)",INDEX('01_Formulario_A00'!$D:$D,MATCH("D01-DOC-DDE-001.STAKEHOLDERS.INTERESSE",'01_Formulario_A00'!$A:$A,0))),"— (a preencher em 01_Formulario_A00)")
A37: D01-DOC-DDE-001.STAKEHOLDERS.INFLUENCIA | B37: influencia | C37: =IFERROR(IF(INDEX('01_Formulario_A00'!$D:$D,MATCH("D01-DOC-DDE-001.STAKEHOLDERS.INFLUENCIA",'01_Formulario_A00'!$A:$A,0))="","— (a preencher em 01_Formulario_A00)",INDEX('01_Formulario_A00'!$D:$D,MATCH("D01-DOC-DDE-001.STAKEHOLDERS.INFLUENCIA",'01_Formulario_A00'!$A:$A,0))),"— (a preencher em 01_Formulario_A00)")
A38: D01-DOC-DDE-001.STAKEHOLDERS.RELACIONAMENTO | B38: relacionamento | C38: =IFERROR(IF(INDEX('01_Formulario_A00'!$D:$D,MATCH("D01-DOC-DDE-001.STAKEHOLDERS.RELACIONAMENTO",'01_Formulario_A00'!$A:$A,0))="","— (a preencher em 01_Formulario_A00)",INDEX('01_Formulario_A00'!$D:$D,MATCH("D01-DOC-DDE-001.STAKEHOLDERS.RELACIONAMENTO",'01_Formulario_A00'!$A:$A,0))),"— (a preencher em 01_Formulario_A00)")
A39: D01-DOC-DDE-001.STRATEGIC_DEPENDENCIES.DEPENDENCIAS | B39: dependencias | C39: =IFERROR(IF(INDEX('01_Formulario_A00'!$D:$D,MATCH("D01-DOC-DDE-001.STRATEGIC_DEPENDENCIES.DEPENDENCIAS",'01_Formulario_A00'!$A:$A,0))="","— (a preencher em 01_Formulario_A00)",INDEX('01_Formulario_A00'!$D:$D,MATCH("D01-DOC-DDE-001.STRATEGIC_DEPENDENCIES.DEPENDENCIAS",'01_Formulario_A00'!$A:$A,0))),"— (a preencher em 01_Formulario_A00)")
A40: D01-DOC-DDE-001.STRATEGIC_DEPENDENCIES.RESTRICOES | B40: restricoes | C40: =IFERROR(IF(INDEX('01_Formulario_A00'!$D:$D,MATCH("D01-DOC-DDE-001.STRATEGIC_DEPENDENCIES.RESTRICOES",'01_Formulario_A00'!$A:$A,0))="","— (a preencher em 01_Formulario_A00)",INDEX('01_Formulario_A00'!$D:$D,MATCH("D01-DOC-DDE-001.STRATEGIC_DEPENDENCIES.RESTRICOES",'01_Formulario_A00'!$A:$A,0))),"— (a preencher em 01_Formulario_A00)")
A41: D01-DOC-DDE-001.STRATEGIC_DEPENDENCIES.PREMISSAS | B41: premissas | C41: =IFERROR(IF(INDEX('01_Formulario_A00'!$D:$D,MATCH("D01-DOC-DDE-001.STRATEGIC_DEPENDENCIES.PREMISSAS",'01_Formulario_A00'!$A:$A,0))="","— (a preencher em 01_Formulario_A00)",INDEX('01_Formulario_A00'!$D:$D,MATCH("D01-DOC-DDE-001.STRATEGIC_DEPENDENCIES.PREMISSAS",'01_Formulario_A00'!$A:$A,0))),"— (a preencher em 01_Formulario_A00)")
A42: D01-DOC-DDE-001.RISKS.RISCOS_ESTRATEGICOS | B42: riscos_estrategicos | C42: =IFERROR(IF(INDEX('01_Formulario_A00'!$D:$D,MATCH("D01-DOC-DDE-001.RISKS.RISCOS_ESTRATEGICOS",'01_Formulario_A00'!$A:$A,0))="","— (a preencher em 01_Formulario_A00)",INDEX('01_Formulario_A00'!$D:$D,MATCH("D01-DOC-DDE-001.RISKS.RISCOS_ESTRATEGICOS",'01_Formulario_A00'!$A:$A,0))),"— (a preencher em 01_Formulario_A00)")
A43: D01-DOC-DDE-001.RISKS.MITIGACOES_EXISTENTES | B43: mitigacoes_existentes | C43: =IFERROR(IF(INDEX('01_Formulario_A00'!$D:$D,MATCH("D01-DOC-DDE-001.RISKS.MITIGACOES_EXISTENTES",'01_Formulario_A00'!$A:$A,0))="","— (a preencher em 01_Formulario_A00)",INDEX('01_Formulario_A00'!$D:$D,MATCH("D01-DOC-DDE-001.RISKS.MITIGACOES_EXISTENTES",'01_Formulario_A00'!$A:$A,0))),"— (a preencher em 01_Formulario_A00)")
A44: D01-DOC-DDE-001.MEASUREMENT.INDICADORES | B44: indicadores | C44: =IFERROR(IF(INDEX('01_Formulario_A00'!$D:$D,MATCH("D01-DOC-DDE-001.MEASUREMENT.INDICADORES",'01_Formulario_A00'!$A:$A,0))="","— (a preencher em 01_Formulario_A00)",INDEX('01_Formulario_A00'!$D:$D,MATCH("D01-DOC-DDE-001.MEASUREMENT.INDICADORES",'01_Formulario_A00'!$A:$A,0))),"— (a preencher em 01_Formulario_A00)")
A45: D01-DOC-DDE-001.MEASUREMENT.METAS | B45: metas | C45: =IFERROR(IF(INDEX('01_Formulario_A00'!$D:$D,MATCH("D01-DOC-DDE-001.MEASUREMENT.METAS",'01_Formulario_A00'!$A:$A,0))="","— (a preencher em 01_Formulario_A00)",INDEX('01_Formulario_A00'!$D:$D,MATCH("D01-DOC-DDE-001.MEASUREMENT.METAS",'01_Formulario_A00'!$A:$A,0))),"— (a preencher em 01_Formulario_A00)")
A46: D01-DOC-DDE-001.MEASUREMENT.CRITERIOS_DE_SUCESSO | B46: criterios_de_sucesso | C46: =IFERROR(IF(INDEX('01_Formulario_A00'!$D:$D,MATCH("D01-DOC-DDE-001.MEASUREMENT.CRITERIOS_DE_SUCESSO",'01_Formulario_A00'!$A:$A,0))="","— (a preencher em 01_Formulario_A00)",INDEX('01_Formulario_A00'!$D:$D,MATCH("D01-DOC-DDE-001.MEASUREMENT.CRITERIOS_DE_SUCESSO",'01_Formulario_A00'!$A:$A,0))),"— (a preencher em 01_Formulario_A00)")
A47: D01-DOC-DDE-001.DECISIONS.DECISOES_VIGENTES | B47: decisoes_vigentes | C47: =IFERROR(IF(INDEX('01_Formulario_A00'!$D:$D,MATCH("D01-DOC-DDE-001.DECISIONS.DECISOES_VIGENTES",'01_Formulario_A00'!$A:$A,0))="","— (a preencher em 01_Formulario_A00)",INDEX('01_Formulario_A00'!$D:$D,MATCH("D01-DOC-DDE-001.DECISIONS.DECISOES_VIGENTES",'01_Formulario_A00'!$A:$A,0))),"— (a preencher em 01_Formulario_A00)")
A48: D01-DOC-DDE-001.DECISIONS.DECISOES_PENDENTES | B48: decisoes_pendentes | C48: =IFERROR(IF(INDEX('01_Formulario_A00'!$D:$D,MATCH("D01-DOC-DDE-001.DECISIONS.DECISOES_PENDENTES",'01_Formulario_A00'!$A:$A,0))="","— (a preencher em 01_Formulario_A00)",INDEX('01_Formulario_A00'!$D:$D,MATCH("D01-DOC-DDE-001.DECISIONS.DECISOES_PENDENTES",'01_Formulario_A00'!$A:$A,0))),"— (a preencher em 01_Formulario_A00)")
A49: D01-DOC-TAP-001 — Termo de Abertura do Ecossistema [PRE_PREENCHIDO/PENDENTE]
A50: D01-DOC-TAP-001.IDENTIFICATION.TITULO | B50: titulo | C50: =IFERROR(IF(INDEX('01_Formulario_A00'!$D:$D,MATCH("D01-DOC-TAP-001.IDENTIFICATION.TITULO",'01_Formulario_A00'!$A:$A,0))="","— (a preencher em 01_Formulario_A00)",INDEX('01_Formulario_A00'!$D:$D,MATCH("D01-DOC-TAP-001.IDENTIFICATION.TITULO",'01_Formulario_A00'!$A:$A,0))),"— (a preencher em 01_Formulario_A00)")
A51: D01-DOC-TAP-001.IDENTIFICATION.JUSTIFICATIVA | B51: justificativa | C51: =IFERROR(IF(INDEX('01_Formulario_A00'!$D:$D,MATCH("D01-DOC-TAP-001.IDENTIFICATION.JUSTIFICATIVA",'01_Formulario_A00'!$A:$A,0))="","— (a preencher em 01_Formulario_A00)",INDEX('01_Formulario_A00'!$D:$D,MATCH("D01-DOC-TAP-001.IDENTIFICATION.JUSTIFICATIVA",'01_Formulario_A00'!$A:$A,0))),"— (a preencher em 01_Formulario_A00)")
A52: D01-DOC-TAP-001.IDENTIFICATION.CONTEXTO | B52: contexto | C52: =IFERROR(IF(INDEX('01_Formulario_A00'!$D:$D,MATCH("D01-DOC-TAP-001.IDENTIFICATION.CONTEXTO",'01_Formulario_A00'!$A:$A,0))="","— (a preencher em 01_Formulario_A00)",INDEX('01_Formulario_A00'!$D:$D,MATCH("D01-DOC-TAP-001.IDENTIFICATION.CONTEXTO",'01_Formulario_A00'!$A:$A,0))),"— (a preencher em 01_Formulario_A00)")
A53: D01-DOC-TAP-001.IDENTIFICATION.SPONSOR | B53: sponsor | C53: =IFERROR(IF(INDEX('01_Formulario_A00'!$D:$D,MATCH("D01-DOC-TAP-001.IDENTIFICATION.SPONSOR",'01_Formulario_A00'!$A:$A,0))="","— (a preencher em 01_Formulario_A00)",INDEX('01_Formulario_A00'!$D:$D,MATCH("D01-DOC-TAP-001.IDENTIFICATION.SPONSOR",'01_Formulario_A00'!$A:$A,0))),"— (a preencher em 01_Formulario_A00)")
A54: D01-DOC-TAP-001.IDENTIFICATION.OWNER | B54: owner | C54: =IFERROR(IF(INDEX('01_Formulario_A00'!$D:$D,MATCH("D01-DOC-TAP-001.IDENTIFICATION.OWNER",'01_Formulario_A00'!$A:$A,0))="","— (a preencher em 01_Formulario_A00)",INDEX('01_Formulario_A00'!$D:$D,MATCH("D01-DOC-TAP-001.IDENTIFICATION.OWNER",'01_Formulario_A00'!$A:$A,0))),"— (a preencher em 01_Formulario_A00)")
A55: D01-DOC-TAP-001.OBJECTIVE.OBJETIVO_GERAL | B55: objetivo_geral | C55: =IFERROR(IF(INDEX('01_Formulario_A00'!$D:$D,MATCH("D01-DOC-TAP-001.OBJECTIVE.OBJETIVO_GERAL",'01_Formulario_A00'!$A:$A,0))="","— (a preencher em 01_Formulario_A00)",INDEX('01_Formulario_A00'!$D:$D,MATCH("D01-DOC-TAP-001.OBJECTIVE.OBJETIVO_GERAL",'01_Formulario_A00'!$A:$A,0))),"— (a preencher em 01_Formulario_A00)")
A56: D01-DOC-TAP-001.OBJECTIVE.OBJETIVOS_ESPECIFICOS | B56: objetivos_especificos | C56: =IFERROR(IF(INDEX('01_Formulario_A00'!$D:$D,MATCH("D01-DOC-TAP-001.OBJECTIVE.OBJETIVOS_ESPECIFICOS",'01_Formulario_A00'!$A:$A,0))="","— (a preencher em 01_Formulario_A00)",INDEX('01_Formulario_A00'!$D:$D,MATCH("D01-DOC-TAP-001.OBJECTIVE.OBJETIVOS_ESPECIFICOS",'01_Formulario_A00'!$A:$A,0))),"— (a preencher em 01_Formulario_A00)")
A57: D01-DOC-TAP-001.OBJECTIVE.RESULTADO_FINAL_ESPERADO | B57: resultado_final_esperado | C57: =IFERROR(IF(INDEX('01_Formulario_A00'!$D:$D,MATCH("D01-DOC-TAP-001.OBJECTIVE.RESULTADO_FINAL_ESPERADO",'01_Formulario_A00'!$A:$A,0))="","— (a preencher em 01_Formulario_A00)",INDEX('01_Formulario_A00'!$D:$D,MATCH("D01-DOC-TAP-001.OBJECTIVE.RESULTADO_FINAL_ESPERADO",'01_Formulario_A00'!$A:$A,0))),"— (a preencher em 01_Formulario_A00)")
A58: D01-DOC-TAP-001.SCOPE.ESCOPO_INCLUIDO | B58: escopo_incluido | C58: =IFERROR(IF(INDEX('01_Formulario_A00'!$D:$D,MATCH("D01-DOC-TAP-001.SCOPE.ESCOPO_INCLUIDO",'01_Formulario_A00'!$A:$A,0))="","— (a preencher em 01_Formulario_A00)",INDEX('01_Formulario_A00'!$D:$D,MATCH("D01-DOC-TAP-001.SCOPE.ESCOPO_INCLUIDO",'01_Formulario_A00'!$A:$A,0))),"— (a preencher em 01_Formulario_A00)")
A59: D01-DOC-TAP-001.SCOPE.ESCOPO_EXCLUIDO | B59: escopo_excluido | C59: =IFERROR(IF(INDEX('01_Formulario_A00'!$D:$D,MATCH("D01-DOC-TAP-001.SCOPE.ESCOPO_EXCLUIDO",'01_Formulario_A00'!$A:$A,0))="","— (a preencher em 01_Formulario_A00)",INDEX('01_Formulario_A00'!$D:$D,MATCH("D01-DOC-TAP-001.SCOPE.ESCOPO_EXCLUIDO",'01_Formulario_A00'!$A:$A,0))),"— (a preencher em 01_Formulario_A00)")
A60: D01-DOC-TAP-001.SCOPE.FRONTEIRAS | B60: fronteiras | C60: =IFERROR(IF(INDEX('01_Formulario_A00'!$D:$D,MATCH("D01-DOC-TAP-001.SCOPE.FRONTEIRAS",'01_Formulario_A00'!$A:$A,0))="","— (a preencher em 01_Formulario_A00)",INDEX('01_Formulario_A00'!$D:$D,MATCH("D01-DOC-TAP-001.SCOPE.FRONTEIRAS",'01_Formulario_A00'!$A:$A,0))),"— (a preencher em 01_Formulario_A00)")
A61: D01-DOC-TAP-001.DELIVERABLES.ENTREGAVEIS_PRINCIPAIS | B61: entregaveis_principais | C61: =IFERROR(IF(INDEX('01_Formulario_A00'!$D:$D,MATCH("D01-DOC-TAP-001.DELIVERABLES.ENTREGAVEIS_PRINCIPAIS",'01_Formulario_A00'!$A:$A,0))="","— (a preencher em 01_Formulario_A00)",INDEX('01_Formulario_A00'!$D:$D,MATCH("D01-DOC-TAP-001.DELIVERABLES.ENTREGAVEIS_PRINCIPAIS",'01_Formulario_A00'!$A:$A,0))),"— (a preencher em 01_Formulario_A00)")
A62: D01-DOC-TAP-001.DELIVERABLES.DEFINITION_OF_DONE | B62: definition_of_done | C62: =IFERROR(IF(INDEX('01_Formulario_A00'!$D:$D,MATCH("D01-DOC-TAP-001.DELIVERABLES.DEFINITION_OF_DONE",'01_Formulario_A00'!$A:$A,0))="","— (a preencher em 01_Formulario_A00)",INDEX('01_Formulario_A00'!$D:$D,MATCH("D01-DOC-TAP-001.DELIVERABLES.DEFINITION_OF_DONE",'01_Formulario_A00'!$A:$A,0))),"— (a preencher em 01_Formulario_A00)")
A63: D01-DOC-TAP-001.MILESTONES.MARCOS | B63: marcos | C63: =IFERROR(IF(INDEX('01_Formulario_A00'!$D:$D,MATCH("D01-DOC-TAP-001.MILESTONES.MARCOS",'01_Formulario_A00'!$A:$A,0))="","— (a preencher em 01_Formulario_A00)",INDEX('01_Formulario_A00'!$D:$D,MATCH("D01-DOC-TAP-001.MILESTONES.MARCOS",'01_Formulario_A00'!$A:$A,0))),"— (a preencher em 01_Formulario_A00)")
A64: D01-DOC-TAP-001.MILESTONES.DATAS_EXISTENTES | B64: datas_existentes | C64: =IFERROR(IF(INDEX('01_Formulario_A00'!$D:$D,MATCH("D01-DOC-TAP-001.MILESTONES.DATAS_EXISTENTES",'01_Formulario_A00'!$A:$A,0))="","— (a preencher em 01_Formulario_A00)",INDEX('01_Formulario_A00'!$D:$D,MATCH("D01-DOC-TAP-001.MILESTONES.DATAS_EXISTENTES",'01_Formulario_A00'!$A:$A,0))),"— (a preencher em 01_Formulario_A00)")
A65: D01-DOC-TAP-001.STAKEHOLDERS.PARTICIPANTES | B65: participantes | C65: =IFERROR(IF(INDEX('01_Formulario_A00'!$D:$D,MATCH("D01-DOC-TAP-001.STAKEHOLDERS.PARTICIPANTES",'01_Formulario_A00'!$A:$A,0))="","— (a preencher em 01_Formulario_A00)",INDEX('01_Formulario_A00'!$D:$D,MATCH("D01-DOC-TAP-001.STAKEHOLDERS.PARTICIPANTES",'01_Formulario_A00'!$A:$A,0))),"— (a preencher em 01_Formulario_A00)")
A66: D01-DOC-TAP-001.STAKEHOLDERS.PAPEIS | B66: papeis | C66: =IFERROR(IF(INDEX('01_Formulario_A00'!$D:$D,MATCH("D01-DOC-TAP-001.STAKEHOLDERS.PAPEIS",'01_Formulario_A00'!$A:$A,0))="","— (a preencher em 01_Formulario_A00)",INDEX('01_Formulario_A00'!$D:$D,MATCH("D01-DOC-TAP-001.STAKEHOLDERS.PAPEIS",'01_Formulario_A00'!$A:$A,0))),"— (a preencher em 01_Formulario_A00)")
A67: D01-DOC-TAP-001.STAKEHOLDERS.RESPONSABILIDADES | B67: responsabilidades | C67: =IFERROR(IF(INDEX('01_Formulario_A00'!$D:$D,MATCH("D01-DOC-TAP-001.STAKEHOLDERS.RESPONSABILIDADES",'01_Formulario_A00'!$A:$A,0))="","— (a preencher em 01_Formulario_A00)",INDEX('01_Formulario_A00'!$D:$D,MATCH("D01-DOC-TAP-001.STAKEHOLDERS.RESPONSABILIDADES",'01_Formulario_A00'!$A:$A,0))),"— (a preencher em 01_Formulario_A00)")
A68: D01-DOC-TAP-001.CONSTRAINTS.RESTRICOES | B68: restricoes | C68: =IFERROR(IF(INDEX('01_Formulario_A00'!$D:$D,MATCH("D01-DOC-TAP-001.CONSTRAINTS.RESTRICOES",'01_Formulario_A00'!$A:$A,0))="","— (a preencher em 01_Formulario_A00)",INDEX('01_Formulario_A00'!$D:$D,MATCH("D01-DOC-TAP-001.CONSTRAINTS.RESTRICOES",'01_Formulario_A00'!$A:$A,0))),"— (a preencher em 01_Formulario_A00)")
A69: D01-DOC-TAP-001.CONSTRAINTS.PREMISSAS | B69: premissas | C69: =IFERROR(IF(INDEX('01_Formulario_A00'!$D:$D,MATCH("D01-DOC-TAP-001.CONSTRAINTS.PREMISSAS",'01_Formulario_A00'!$A:$A,0))="","— (a preencher em 01_Formulario_A00)",INDEX('01_Formulario_A00'!$D:$D,MATCH("D01-DOC-TAP-001.CONSTRAINTS.PREMISSAS",'01_Formulario_A00'!$A:$A,0))),"— (a preencher em 01_Formulario_A00)")
A70: D01-DOC-TAP-001.CONSTRAINTS.DEPENDENCIAS | B70: dependencias | C70: =IFERROR(IF(INDEX('01_Formulario_A00'!$D:$D,MATCH("D01-DOC-TAP-001.CONSTRAINTS.DEPENDENCIAS",'01_Formulario_A00'!$A:$A,0))="","— (a preencher em 01_Formulario_A00)",INDEX('01_Formulario_A00'!$D:$D,MATCH("D01-DOC-TAP-001.CONSTRAINTS.DEPENDENCIAS",'01_Formulario_A00'!$A:$A,0))),"— (a preencher em 01_Formulario_A00)")
A71: D01-DOC-TAP-001.RESOURCES.CAPACIDADE | B71: capacidade | C71: =IFERROR(IF(INDEX('01_Formulario_A00'!$D:$D,MATCH("D01-DOC-TAP-001.RESOURCES.CAPACIDADE",'01_Formulario_A00'!$A:$A,0))="","— (a preencher em 01_Formulario_A00)",INDEX('01_Formulario_A00'!$D:$D,MATCH("D01-DOC-TAP-001.RESOURCES.CAPACIDADE",'01_Formulario_A00'!$A:$A,0))),"— (a preencher em 01_Formulario_A00)")
A72: D01-DOC-TAP-001.RESOURCES.RECURSOS | B72: recursos | C72: =IFERROR(IF(INDEX('01_Formulario_A00'!$D:$D,MATCH("D01-DOC-TAP-001.RESOURCES.RECURSOS",'01_Formulario_A00'!$A:$A,0))="","— (a preencher em 01_Formulario_A00)",INDEX('01_Formulario_A00'!$D:$D,MATCH("D01-DOC-TAP-001.RESOURCES.RECURSOS",'01_Formulario_A00'!$A:$A,0))),"— (a preencher em 01_Formulario_A00)")
A73: D01-DOC-TAP-001.RESOURCES.ORCAMENTO | B73: orcamento | C73: =IFERROR(IF(INDEX('01_Formulario_A00'!$D:$D,MATCH("D01-DOC-TAP-001.RESOURCES.ORCAMENTO",'01_Formulario_A00'!$A:$A,0))="","— (a preencher em 01_Formulario_A00)",INDEX('01_Formulario_A00'!$D:$D,MATCH("D01-DOC-TAP-001.RESOURCES.ORCAMENTO",'01_Formulario_A00'!$A:$A,0))),"— (a preencher em 01_Formulario_A00)")
A74: D01-DOC-TAP-001.SUCCESS.CRITERIOS_DE_ACEITE | B74: criterios_de_aceite | C74: =IFERROR(IF(INDEX('01_Formulario_A00'!$D:$D,MATCH("D01-DOC-TAP-001.SUCCESS.CRITERIOS_DE_ACEITE",'01_Formulario_A00'!$A:$A,0))="","— (a preencher em 01_Formulario_A00)",INDEX('01_Formulario_A00'!$D:$D,MATCH("D01-DOC-TAP-001.SUCCESS.CRITERIOS_DE_ACEITE",'01_Formulario_A00'!$A:$A,0))),"— (a preencher em 01_Formulario_A00)")
A75: D01-DOC-TAP-001.SUCCESS.INDICADORES_DE_SUCESSO | B75: indicadores_de_sucesso | C75: =IFERROR(IF(INDEX('01_Formulario_A00'!$D:$D,MATCH("D01-DOC-TAP-001.SUCCESS.INDICADORES_DE_SUCESSO",'01_Formulario_A00'!$A:$A,0))="","— (a preencher em 01_Formulario_A00)",INDEX('01_Formulario_A00'!$D:$D,MATCH("D01-DOC-TAP-001.SUCCESS.INDICADORES_DE_SUCESSO",'01_Formulario_A00'!$A:$A,0))),"— (a preencher em 01_Formulario_A00)")
A76: D01-DOC-TAP-001.RISKS.RISCOS_INICIAIS | B76: riscos_iniciais | C76: =IFERROR(IF(INDEX('01_Formulario_A00'!$D:$D,MATCH("D01-DOC-TAP-001.RISKS.RISCOS_INICIAIS",'01_Formulario_A00'!$A:$A,0))="","— (a preencher em 01_Formulario_A00)",INDEX('01_Formulario_A00'!$D:$D,MATCH("D01-DOC-TAP-001.RISKS.RISCOS_INICIAIS",'01_Formulario_A00'!$A:$A,0))),"— (a preencher em 01_Formulario_A00)")
A77: D01-DOC-TAP-001.APPROVALS.APROVADORES | B77: aprovadores | C77: =IFERROR(IF(INDEX('01_Formulario_A00'!$D:$D,MATCH("D01-DOC-TAP-001.APPROVALS.APROVADORES",'01_Formulario_A00'!$A:$A,0))="","— (a preencher em 01_Formulario_A00)",INDEX('01_Formulario_A00'!$D:$D,MATCH("D01-DOC-TAP-001.APPROVALS.APROVADORES",'01_Formulario_A00'!$A:$A,0))),"— (a preencher em 01_Formulario_A00)")
A78: D01-DOC-TAP-001.APPROVALS.STATUS_APROVACAO | B78: status_aprovacao | C78: =IFERROR(IF(INDEX('01_Formulario_A00'!$D:$D,MATCH("D01-DOC-TAP-001.APPROVALS.STATUS_APROVACAO",'01_Formulario_A00'!$A:$A,0))="","— (a preencher em 01_Formulario_A00)",INDEX('01_Formulario_A00'!$D:$D,MATCH("D01-DOC-TAP-001.APPROVALS.STATUS_APROVACAO",'01_Formulario_A00'!$A:$A,0))),"— (a preencher em 01_Formulario_A00)")
A79: D01-DOC-MNE-001 — Modelo de Negócio do Ecossistema [PRE_PREENCHIDO/PENDENTE]
A80: D01-DOC-MNE-001.CUSTOMER.SEGMENTOS | B80: segmentos | C80: =IFERROR(IF(INDEX('01_Formulario_A00'!$D:$D,MATCH("D01-DOC-MNE-001.CUSTOMER.SEGMENTOS",'01_Formulario_A00'!$A:$A,0))="","— (a preencher em 01_Formulario_A00)",INDEX('01_Formulario_A00'!$D:$D,MATCH("D01-DOC-MNE-001.CUSTOMER.SEGMENTOS",'01_Formulario_A00'!$A:$A,0))),"— (a preencher em 01_Formulario_A00)")
A81: D01-DOC-MNE-001.CUSTOMER.USUARIOS | B81: usuarios | C81: =IFERROR(IF(INDEX('01_Formulario_A00'!$D:$D,MATCH("D01-DOC-MNE-001.CUSTOMER.USUARIOS",'01_Formulario_A00'!$A:$A,0))="","— (a preencher em 01_Formulario_A00)",INDEX('01_Formulario_A00'!$D:$D,MATCH("D01-DOC-MNE-001.CUSTOMER.USUARIOS",'01_Formulario_A00'!$A:$A,0))),"— (a preencher em 01_Formulario_A00)")
A82: D01-DOC-MNE-001.CUSTOMER.CLIENTES | B82: clientes | C82: =IFERROR(IF(INDEX('01_Formulario_A00'!$D:$D,MATCH("D01-DOC-MNE-001.CUSTOMER.CLIENTES",'01_Formulario_A00'!$A:$A,0))="","— (a preencher em 01_Formulario_A00)",INDEX('01_Formulario_A00'!$D:$D,MATCH("D01-DOC-MNE-001.CUSTOMER.CLIENTES",'01_Formulario_A00'!$A:$A,0))),"— (a preencher em 01_Formulario_A00)")
A83: D01-DOC-MNE-001.CUSTOMER.PROBLEMAS | B83: problemas | C83: =IFERROR(IF(INDEX('01_Formulario_A00'!$D:$D,MATCH("D01-DOC-MNE-001.CUSTOMER.PROBLEMAS",'01_Formulario_A00'!$A:$A,0))="","— (a preencher em 01_Formulario_A00)",INDEX('01_Formulario_A00'!$D:$D,MATCH("D01-DOC-MNE-001.CUSTOMER.PROBLEMAS",'01_Formulario_A00'!$A:$A,0))),"— (a preencher em 01_Formulario_A00)")
A84: D01-DOC-MNE-001.CUSTOMER.JTBD | B84: jtbd | C84: =IFERROR(IF(INDEX('01_Formulario_A00'!$D:$D,MATCH("D01-DOC-MNE-001.CUSTOMER.JTBD",'01_Formulario_A00'!$A:$A,0))="","— (a preencher em 01_Formulario_A00)",INDEX('01_Formulario_A00'!$D:$D,MATCH("D01-DOC-MNE-001.CUSTOMER.JTBD",'01_Formulario_A00'!$A:$A,0))),"— (a preencher em 01_Formulario_A00)")
A85: D01-DOC-MNE-001.VALUE.PROPOSTAS_DE_VALOR | B85: propostas_de_valor | C85: =IFERROR(IF(INDEX('01_Formulario_A00'!$D:$D,MATCH("D01-DOC-MNE-001.VALUE.PROPOSTAS_DE_VALOR",'01_Formulario_A00'!$A:$A,0))="","— (a preencher em 01_Formulario_A00)",INDEX('01_Formulario_A00'!$D:$D,MATCH("D01-DOC-MNE-001.VALUE.PROPOSTAS_DE_VALOR",'01_Formulario_A00'!$A:$A,0))),"— (a preencher em 01_Formulario_A00)")
A86: D01-DOC-MNE-001.VALUE.BENEFICIOS | B86: beneficios | C86: =IFERROR(IF(INDEX('01_Formulario_A00'!$D:$D,MATCH("D01-DOC-MNE-001.VALUE.BENEFICIOS",'01_Formulario_A00'!$A:$A,0))="","— (a preencher em 01_Formulario_A00)",INDEX('01_Formulario_A00'!$D:$D,MATCH("D01-DOC-MNE-001.VALUE.BENEFICIOS",'01_Formulario_A00'!$A:$A,0))),"— (a preencher em 01_Formulario_A00)")
A87: D01-DOC-MNE-001.VALUE.DIFERENCIADORES | B87: diferenciadores | C87: =IFERROR(IF(INDEX('01_Formulario_A00'!$D:$D,MATCH("D01-DOC-MNE-001.VALUE.DIFERENCIADORES",'01_Formulario_A00'!$A:$A,0))="","— (a preencher em 01_Formulario_A00)",INDEX('01_Formulario_A00'!$D:$D,MATCH("D01-DOC-MNE-001.VALUE.DIFERENCIADORES",'01_Formulario_A00'!$A:$A,0))),"— (a preencher em 01_Formulario_A00)")
A88: D01-DOC-MNE-001.VALUE.ALTERNATIVAS_EXISTENTES | B88: alternativas_existentes | C88: =IFERROR(IF(INDEX('01_Formulario_A00'!$D:$D,MATCH("D01-DOC-MNE-001.VALUE.ALTERNATIVAS_EXISTENTES",'01_Formulario_A00'!$A:$A,0))="","— (a preencher em 01_Formulario_A00)",INDEX('01_Formulario_A00'!$D:$D,MATCH("D01-DOC-MNE-001.VALUE.ALTERNATIVAS_EXISTENTES",'01_Formulario_A00'!$A:$A,0))),"— (a preencher em 01_Formulario_A00)")
A89: D01-DOC-MNE-001.OFFERINGS.PRODUTOS | B89: produtos | C89: =IFERROR(IF(INDEX('01_Formulario_A00'!$D:$D,MATCH("D01-DOC-MNE-001.OFFERINGS.PRODUTOS",'01_Formulario_A00'!$A:$A,0))="","— (a preencher em 01_Formulario_A00)",INDEX('01_Formulario_A00'!$D:$D,MATCH("D01-DOC-MNE-001.OFFERINGS.PRODUTOS",'01_Formulario_A00'!$A:$A,0))),"— (a preencher em 01_Formulario_A00)")
A90: D01-DOC-MNE-001.OFFERINGS.SERVICOS | B90: servicos | C90: =IFERROR(IF(INDEX('01_Formulario_A00'!$D:$D,MATCH("D01-DOC-MNE-001.OFFERINGS.SERVICOS",'01_Formulario_A00'!$A:$A,0))="","— (a preencher em 01_Formulario_A00)",INDEX('01_Formulario_A00'!$D:$D,MATCH("D01-DOC-MNE-001.OFFERINGS.SERVICOS",'01_Formulario_A00'!$A:$A,0))),"— (a preencher em 01_Formulario_A00)")
A91: D01-DOC-MNE-001.OFFERINGS.PLANOS | B91: planos | C91: =IFERROR(IF(INDEX('01_Formulario_A00'!$D:$D,MATCH("D01-DOC-MNE-001.OFFERINGS.PLANOS",'01_Formulario_A00'!$A:$A,0))="","— (a preencher em 01_Formulario_A00)",INDEX('01_Formulario_A00'!$D:$D,MATCH("D01-DOC-MNE-001.OFFERINGS.PLANOS",'01_Formulario_A00'!$A:$A,0))),"— (a preencher em 01_Formulario_A00)")
A92: D01-DOC-MNE-001.OFFERINGS.OFERTAS | B92: ofertas | C92: =IFERROR(IF(INDEX('01_Formulario_A00'!$D:$D,MATCH("D01-DOC-MNE-001.OFFERINGS.OFERTAS",'01_Formulario_A00'!$A:$A,0))="","— (a preencher em 01_Formulario_A00)",INDEX('01_Formulario_A00'!$D:$D,MATCH("D01-DOC-MNE-001.OFFERINGS.OFERTAS",'01_Formulario_A00'!$A:$A,0))),"— (a preencher em 01_Formulario_A00)")
A93: D01-DOC-MNE-001.CHANNELS.AQUISICAO | B93: aquisicao | C93: =IFERROR(IF(INDEX('01_Formulario_A00'!$D:$D,MATCH("D01-DOC-MNE-001.CHANNELS.AQUISICAO",'01_Formulario_A00'!$A:$A,0))="","— (a preencher em 01_Formulario_A00)",INDEX('01_Formulario_A00'!$D:$D,MATCH("D01-DOC-MNE-001.CHANNELS.AQUISICAO",'01_Formulario_A00'!$A:$A,0))),"— (a preencher em 01_Formulario_A00)")
A94: D01-DOC-MNE-001.CHANNELS.DISTRIBUICAO | B94: distribuicao | C94: =IFERROR(IF(INDEX('01_Formulario_A00'!$D:$D,MATCH("D01-DOC-MNE-001.CHANNELS.DISTRIBUICAO",'01_Formulario_A00'!$A:$A,0))="","— (a preencher em 01_Formulario_A00)",INDEX('01_Formulario_A00'!$D:$D,MATCH("D01-DOC-MNE-001.CHANNELS.DISTRIBUICAO",'01_Formulario_A00'!$A:$A,0))),"— (a preencher em 01_Formulario_A00)")
A95: D01-DOC-MNE-001.CHANNELS.ENTREGA | B95: entrega | C95: =IFERROR(IF(INDEX('01_Formulario_A00'!$D:$D,MATCH("D01-DOC-MNE-001.CHANNELS.ENTREGA",'01_Formulario_A00'!$A:$A,0))="","— (a preencher em 01_Formulario_A00)",INDEX('01_Formulario_A00'!$D:$D,MATCH("D01-DOC-MNE-001.CHANNELS.ENTREGA",'01_Formulario_A00'!$A:$A,0))),"— (a preencher em 01_Formulario_A00)")
A96: D01-DOC-MNE-001.RELATIONSHIPS.RELACIONAMENTO_COM_CLIENTE | B96: relacionamento_com_cliente | C96: =IFERROR(IF(INDEX('01_Formulario_A00'!$D:$D,MATCH("D01-DOC-MNE-001.RELATIONSHIPS.RELACIONAMENTO_COM_CLIENTE",'01_Formulario_A00'!$A:$A,0))="","— (a preencher em 01_Formulario_A00)",INDEX('01_Formulario_A00'!$D:$D,MATCH("D01-DOC-MNE-001.RELATIONSHIPS.RELACIONAMENTO_COM_CLIENTE",'01_Formulario_A00'!$A:$A,0))),"— (a preencher em 01_Formulario_A00)")
A97: D01-DOC-MNE-001.RELATIONSHIPS.COMUNIDADE | B97: comunidade | C97: =IFERROR(IF(INDEX('01_Formulario_A00'!$D:$D,MATCH("D01-DOC-MNE-001.RELATIONSHIPS.COMUNIDADE",'01_Formulario_A00'!$A:$A,0))="","— (a preencher em 01_Formulario_A00)",INDEX('01_Formulario_A00'!$D:$D,MATCH("D01-DOC-MNE-001.RELATIONSHIPS.COMUNIDADE",'01_Formulario_A00'!$A:$A,0))),"— (a preencher em 01_Formulario_A00)")
A98: D01-DOC-MNE-001.RELATIONSHIPS.SUPORTE | B98: suporte | C98: =IFERROR(IF(INDEX('01_Formulario_A00'!$D:$D,MATCH("D01-DOC-MNE-001.RELATIONSHIPS.SUPORTE",'01_Formulario_A00'!$A:$A,0))="","— (a preencher em 01_Formulario_A00)",INDEX('01_Formulario_A00'!$D:$D,MATCH("D01-DOC-MNE-001.RELATIONSHIPS.SUPORTE",'01_Formulario_A00'!$A:$A,0))),"— (a preencher em 01_Formulario_A00)")
A99: D01-DOC-MNE-001.REVENUE.FONTES_DE_RECEITA | B99: fontes_de_receita | C99: =IFERROR(IF(INDEX('01_Formulario_A00'!$D:$D,MATCH("D01-DOC-MNE-001.REVENUE.FONTES_DE_RECEITA",'01_Formulario_A00'!$A:$A,0))="","— (a preencher em 01_Formulario_A00)",INDEX('01_Formulario_A00'!$D:$D,MATCH("D01-DOC-MNE-001.REVENUE.FONTES_DE_RECEITA",'01_Formulario_A00'!$A:$A,0))),"— (a preencher em 01_Formulario_A00)")
A100: D01-DOC-MNE-001.REVENUE.PRECIFICACAO | B100: precificacao | C100: =IFERROR(IF(INDEX('01_Formulario_A00'!$D:$D,MATCH("D01-DOC-MNE-001.REVENUE.PRECIFICACAO",'01_Formulario_A00'!$A:$A,0))="","— (a preencher em 01_Formulario_A00)",INDEX('01_Formulario_A00'!$D:$D,MATCH("D01-DOC-MNE-001.REVENUE.PRECIFICACAO",'01_Formulario_A00'!$A:$A,0))),"— (a preencher em 01_Formulario_A00)")
A101: D01-DOC-MNE-001.REVENUE.RECORRENCIA | B101: recorrencia | C101: =IFERROR(IF(INDEX('01_Formulario_A00'!$D:$D,MATCH("D01-DOC-MNE-001.REVENUE.RECORRENCIA",'01_Formulario_A00'!$A:$A,0))="","— (a preencher em 01_Formulario_A00)",INDEX('01_Formulario_A00'!$D:$D,MATCH("D01-DOC-MNE-001.REVENUE.RECORRENCIA",'01_Formulario_A00'!$A:$A,0))),"— (a preencher em 01_Formulario_A00)")
A102: D01-DOC-MNE-001.COSTS.ESTRUTURA_DE_CUSTOS | B102: estrutura_de_custos | C102: =IFERROR(IF(INDEX('01_Formulario_A00'!$D:$D,MATCH("D01-DOC-MNE-001.COSTS.ESTRUTURA_DE_CUSTOS",'01_Formulario_A00'!$A:$A,0))="","— (a preencher em 01_Formulario_A00)",INDEX('01_Formulario_A00'!$D:$D,MATCH("D01-DOC-MNE-001.COSTS.ESTRUTURA_DE_CUSTOS",'01_Formulario_A00'!$A:$A,0))),"— (a preencher em 01_Formulario_A00)")
...

Sheet 06_Visao_Dependencias
B2: Visão Dependências
B4: Nenhuma dependência registrada — ver GAP-DEP-01 em 21_REG_Gaps (PF-24 não executado na fonte).

Sheet 07_Visao_Gates
A1: gate_id | B1: name | C1: decision
A2: G00 | B2: INITIATIVE_READY | C2: PENDING
A3: G01 | B3: BUSINESS_READY | C3: PENDING
A4: G02 | B4: PRODUCT_READY | C4: PENDING
A5: G03 | B5: DEVELOPMENT_READY | C5: PENDING
A6: G04 | B6: ENGINEERING_READY | C6: PENDING
A7: G05 | B7: RELEASE_READY | C7: PENDING
A8: G06 | B8: GO_LIVE | C8: PENDING
A9: G07 | B9: OPERATIONAL_READY | C9: PENDING
A10: G08 | B10: GTM_READY | C10: PENDING
A11: G09 | B11: MEASURED | C11: PENDING
A12: G10 | B12: LEARNING_CAPTURED | C12: PENDING
A13: G11 | B13: DOCUMENTED | C13: PENDING

Sheet 08_Visao_Documentos_Finais
A1: document_id | B1: level | C1: scope_id | D1: status
A2: A00-FINAL-001 | B2: MACROAREA | C2: A00 | D2: NOT_CREATED
A3: A01-FINAL-001 | B3: MACROAREA | C3: A01 | D3: NOT_CREATED
A4: A02-FINAL-001 | B4: MACROAREA | C4: A02 | D4: NOT_CREATED
A5: A03-FINAL-001 | B5: MACROAREA | C5: A03 | D5: NOT_CREATED
A6: A04-FINAL-001 | B6: MACROAREA | C6: A04 | D6: NOT_CREATED
A7: A05-FINAL-001 | B7: MACROAREA | C7: A05 | D7: NOT_CREATED
A8: A06-FINAL-001 | B8: MACROAREA | C8: A06 | D8: NOT_CREATED
A9: A07-FINAL-001 | B9: MACROAREA | C9: A07 | D9: NOT_CREATED
A10: A08-FINAL-001 | B10: MACROAREA | C10: A08 | D10: NOT_CREATED
A11: A09-FINAL-001 | B11: MACROAREA | C11: A09 | D11: NOT_CREATED
A12: A10-FINAL-001 | B12: MACROAREA | C12: A10 | D12: NOT_CREATED
... A35: EXECUTAR-FINAL-001 | B35: PROGRAM | C35: EXECUTAR | D35: NOT_CREATED

Sheet 09_Indice_IDs
A1: legacy_id | B1: canonical_id | C1: sheet | D1: row_in_sheet | E1: object_type
A2: D01-DOC-DDE-001 | B2: D01-DOC-DDE-001 | C2: 14_REG_Artefatos | D2: =MATCH(B2,'14_REG_Artefatos'!A:A,0) | E2: artifact
A3: D01-DOC-TAP-001 | B3: D01-DOC-TAP-001 | C3: 14_REG_Artefatos | D3: =MATCH(B3,'14_REG_Artefatos'!A:A,0) | E3: artifact
A4: D01-DOC-MNE-001 | B4: D01-DOC-MNE-001 | C4: 14_REG_Artefatos | D4: =MATCH(B4,'14_REG_Artefatos'!A:A,0) | E4: artifact
A5: D01-DOC-MRE-001 | B5: D01-DOC-MRE-001 | C5: 14_REG_Artefatos | D5: =MATCH(B5,'14_REG_Artefatos'!A:A,0) | E5: artifact
A6: D02-DOC-DGRC-001 | B6: D02-DOC-DGRC-001 | C6: 14_REG_Artefatos | D6: =MATCH(B6,'14_REG_Artefatos'!A:A,0) | E6: artifact
A7: D02-DOC-MRC-001 | B7: D02-DOC-MRC-001 | C7: 14_REG_Artefatos | D7: =MATCH(B7,'14_REG_Artefatos'!A:A,0) | E7: artifact
A8: D02-DOC-PPT-001 | B8: D02-DOC-PPT-001 | C8: 14_REG_Artefatos | D8: =MATCH(B8,'14_REG_Artefatos'!A:A,0) | E8: artifact
A9: D03-DOC-PFO-001 | B9: D03-DOC-PFO-001 | C9: 14_REG_Artefatos | D9: =MATCH(B9,'14_REG_Artefatos'!A:A,0) | E9: artifact
A10: D03-DOC-MFO-001 | B10: D03-DOC-MFO-001 | C10: 14_REG_Artefatos | D10: =MATCH(B10,'14_REG_Artefatos'!A:A,0) | E10: artifact
A11: D04-DOC-PPC-001 | B11: D04-DOC-PPC-001 | C11: 14_REG_Artefatos | D11: =MATCH(B11,'14_REG_Artefatos'!A:A,0) | E11: artifact
A12: D05-DOC-EPGD-001 | B12: D05-DOC-EPGD-001 | C12: 14_REG_Artefatos | D12: =MATCH(B12,'14_REG_Artefatos'!A:A,0) | E12: artifact
A13: D05-DOC-DCM-001 | B13: D05-DOC-DCM-001 | C13: 14_REG_Artefatos | D13: =MATCH(B13,'14_REG_Artefatos'!A:A,0) | E13: artifact
... A38: D23-DOC-PBL-001 | B38: D23-DOC-PBL-001 | C38: 14_REG_Artefatos | D38: =MATCH(B38,'14_REG_Artefatos'!A:A,0) | E38: artifact

Sheet 10_REG_Macroareas
A1: macroarea_id | B1: name | C1: status | D1: source_refs
A2: A00 | B2: Governança, Estratégia e Gestão | C2: ACTIVE | D2: ["ADR-EXECUTAR-HUB-001"]
A3: A01 | B3: Negócio e Go-to-Market | C3: ACTIVE | D3: ["ADR-EXECUTAR-HUB-001"]
A4: A02 | B4: Produto e Experiência | C4: ACTIVE | D4: ["ADR-EXECUTAR-HUB-001"]
A5: A03 | B5: Handoff Produto → Engenharia | C5: ACTIVE | D5: ["ADR-EXECUTAR-HUB-001"]
A6: A04 | B6: Arquitetura, Engenharia e Implementação | C6: ACTIVE | D6: ["ADR-EXECUTAR-HUB-001"]
A7: A05 | B7: Operações, Plataforma, Deploy e Segurança | C7: ACTIVE | D7: ["ADR-EXECUTAR-HUB-001"]
A8: A06 | B8: Dados, Pesquisa e Conhecimento | C8: ACTIVE | D8: ["ADR-EXECUTAR-HUB-001"]
A9: A07 | B9: Corporativo e Suporte | C9: ACTIVE | D9: ["ADR-EXECUTAR-HUB-001"]
A10: A08 | B10: Conteúdo, Comunicação e Growth | C10: ACTIVE | D10: ["ADR-EXECUTAR-HUB-001"]
A11: A09 | B11: Execução e Planejamento do Trabalho | C11: ACTIVE | D11: ["ADR-EXECUTAR-HUB-001"]
A12: A10 | B12: Documentação e Governança do Conhecimento | C12: ACTIVE | D12: ["ADR-EXECUTAR-HUB-001"]
... A14: A12 | B14: Stakeholders e Ecossistema | C14: ACTIVE | D14: ["ADR-EXECUTAR-HUB-001"]

Sheet 11_REG_Dominios
A1: domain_id | B1: macroarea_id | C1: name | D1: description | E1: status | F1: legacy_ids | G1: source_refs
A2: D0 | B2: A00 | C2: Pmbook Governança e Operação | D2: Charter integrado / PMBOK do programa EXECUTAR (D0.01 ficha de iniciativa). | E2: ACTIVE | F2: ["D0_Pmbook-Governanca-Operaco"] | G2: ["Progama_Master_index.docx", "ecossistema_operacional.yaml"]
A3: D01 | B3: A00 | C3: Gestão Empresarial | D3: Gestão Empresarial | E3: ACTIVE | F3: ["D01"] | G3: ["EXECUTAR_CHECKLIST_D01-D23_GRANULAR.yaml"]
A4: D02 | B4: A00 | C4: Jurídico, Riscos e Conformidade | D4: Jurídico, Riscos e Conformidade | E4: ACTIVE | F4: ["D02"] | G4: ["EXECUTAR_CHECKLIST_D01-D23_GRANULAR.yaml"]
A5: D03 | B5: A00 | C5: Finanças | D5: Finanças | E5: ACTIVE | F5: ["D03"] | G5: ["EXECUTAR_CHECKLIST_D01-D23_GRANULAR.yaml"]
A6: D04 | B6: A07 | C6: Pessoas e Recursos Humanos | D6: Pessoas e Recursos Humanos | E6: ACTIVE | F6: ["D04"] | G6: ["EXECUTAR_CHECKLIST_D01-D23_GRANULAR.yaml"]
A7: D05 | B7: A06 | C7: Dados | D7: Dados | E7: ACTIVE | F7: ["D05"] | G7: ["EXECUTAR_CHECKLIST_D01-D23_GRANULAR.yaml"]
A8: D06 | B8: A06 | C8: Conhecimento e Busca Corporativa | D8: Conhecimento e Busca Corporativa | E8: ACTIVE | F8: ["D06"] | G8: ["EXECUTAR_CHECKLIST_D01-D23_GRANULAR.yaml"]
A9: D07 | B9: A09 | C9: Produtividade e Execução | D9: Produtividade e Execução | E9: ACTIVE | F9: ["D07"] | G9: ["EXECUTAR_CHECKLIST_D01-D23_GRANULAR.yaml"]
A10: D08 | B10: A05 | C10: Operações | D10: Operações | E10: ACTIVE | F10: ["D08"] | G10: ["EXECUTAR_CHECKLIST_D01-D23_GRANULAR.yaml"]
A11: D09 | B11: A06 | C11: Pesquisa e Inovação | D11: Pesquisa e Inovação | E11: ACTIVE | F11: ["D09"] | G11: ["EXECUTAR_CHECKLIST_D01-D23_GRANULAR.yaml"]
A12: D10 | B12: A02 | C12: Gestão de Produto | D12: Gestão de Produto | E12: ACTIVE | F12: ["D10"] | G12: ["EXECUTAR_CHECKLIST_D01-D23_GRANULAR.yaml"]
... A25: D23 | B25: A10 | C25: Blueprints | D25: Blueprints | E25: ACTIVE | F25: ["D23"] | G25: ["EXECUTAR_CHECKLIST_D01-D23_GRANULAR.yaml"]

Sheet 12_REG_Portfolio
A1: portfolio_id | B1: parent_portfolio_id | C1: name | D1: type | E1: status | F1: owner | G1: legacy_ids
A2: S0 | C2: Executar programa governança e operações. | D2: PROGRAM_OPS | E2: ACTIVE | F2: A_DEFINIR | G2: ["S0"]
A3: M0 | C3: Executar Institucional | D3: PRODUCT_INITIATIVE | E3: ACTIVE | F3: A_DEFINIR | G3: ["M0"]
A4: M1 | C4: Executar App | D4: PRODUCT_INITIATIVE | E4: ACTIVE | F4: A_DEFINIR | G4: ["M1"]
A5: M2 | C5: Executar Blog | D5: PRODUCT_INITIATIVE | E5: ACTIVE | F5: A_DEFINIR | G5: ["M2"]
A6: M2.1 | C6: Risco cognitivo Blog | D6: PRODUCT_INITIATIVE | E6: ACTIVE | F6: A_DEFINIR | G6: ["M2.1"]
A7: M3 | C7: Executar Oficina | D7: PRODUCT_INITIATIVE | E7: ACTIVE | F7: A_DEFINIR | G7: ["M3"]
A8: M4 | C8: Executar Mapa Cognitivo | D8: PRODUCT_INITIATIVE | E8: ACTIVE | F8: A_DEFINIR | G8: ["M4"]
A9: M5 | C9: Executar Agente Copiloto | D9: PRODUCT_INITIATIVE | E9: ACTIVE | F9: A_DEFINIR | G9: ["M5"]
A10: M6 | C10: Executar Agente Maestro | D10: PRODUCT_INITIATIVE | E10: ACTIVE | F10: A_DEFINIR | G10: ["M6"]
A11: M7 | C11: Executar Agente Vera | D11: PRODUCT_INITIATIVE | E11: ACTIVE | F11: A_DEFINIR | G11: ["M7"]
A12: M7.1 | C12: Executar emprego e portfólio | D12: PRODUCT_INITIATIVE | E12: ACTIVE | F12: A_DEFINIR | G12: ["M7.1"]
A13: M8 | C13: Executar Consultoria / Studio | D13: PRODUCT_INITIATIVE | E13: ACTIVE | F13: A_DEFINIR | G13: ["M8"]
... A21: M16 | C21: Executar lead business creator strategy launch | D21: PRODUCT_INITIATIVE | E21: ACTIVE | F21: A_DEFINIR | G21: ["M16"]

Sheet 13_REG_Templates
A1: template_id | B1: artifact_type | C1: version | D1: required_fields | E1: applicable_macroareas | F1: applicable_domains | G1: applicable_portfolio_types
A2: TPL-CHARTER-001 | B2: CHARTER | C2: 1.0.0 | D2: [] | E2: ["D0"] | F2: [] | G2: ["PRODUCT_INITIATIVE"]
A3: TPL-BUSINESS-001 | B3: BUSINESS | C3: 1.0.0 | D3: [] | E3: ["A00", "A01"] | F3: [] | G3: ["PRODUCT_INITIATIVE"]
A4: TPL-PRD-001 | B4: PRD | C4: 1.0.0 | D4: [] | E4: ["A02"] | F4: [] | G4: ["PRODUCT_INITIATIVE"]
A5: TPL-UX-001 | B5: UX | C5: 1.0.0 | D5: [] | E5: ["A02"] | F5: [] | G5: ["PRODUCT_INITIATIVE"]
A6: TPL-DRP-001 | B6: DRP | C6: 1.0.0 | D6: [] | E6: ["A03"] | F6: [] | G6: ["PRODUCT_INITIATIVE"]
A7: TPL-FUNCTIONAL_REQ-001 | B7: FUNCTIONAL_REQUIREMENTS | C7: 1.0.0 | D7: [] | E7: ["A03", "A04"] | F7: [] | G7: ["PRODUCT_INITIATIVE"]
A8: TPL-ACCEPTANCE_CRITERIA-001 | B8: ACCEPTANCE_CRITERIA | C8: 1.0.0 | D8: [] | E8: ["A03", "A04"] | F8: [] | G8: ["PRODUCT_INITIATIVE"]
A9: TPL-NFR-001 | B9: NFR | C9: 1.0.0 | D9: [] | E9: ["A04"] | F9: [] | G9: ["PRODUCT_INITIATIVE"]
A10: TPL-DATA_INTEGRATION-001 | B10: DATA_INTEGRATION_REQUIREMENTS | C10: 1.0.0 | D10: [] | E10: ["A04", "A06"] | F10: [] | G10: ["PRODUCT_INITIATIVE"]
A11: TPL-ANALYTICS-001 | B11: ANALYTICS | C11: 1.0.0 | D11: [] | E11: ["A06"] | F11: [] | G11: ["PRODUCT_INITIATIVE"]
A12: TPL-ADR-001 | B12: ADR | C12: 1.0.0 | D12: [] | E12: ["A04"] | F12: [] | G12: ["PRODUCT_INITIATIVE"]
... A21: TPL-FINAL_DOSSIER-001 | B21: FINAL_DOSSIER | C21: 1.0.0 | D21: [] | E21: ["A00"] | F21: [] | G21: ["PRODUCT_INITIATIVE"]

Sheet 14_REG_Artefatos
A1: artifact_id | B1: program_id | C1: portfolio_id | D1: macroarea_id | E1: domain_id | F1: subdomain_id | G1: lifecycle_stage_id | H1: gate_id | I1: artifact_type | J1: template_id | K1: title | L1: version | M1: required | N1: status | O1: approval_status | P1: owner | Q1: approver | R1: depends_on | S1: blocks | T1: evidence_ids | U1: source_links | V1: next_action | W1: automation_level | X1: legacy_ids
A2: D01-DOC-DDE-001 | B2: EXECUTAR | D2: A00 | E2: D01 | I2: MACRO | K2: Documento de Direção Empresarial | L2: 1.0.0 | M2: TRUE | N2: PRE_PREENCHIDO | O2: PENDENTE | P2: A_DEFINIR | Q2: A_DEFINIR | R2: [] | S2: [] | T2: ["D01-DOC-DDE-001-EVD"] | U2: ["Drive: D01__*"] | V2: Executar PF-24 (reconciliação cruzada depends_on/blocks) — NA-03. | W2: A4 | X2: ["D01-DOC-DDE-001"]
A3: D01-DOC-TAP-001 | B3: EXECUTAR | D3: A00 | E3: D01 | I3: SPECIALIZED | K3: Termo de Abertura do Ecossistema | L3: 1.0.0 | M3: TRUE | N3: PRE_PREENCHIDO | O3: PENDENTE | P3: A_DEFINIR | Q3: A_DEFINIR | R3: [] | S3: [] | T3: ["D01-DOC-TAP-001-EVD"] | U3: ["Drive: D01__*"] | V3: Executar PF-24 (reconciliação cruzada depends_on/blocks) — NA-03. | W3: A4 | X3: ["D01-DOC-TAP-001"]
A4: D01-DOC-MNE-001 | B4: EXECUTAR | D4: A00 | E4: D01 | I4: SPECIALIZED | K4: Modelo de Negócio do Ecossistema | L4: 1.0.0 | M4: TRUE | N4: PRE_PREENCHIDO | O4: PENDENTE | P4: A_DEFINIR | Q4: A_DEFINIR | R4: [] | S4: [] | T4: ["D01-DOC-MNE-001-EVD"] | U4: ["Drive: D01__*"] | V4: Executar PF-24 (reconciliação cruzada depends_on/blocks) — NA-03. | W4: A4 | X4: ["D01-DOC-MNE-001"]
A5: D01-DOC-MRE-001 | B5: EXECUTAR | D5: A00 | E5: D01 | I5: SPECIALIZED | K5: Mapa de Relações do Ecossistema | L5: 1.0.0 | M5: TRUE | N5: PRE_PREENCHIDO | O5: PENDENTE | P5: A_DEFINIR | Q5: A_DEFINIR | R5: [] | S5: [] | T5: ["D01-DOC-MRE-001-EVD"] | U5: ["Drive: D01__*"] | V5: Executar PF-24 (reconciliação cruzada depends_on/blocks) — NA-03. | W5: A4 | X5: ["D01-DOC-MRE-001"]
A6: D02-DOC-DGRC-001 | B6: EXECUTAR | D6: A00 | E6: D02 | I6: MACRO | K6: Documento de Governança, Riscos e Conformidade | L6: 1.0.0 | M6: TRUE | N6: PRE_PREENCHIDO | O6: PENDENTE | P6: A_DEFINIR | Q6: A_DEFINIR | R6: [] | S6: [] | T6: ["D02-DOC-DGRC-001-EVD"] | U6: ["Drive: D02__*"] | V6: Executar PF-24 (reconciliação cruzada depends_on/blocks) — NA-03. | W6: A4 | X6: ["D02-DOC-DGRC-001"]
A7: D02-DOC-MRC-001 | B7: EXECUTAR | D7: A00 | E7: D02 | I7: SPECIALIZED | K7: Matriz de Riscos e Controles | L7: 1.0.0 | M7: TRUE | N7: PRE_PREENCHIDO | O7: PENDENTE | P7: A_DEFINIR | Q7: A_DEFINIR | R7: [] | S7: [] | T7: ["D02-DOC-MRC-001-EVD"] | U7: ["Drive: D02__*"] | V7: Executar PF-24 (reconciliação cruzada depends_on/blocks) — NA-03. | W7: A4 | X7: ["D02-DOC-MRC-001"]
A8: D02-DOC-PPT-001 | B8: EXECUTAR | D8: A00 | E8: D02 | I8: SPECIALIZED | K8: Política de Privacidade e Termos | L8: 1.0.0 | M8: TRUE | N8: PRE_PREENCHIDO | O8: PENDENTE | P8: A_DEFINIR | Q8: A_DEFINIR | R8: [] | S8: [] | T8: ["D02-DOC-PPT-001-EVD"] | U8: ["Drive: D02__*"] | V8: Executar PF-24 (reconciliação cruzada depends_on/blocks) — NA-03. | W8: A4 | X8: ["D02-DOC-PPT-001"]
A9: D03-DOC-PFO-001 | B9: EXECUTAR | D9: A00 | E9: D03 | I9: MACRO | K9: Plano Financeiro e Orçamentário | L9: 1.0.0 | M9: TRUE | N9: PRE_PREENCHIDO | O9: PENDENTE | P9: A_DEFINIR | Q9: A_DEFINIR | R9: [] | S9: [] | T9: ["D03-DOC-PFO-001-EVD"] | U9: ["Drive: D03__*"] | V9: Executar PF-24 (reconciliação cruzada depends_on/blocks) — NA-03. | W9: A4 | X9: ["D03-DOC-PFO-001"]
A10: D03-DOC-MFO-001 | B10: EXECUTAR | D10: A00 | E10: D03 | I10: SPECIALIZED | K10: Modelo Financeiro do Ecossistema | L10: 1.0.0 | M10: TRUE | N10: PRE_PREENCHIDO | O10: PENDENTE | P10: A_DEFINIR | Q10: A_DEFINIR | R10: [] | S10: [] | T10: ["D03-DOC-MFO-001-EVD"] | U10: ["Drive: D03__*"] | V10: Executar PF-24 (reconciliação cruzada depends_on/blocks) — NA-03. | W10: A4 | X10: ["D03-DOC-MFO-001"]
A11: D04-DOC-PPC-001 | B11: EXECUTAR | D11: A07 | E11: D04 | I11: MACRO | K11: Plano de Pessoas e Capacidade | L11: 1.0.0 | M11: TRUE | N11: PRE_PREENCHIDO | O11: PENDENTE | P11: A_DEFINIR | Q11: A_DEFINIR | R11: [] | S11: [] | T11: ["D04-DOC-PPC-001-EVD"] | U11: ["Drive: D04__*"] | V11: Executar PF-24 (reconciliação cruzada depends_on/blocks) — NA-03. | W11: A4 | X11: ["D04-DOC-PPC-001"]
A12: D05-DOC-EPGD-001 | B12: EXECUTAR | D12: A06 | E12: D05 | I12: MACRO | K12: Estratégia e Plano de Gestão de Dados | L12: 1.0.0 | M12: TRUE | N12: PRE_PREENCHIDO | O12: PENDENTE | P12: A_DEFINIR | Q12: A_DEFINIR | R12: [] | S12: [] | T12: ["D05-DOC-EPGD-001-EVD"] | U12: ["Drive: D05__*"] | V12: Executar PF-24 (reconciliação cruzada depends_on/blocks) — NA-03. | W12: A4 | X12: ["D05-DOC-EPGD-001"]
A13: D05-DOC-DCM-001 | B13: EXECUTAR | D13: A06 | E13: D05 | I13: SPECIALIZED | K13: Dicionário de Dados e Catálogo de Métricas | L13: 1.0.0 | M13: TRUE | N13: PRE_PREENCHIDO | O13: PENDENTE | P13: A_DEFINIR | Q13: A_DEFINIR | R13: [] | S13: [] | T13: ["D05-DOC-DCM-001-EVD"] | U13: ["Drive: D05__*"] | V13: Executar PF-24 (reconciliação cruzada depends_on/blocks) — NA-03. | W13: A4 | X13: ["D05-DOC-DCM-001"]
... A38: D23-DOC-PBL-001 | B38: EXECUTAR | D38: A10 | E38: D23 | I38: MACRO | K38: Plano de Blueprints | L38: 1.0.0 | M38: TRUE | N38: PRE_PREENCHIDO | O38: PENDENTE | P38: A_DEFINIR | Q38: A_DEFINIR | R38: [] | S38: [] | T38: ["D23-DOC-PBL-001-EVD"] | U38: ["Drive: D23__*"] | V38: Executar PF-24 (reconciliação cruzada depends_on/blocks) — NA-03. | W38: A4 | X38: ["D23-DOC-PBL-001"]

Sheet 15_REG_Campos
A1: field_instance_id | B1: artifact_id | C1: section_id | D1: label | E1: instruction | F1: value | G1: required | H1: editable | I1: status | J1: epistemic_class | K1: evidence_status | L1: confidence | M1: legacy_ids
A2: D01-DOC-DDE-001.IDENTITY.NOME_DO_ECOSSISTEMA | B2: D01-DOC-DDE-001 | C2: D01-DOC-DDE-001-T01 | D2: nome_do_ecossistema | E2: Definir, validar e manter: Nome Do Ecossistema | G2: TRUE | H2: TRUE | I2: FOUND | J2: DIRECT | K2: FOUND | L2: alta | M2: ["D01-DOC-DDE-001.IDENTITY.NOME_DO_ECOSSISTEMA"]
A3: D01-DOC-DDE-001.IDENTITY.DESCRICAO_EXECUTIVA | B3: D01-DOC-DDE-001 | C3: D01-DOC-DDE-001-T01 | D3: descricao_executiva | E3: Definir, validar e manter: Descricao Executiva | G3: TRUE | H3: TRUE | I3: DERIVED | J3: PROPOSED | K3: DERIVED | L3: baixa | M3: ["D01-DOC-DDE-001.IDENTITY.DESCRICAO_EXECUTIVA"]
A4: D01-DOC-DDE-001.IDENTITY.CONTEXTO | B4: D01-DOC-DDE-001 | C4: D01-DOC-DDE-001-T01 | D4: contexto | E4: Definir, validar e manter: Contexto | G4: TRUE | H4: TRUE | I4: DERIVED | J4: PROPOSED | K4: DERIVED | L4: baixa | M4: ["D01-DOC-DDE-001.IDENTITY.CONTEXTO"]
A5: D01-DOC-DDE-001.IDENTITY.RAZAO_DE_EXISTENCIA | B5: D01-DOC-DDE-001 | C5: D01-DOC-DDE-001-T01 | D5: razao_de_existencia | E5: Definir, validar e manter: Razao De Existencia | G5: TRUE | H5: TRUE | I5: DERIVED | J5: PROPOSED | K5: DERIVED | L5: baixa | M5: ["D01-DOC-DDE-001.IDENTITY.RAZAO_DE_EXISTENCIA"]
A6: D01-DOC-DDE-001.IDENTITY.FASE_ATUAL | B6: D01-DOC-DDE-001 | C6: D01-DOC-DDE-001-T01 | D6: fase_atual | E6: Definir, validar e manter: Fase Atual | G6: TRUE | H6: TRUE | I6: DERIVED | J6: PROPOSED | K6: DERIVED | L6: baixa | M6: ["D01-DOC-DDE-001.IDENTITY.FASE_ATUAL"]
A7: D01-DOC-DDE-001.PROBLEM_AND_OPPORTUNITY.PROBLEMA_CENTRAL | B7: D01-DOC-DDE-001 | C7: D01-DOC-DDE-001-T02 | D7: problema_central | E7: Definir, validar e manter: Problema Central | G7: TRUE | H7: TRUE | I7: DERIVED | J7: PROPOSED | K7: DERIVED | L7: baixa | M7: ["D01-DOC-DDE-001.PROBLEM_AND_OPPORTUNITY.PROBLEMA_CENTRAL"]
A8: D01-DOC-DDE-001.PROBLEM_AND_OPPORTUNITY.PROBLEMAS_SECUNDARIOS | B8: D01-DOC-DDE-001 | C8: D01-DOC-DDE-001-T02 | D8: problemas_secundarios | E8: Definir, validar e manter: Problemas Secundarios | G8: TRUE | H8: TRUE | I8: DERIVED | J8: PROPOSED | K8: DERIVED | L8: baixa | M8: ["D01-DOC-DDE-001.PROBLEM_AND_OPPORTUNITY.PROBLEMAS_SECUNDARIOS"]
A9: D01-DOC-DDE-001.PROBLEM_AND_OPPORTUNITY.OPORTUNIDADE | B9: D01-DOC-DDE-001 | C9: D01-DOC-DDE-001-T02 | D9: oportunidade | E9: Definir, validar e manter: Oportunidade | G9: TRUE | H9: TRUE | I9: DERIVED | J9: PROPOSED | K9: DERIVED | L9: baixa | M9: ["D01-DOC-DDE-001.PROBLEM_AND_OPPORTUNITY.OPORTUNIDADE"]
A10: D01-DOC-DDE-001.PROBLEM_AND_OPPORTUNITY.EVIDENCIAS_DO_PROBLEMA | B10: D01-DOC-DDE-001 | C10: D01-DOC-DDE-001-T02 | D10: evidencias_do_problema | E10: Definir, validar e manter: Evidencias Do Problema | G10: TRUE | H10: TRUE | I10: DERIVED | J10: PROPOSED | K10: DERIVED | L10: baixa | M10: ["D01-DOC-DDE-001.PROBLEM_AND_OPPORTUNITY.EVIDENCIAS_DO_PROBLEMA"]
A11: D01-DOC-DDE-001.PURPOSE.PROPOSITO | B11: D01-DOC-DDE-001 | C11: D01-DOC-DDE-001-T03 | D11: proposito | E11: Definir, validar e manter: Proposito | G11: TRUE | H11: TRUE | I11: DERIVED | J11: PROPOSED | K11: DERIVED | L11: baixa | M11: ["D01-DOC-DDE-001.PURPOSE.PROPOSITO"]
A12: D01-DOC-DDE-001.PURPOSE.MISSAO | B12: D01-DOC-DDE-001 | C12: D01-DOC-DDE-001-T03 | D12: missao | E12: Definir, validar e manter: Missao | G12: TRUE | H12: TRUE | I12: DERIVED | J12: PROPOSED | K12: DERIVED | L12: baixa | M12: ["D01-DOC-DDE-001.PURPOSE.MISSAO"]
A13: D01-DOC-DDE-001.PURPOSE.VISAO | B13: D01-DOC-DDE-001 | C13: D01-DOC-DDE-001-T03 | D13: visao | E13: Definir, validar e manter: Visao | G13: TRUE | H13: TRUE | I13: DERIVED | J13: PROPOSED | K13: DERIVED | L13: baixa | M13: ["D01-DOC-DDE-001.PURPOSE.VISAO"]
... A1126: D23-DOC-PBL-001.EVIDENCE.REGISTROS | B1126: D23-DOC-PBL-001 | C1126: D23-DOC-PBL-001-T18 | D1126: registros | E1126: Definir, validar e manter: Registros | G1126: TRUE | H1126: TRUE | I1126: DERIVED | J1126: PROPOSED | K1126: DERIVED | L1126: baixa | M1126: ["D23-DOC-PBL-001.EVIDENCE.REGISTROS"]

Sheet 16_REG_Dependencias
A1: dependency_id | B1: source_artifact_id | C1: target_artifact_id | D1: relation | E1: mandatory | F1: gate_id | G1: required_status | H1: status

Sheet 17_REG_Gates
A1: gate_id | B1: name | C1: scope | D1: required_artifact_types | E1: required_statuses | F1: decision | G1: evidence_ids
A2: G00 | B2: INITIATIVE_READY | C2: PROGRAM | D2: [] | E2: ["APPROVED"] | F2: PENDING | G2: []
A3: G01 | B3: BUSINESS_READY | C3: PROGRAM | D3: [] | E3: ["APPROVED"] | F3: PENDING | G3: []
A4: G02 | B4: PRODUCT_READY | C4: PROGRAM | D4: [] | E4: ["APPROVED"] | F4: PENDING | G4: []
A5: G03 | B5: DEVELOPMENT_READY | C5: PROGRAM | D5: [] | E5: ["APPROVED"] | F5: PENDING | G5: []
A6: G04 | B6: ENGINEERING_READY | C6: PROGRAM | D6: [] | E6: ["APPROVED"] | F6: PENDING | G6: []
A7: G05 | B7: RELEASE_READY | C7: PROGRAM | D7: [] | E7: ["APPROVED"] | F7: PENDING | G7: []
A8: G06 | B8: GO_LIVE | C8: PROGRAM | D8: [] | E8: ["APPROVED"] | F8: PENDING | G8: []
A9: G07 | B9: OPERATIONAL_READY | C9: PROGRAM | D9: [] | E9: ["APPROVED"] | F9: PENDING | G9: []
A10: G08 | B10: GTM_READY | C10: PROGRAM | D10: [] | E10: ["APPROVED"] | F10: PENDING | G10: []
A11: G09 | B11: MEASURED | C11: PROGRAM | D11: [] | E11: ["APPROVED"] | F11: PENDING | G11: []
A12: G10 | B12: LEARNING_CAPTURED | C12: PROGRAM | D12: [] | E12: ["APPROVED"] | F12: PENDING | G12: []
A13: G11 | B13: DOCUMENTED | C13: PROGRAM | D13: [] | E13: ["APPROVED"] | F13: PENDING | G13: []

Sheet 18_REG_Evidencias
A1: evidence_id | B1: artifact_id | C1: total_fields | D1: found_direct | E1: found_external | F1: found_proposed | G1: conflict | H1: not_found | I1: coverage_percent | J1: evidence_status
A2: D01-DOC-DDE-001-EVD | B2: D01-DOC-DDE-001 | C2: 44 | D2: 5 | E2: 1 | F2: 38 | G2: 0 | H2: 0 | I2: 100 | J2: DIRECT
A3: D01-DOC-TAP-001-EVD | B3: D01-DOC-TAP-001 | C3: 29 | D3: 0 | E3: 1 | F3: 28 | G3: 0 | H3: 0 | I3: 100 | J3: PROPOSED
A4: D01-DOC-MNE-001-EVD | B4: D01-DOC-MNE-001 | C4: 36 | D4: 0 | E4: 6 | F4: 30 | G4: 0 | H4: 0 | I4: 100 | J4: PROPOSED
A5: D01-DOC-MRE-001-EVD | B5: D01-DOC-MRE-001 | C5: 23 | D5: 0 | E5: 0 | F5: 23 | G5: 0 | H5: 0 | I5: 100 | J5: PROPOSED
A6: D02-DOC-DGRC-001-EVD | B6: D02-DOC-DGRC-001 | C6: 33 | D6: 0 | E6: 4 | F6: 29 | G6: 0 | H6: 0 | I6: 100 | J6: PROPOSED
A7: D02-DOC-MRC-001-EVD | B7: D02-DOC-MRC-001 | C7: 18 | D7: 0 | E7: 0 | F7: 18 | G7: 0 | H7: 0 | I7: 100 | J7: PROPOSED
A8: D02-DOC-PPT-001-EVD | B8: D02-DOC-PPT-001 | C8: 27 | D8: 0 | E8: 4 | F8: 23 | G8: 0 | H8: 0 | I8: 100 | J8: PROPOSED
A9: D03-DOC-PFO-001-EVD | B9: D03-DOC-PFO-001 | C9: 38 | D9: 2 | E9: 2 | F9: 34 | G9: 0 | H9: 0 | I9: 100 | J9: DIRECT
A10: D03-DOC-MFO-001-EVD | B10: D03-DOC-MFO-001 | C10: 27 | D10: 0 | E10: 7 | F10: 20 | G10: 0 | H10: 0 | I10: 100 | J10: PROPOSED
A11: D04-DOC-PPC-001-EVD | B11: D04-DOC-PPC-001 | C11: 39 | D11: 1 | E11: 5 | F11: 33 | G11: 1 | H11: 0 | I11: 100 | J11: DIRECT
A12: D05-DOC-EPGD-001-EVD | B12: D05-DOC-EPGD-001 | C12: 36 | D12: 0 | E12: 7 | F12: 29 | G12: 0 | H12: 0 | I12: 100 | J12: PROPOSED
A13: D05-DOC-DCM-001-EVD | B13: D05-DOC-DCM-001 | C13: 18 | D13: 0 | E13: 3 | F13: 15 | G13: 0 | H13: 0 | I13: 100 | J13: PROPOSED
... A38: D23-DOC-PBL-001-EVD | B38: D23-DOC-PBL-001 | C38: 40 | D38: 0 | E38: 1 | F38: 39 | G38: 0 | H38: 0 | I38: 100 | J38: PROPOSED

Sheet 19_REG_Documentos
A1: document_id | B1: level | C1: scope_id | D1: status | E1: derives_from
A2: A00-FINAL-001 | B2: MACROAREA | C2: A00 | D2: NOT_CREATED | E2: artifacts of this macroarea
A3: A01-FINAL-001 | B3: MACROAREA | C3: A01 | D3: NOT_CREATED | E3: artifacts of this macroarea
A4: A02-FINAL-001 | B4: MACROAREA | C4: A02 | D4: NOT_CREATED | E4: artifacts of this macroarea
A5: A03-FINAL-001 | B5: MACROAREA | C5: A03 | D5: NOT_CREATED | E5: artifacts of this macroarea
A6: A04-FINAL-001 | B6: MACROAREA | C6: A04 | D6: NOT_CREATED | E6: artifacts of this macroarea
A7: A05-FINAL-001 | B7: MACROAREA | C7: A05 | D7: NOT_CREATED | E7: artifacts of this macroarea
A8: A06-FINAL-001 | B8: MACROAREA | C8: A06 | D8: NOT_CREATED | E8: artifacts of this macroarea
A9: A07-FINAL-001 | B9: MACROAREA | C9: A07 | D9: NOT_CREATED | E9: artifacts of this macroarea
A10: A08-FINAL-001 | B10: MACROAREA | C10: A08 | D10: NOT_CREATED | E10: artifacts of this macroarea
A11: A09-FINAL-001 | B11: MACROAREA | C11: A09 | D11: NOT_CREATED | E11: artifacts of this macroarea
A12: A10-FINAL-001 | B12: MACROAREA | C12: A10 | D12: NOT_CREATED | E12: artifacts of this macroarea
... A35: EXECUTAR-FINAL-001 | B35: PROGRAM | C35: EXECUTAR | D35: NOT_CREATED | E35: all macroareas + portfolio

Sheet 20_REG_Decisoes
A1: decision_id | B1: topic | C1: decision | D1: rationale | E1: status | F1: requires_human_validation | G1: adr_ref
A2: DEC-MACRO-D01 | B2: Atribuição de macroárea para D01 (Gestão Empresarial) | C2: D01 -> A00 | D2: Mapeamento semântico nome-do-domínio -> macroárea alvo do ADR-EXECUTAR-HUB-001, Fase 2 (Reconciliation). Não há atribuição explícita nas fontes originais; decisão registrada para revisão humana. | E2: PROPOSED | F2: TRUE | G2: ADR-EXECUTAR-HUB-001
A3: DEC-MACRO-D02 | B3: Atribuição de macroárea para D02 (Jurídico, Riscos e Conformidade) | C3: D02 -> A00 | D3: Mapeamento semântico nome-do-domínio -> macroárea alvo do ADR-EXECUTAR-HUB-001, Fase 2 (Reconciliation). Não há atribuição explícita nas fontes originais; decisão registrada para revisão humana. | E3: PROPOSED | F3: TRUE | G3: ADR-EXECUTAR-HUB-001
A4: DEC-MACRO-D03 | B4: Atribuição de macroárea para D03 (Finanças) | C4: D03 -> A00 | D4: Mapeamento semântico nome-do-domínio -> macroárea alvo do ADR-EXECUTAR-HUB-001, Fase 2 (Reconciliation). Não há atribuição explícita nas fontes originais; decisão registrada para revisão humana. | E4: PROPOSED | F4: TRUE | G4: ADR-EXECUTAR-HUB-001
A5: DEC-MACRO-D04 | B5: Atribuição de macroárea para D04 (Pessoas e Recursos Humanos) | C5: D04 -> A07 | D5: Mapeamento semântico nome-do-domínio -> macroárea alvo do ADR-EXECUTAR-HUB-001, Fase 2 (Reconciliation). Não há atribuição explícita nas fontes originais; decisão registrada para revisão humana. | E5: PROPOSED | F5: TRUE | G5: ADR-EXECUTAR-HUB-001
A6: DEC-MACRO-D05 | B6: Atribuição de macroárea para D05 (Dados) | C6: D05 -> A06 | D6: Mapeamento semântico nome-do-domínio -> macroárea alvo do ADR-EXECUTAR-HUB-001, Fase 2 (Reconciliation). Não há atribuição explícita nas fontes originais; decisão registrada para revisão humana. | E6: PROPOSED | F6: TRUE | G6: ADR-EXECUTAR-HUB-001
A7: DEC-MACRO-D06 | B7: Atribuição de macroárea para D06 (Conhecimento e Busca Corporativa) | C7: D06 -> A06 | D7: Mapeamento semântico nome-do-domínio -> macroárea alvo do ADR-EXECUTAR-HUB-001, Fase 2 (Reconciliation). Não há atribuição explícita nas fontes originais; decisão registrada para revisão humana. | E7: PROPOSED | F7: TRUE | G7: ADR-EXECUTAR-HUB-001
A8: DEC-MACRO-D07 | B8: Atribuição de macroárea para D07 (Produtividade e Execução) | C8: D07 -> A09 | D8: Mapeamento semântico nome-do-domínio -> macroárea alvo do ADR-EXECUTAR-HUB-001, Fase 2 (Reconciliation). Não há atribuição explícita nas fontes originais; decisão registrada para revisão humana. | E8: PROPOSED | F8: TRUE | G8: ADR-EXECUTAR-HUB-001
A9: DEC-MACRO-D08 | B9: Atribuição de macroárea para D08 (Operações) | C9: D08 -> A05 | D9: Mapeamento semântico nome-do-domínio -> macroárea alvo do ADR-EXECUTAR-HUB-001, Fase 2 (Reconciliation). Não há atribuição explícita nas fontes originais; decisão registrada para revisão humana. | E9: PROPOSED | F9: TRUE | G9: ADR-EXECUTAR-HUB-001
A10: DEC-MACRO-D09 | B10: Atribuição de macroárea para D09 (Pesquisa e Inovação) | C10: D09 -> A06 | D10: Mapeamento semântico nome-do-domínio -> macroárea alvo do ADR-EXECUTAR-HUB-001, Fase 2 (Reconciliation). Não há atribuição explícita nas fontes originais; decisão registrada para revisão humana. | E10: PROPOSED | F10: TRUE | G10: ADR-EXECUTAR-HUB-001
A11: DEC-MACRO-D10 | B11: Atribuição de macroárea para D10 (Gestão de Produto) | C11: D10 -> A02 | D11: Mapeamento semântico nome-do-domínio -> macroárea alvo do ADR-EXECUTAR-HUB-001, Fase 2 (Reconciliation). Não há atribuição explícita nas fontes originais; decisão registrada para revisão humana. | E11: PROPOSED | F11: TRUE | G11: ADR-EXECUTAR-HUB-001
A12: DEC-MACRO-D11 | B12: Atribuição de macroárea para D11 (Experiência e Projeto) | C12: D11 -> A02 | D12: Mapeamento semântico nome-do-domínio -> macroárea alvo do ADR-EXECUTAR-HUB-001, Fase 2 (Reconciliation). Não há atribuição explícita nas fontes originais; decisão registrada para revisão humana. | E12: PROPOSED | F12: TRUE | G12: ADR-EXECUTAR-HUB-001
A13: DEC-MACRO-D12 | B13: Atribuição de macroárea para D12 (Engenharia) | C13: D12 -> A04 | D13: Mapeamento semântico nome-do-domínio -> macroárea alvo do ADR-EXECUTAR-HUB-001, Fase 2 (Reconciliation). Não há atribuição explícita nas fontes originais; decisão registrada para revisão humana. | E13: PROPOSED | F13: TRUE | G13: ADR-EXECUTAR-HUB-001
... A26: DEC-UX-02 | B26: 09_Indice_IDs formula-driven (desvio do original estático) | C26: INDEX/MATCH sobre REG_Artefatos e REG_Legacy_ID_Map | D26: O original era digitado à mão (sem fórmula); o MASTER COMMAND exige 'sem referências quebradas', o que uma tabela estática não garante sozinha. | E26: APPROVED_BY_USER | F26: FALSE | G26: ADR-EXECUTAR-HUB-001

Sheet 21_REG_Gaps
A1: gap_id | B1: type | C1: description | D1: priority | E1: status | F1: source | G1: fields_afetados
A2: NA-01 | B2: NEXT_ACTION | C2: Validar com o owner de cada area os campos marcados PROPOSED (interpretacao logica de negocio) e substituir por dado real. | D2: alta | E2: OPEN | F2: EXECUTAR_CHECKLIST_D01-D23_GRANULAR.yaml#next_actions_register
A3: NA-02 | B3: NEXT_ACTION | C3: Confirmar ou descartar os benchmarks EXTERNAL_EVIDENCE (LGPD, SaaS metrics, RACI, SLA, RTO/RPO, WCAG, data governance, portfolio) com dados proprios do ecossistema. | D3: alta | E3: OPEN | F3: EXECUTAR_CHECKLIST_D01-D23_GRANULAR.yaml#next_actions_register
A4: NA-03 | B4: NEXT_ACTION | C4: Executar PF-24 (reconciliacao cruzada) preenchendo depends_on/blocks entre areas. | D4: alta | E4: OPEN | F4: EXECUTAR_CHECKLIST_D01-D23_GRANULAR.yaml#next_actions_register
A5: NA-04 | B5: NEXT_ACTION | C5: Resolver CONFLICT_REGISTER (11 itens), comecando por contagem de documentos (37 vs 46) e identidade de 'Vera' (produto/agente vs pessoa fisica). | D5: alta | E5: OPEN | F5: EXECUTAR_CHECKLIST_D01-D23_GRANULAR.yaml#next_actions_register
A6: NA-05 | B6: NEXT_ACTION | C6: Ler campo a campo os pacotes de skill/SDK do Workflow.zip e os blocos B03/B05/B06 do GOV-SPEC ainda nao lidos linha a linha, para promover mais campos PROPOSED/EXTERNAL para FOUND/DIRECT. | D6: media | E6: OPEN | F6: EXECUTAR_CHECKLIST_D01-D23_GRANULAR.yaml#next_actions_register
A7: UAR-01 | B7: USER_ACTION_REQUIRED | C7: Qual numero de documentos prevalece: 37 (Handoff.md) ou 46 (GOVERNANCA)? | D7: alta | E7: OPEN | F7: EXECUTAR_CHECKLIST_D01-D23_GRANULAR.yaml#user_action_required | G7: ["D06-DOC-EGC-001"]
A8: UAR-02 | B8: USER_ACTION_REQUIRED | C8: O plano GTM de lancamento em 07/09/2026 ja foi executado? Com qual resultado? Se nao, qual a nova data? | D8: alta | E8: OPEN | F8: EXECUTAR_CHECKLIST_D01-D23_GRANULAR.yaml#user_action_required | G8: ["D07-DOC-PIM-001.milestones.marco", "D13-DOC-GTM-001.launch.launch"]
A9: UAR-03 | B9: USER_ACTION_REQUIRED | C9: Vera e uma pessoa real da equipe (com pendencia de INSS registrada) ou apenas o nome do agente/produto? Se pessoa real, qual seu papel formal? | D9: alta | E9: OPEN | F9: EXECUTAR_CHECKLIST_D01-D23_GRANULAR.yaml#user_action_required | G9: ["D04-DOC-PPC-001.people.pessoa"]
A10: UAR-04 | B10: USER_ACTION_REQUIRED | C10: Todos os 1.013 campos PROPOSED neste YAML sao recomendacoes genericas de pratica de mercado, nao fatos deste ecossistema. Autoriza tratar cada um deles como base para trabalho subsequente, ou prefere que eu priorize revisao humana antes de qualquer uso operacional desses campos? | D10: alta | E10: OPEN | F10: EXECUTAR_CHECKLIST_D01-D23_GRANULAR.yaml#user_action_required | G10: ["Todos os campos com epistemic_class=PROPOSED em todos os 37 documentos"]
A11: GAP-DEP-01 | B11: STRUCTURAL | C11: Campos depends_on/blocks entre areas continuam nao preenchidos (PF-24 nao executado em profundidade); proximo passo registrado em NEXT_ACTIONS_REGISTER. | D11: alta | E11: OPEN | F11: validation_report

Sheet 22_REG_Conflitos
A1: conflict_id | B1: domain_id | C1: document_id | D1: field_id | E1: issue | F1: resolution_rule | G1: requires_human_decision | H1: status
A2: D22-DEC-CFL-01 | B2: D06/D22 | E2: Contagem de documentos: 37 (Handoff) vs 46 (GOVERNANCA) — Handoff.md (EXECUTAR-DOC-PREFILL-001) define escopo de 37 documentos (23 macro + 14 especializados); GOVERNANCA (Drive) declara '46 documentos registrados no índice documental' sem enumerá-los. | F2: Precedencia conforme regra do EXECUTAR-DOC-PREFILL-001: fonte mais recente e de maior autoridade vence; sem isso, permanece CONFLICT. | G2: TRUE | H2: ABERTO
A3: D22-DEC-CFL-02 | B3: D07/D13/D14 | E3: Janela de lançamento GTM 07/09/2026 expirada sem verificação — Plano GTM escrito em 25/08/2026 para lançamento em 07/09/2026; na data desta extração (22/09/2026) o cronograma está vencido e seu estado real não foi verificado. | F3: Precedencia conforme regra do EXECUTAR-DOC-PREFILL-001: fonte mais recente e de maior autoridade vence; sem isso, permanece CONFLICT. | G3: TRUE | H3: ABERTO
A4: D22-DEC-CFL-03 | B4: D14 | E4: Ancoragem de preço: piloto R$700 vs benchmark de mercado R$2.500-4.000 — Modelo anterior registrava R$700 por projeto de uma semana; benchmark de mercado mostra R$2.500/15 dias e R$4.000/30 dias para mapeamento puro; consultoria a R$300/hora. | F4: Precedencia conforme regra do EXECUTAR-DOC-PREFILL-001: fonte mais recente e de maior autoridade vence; sem isso, permanece CONFLICT. | G4: TRUE | H4: ABERTO
A5: D22-DEC-CFL-04 | B5: D16 | E5: Nomenclatura de área D16 divergente — GOVERNANCA usa 'Mídias Sociais e Distribuição Digital'; estrutura de pastas do Drive usa 'Mídias Sociais e Estratégias'. Handoff.md já registra ambas como aliases. | F5: Precedencia conforme regra do EXECUTAR-DOC-PREFILL-001: fonte mais recente e de maior autoridade vence; sem isso, permanece CONFLICT. | G5: TRUE | H5: ABERTO
A6: D22-DEC-CFL-05 | B6: D18 | E6: Nomenclatura de área D18 divergente — 'Contratos e Esquemas' (GOVERNANCA/Handoff) vs 'Contratos e Schemas' (estrutura de pastas do Drive). Handoff.md já registra ambas como aliases. | F6: Precedencia conforme regra do EXECUTAR-DOC-PREFILL-001: fonte mais recente e de maior autoridade vence; sem isso, permanece CONFLICT. | G6: TRUE | H6: ABERTO
A7: D22-DEC-GOVSPEC-A01 | B7: D06/D07 | E7: Matriz de 16 áreas e GOV-DOM-006 usam numeração diferente para vários domínios ( — Matriz de 16 áreas e GOV-DOM-006 usam numeração diferente para vários domínios (ex.: D02 é Jurídico numa e Dados na outra). | F7: Precedencia conforme regra do EXECUTAR-DOC-PREFILL-001: fonte mais recente e de maior autoridade vence; sem isso, permanece CONFLICT. | G7: TRUE | H7: ABERTO
A8: D22-DEC-GOVSPEC-A02 | B8: D06/D07 | E8: Duas estruturas de endereço concorrentes: D01.01-IDE-001 e domínio->área->subáre — Duas estruturas de endereço concorrentes: D01.01-IDE-001 e domínio->área->subárea->objeto. | F8: Precedencia conforme regra do EXECUTAR-DOC-PREFILL-001: fonte mais recente e de maior autoridade vence; sem isso, permanece CONFLICT. | G8: TRUE | H8: ABERTO
A9: D22-DEC-GOVSPEC-A05 | B9: D06/D07 | E9: Painel declara 39 peças de conteúdo mas a soma própria resulta em 45-47 incluind — Painel declara 39 peças de conteúdo mas a soma própria resulta em 45-47 incluindo os três ebooks. | F9: Precedencia conforme regra do EXECUTAR-DOC-PREFILL-001: fonte mais recente e de maior autoridade vence; sem isso, permanece CONFLICT. | G9: TRUE | H9: ABERTO
A10: D22-DEC-GOVSPEC-A07 | B10: D06/D07 | E10: Artigo: 1.900-2.500 palavras num trecho vs 1.800-2.400 noutro. — Artigo: 1.900-2.500 palavras num trecho vs 1.800-2.400 noutro. | F10: Precedencia conforme regra do EXECUTAR-DOC-PREFILL-001: fonte mais recente e de maior autoridade vence; sem isso, permanece CONFLICT. | G10: TRUE | H10: ABERTO
A11: D22-DEC-GOVSPEC-A16 | B11: D06/D07 | E11: Runbook de 19 tarefas, referência a tarefas 01-22 e outro registro de dez tarefa — Runbook de 19 tarefas, referência a tarefas 01-22 e outro registro de dez tarefas. | F11: Precedencia conforme regra do EXECUTAR-DOC-PREFILL-001: fonte mais recente e de maior autoridade vence; sem isso, permanece CONFLICT. | G11: TRUE | H11: ABERTO

Sheet 23_REG_Legacy_ID_Map
A1: legacy_id | B1: canonical_id | C1: object_type | D1: note
A2: D01-DOC-DDE-001 | B2: D01-DOC-DDE-001 | C2: artifact | D2: ID de origem já em formato canônico; preservado sem alteração.
A3: D01-DOC-TAP-001 | B3: D01-DOC-TAP-001 | C3: artifact | D3: ID de origem já em formato canônico; preservado sem alteração.
A4: D01-DOC-MNE-001 | B4: D01-DOC-MNE-001 | C4: artifact | D4: ID de origem já em formato canônico; preservado sem alteração.
A5: D01-DOC-MRE-001 | B5: D01-DOC-MRE-001 | C5: artifact | D5: ID de origem já em formato canônico; preservado sem alteração.
A6: D02-DOC-DGRC-001 | B6: D02-DOC-DGRC-001 | C6: artifact | D6: ID de origem já em formato canônico; preservado sem alteração.
A7: D02-DOC-MRC-001 | B7: D02-DOC-MRC-001 | C7: artifact | D7: ID de origem já em formato canônico; preservado sem alteração.
A8: D02-DOC-PPT-001 | B8: D02-DOC-PPT-001 | C8: artifact | D8: ID de origem já em formato canônico; preservado sem alteração.
A9: D03-DOC-PFO-001 | B9: D03-DOC-PFO-001 | C9: artifact | D9: ID de origem já em formato canônico; preservado sem alteração.
A10: D03-DOC-MFO-001 | B10: D03-DOC-MFO-001 | C10: artifact | D10: ID de origem já em formato canônico; preservado sem alteração.
A11: D04-DOC-PPC-001 | B11: D04-DOC-PPC-001 | C11: artifact | D11: ID de origem já em formato canônico; preservado sem alteração.
A12: D05-DOC-EPGD-001 | B12: D05-DOC-EPGD-001 | C12: artifact | D12: ID de origem já em formato canônico; preservado sem alteração.
... A38: D23-DOC-PBL-001 | B38: D23-DOC-PBL-001 | C38: artifact | D38: ID de origem já em formato canônico; preservado sem alteração.

Sheet 24_REG_Sources
A1: source_id | B1: name | C1: role
A2: SRC-01 | B2: EXECUTAR_projetosaasentrypoint_EXPANDIDO.xlsx | C2: UX/structure reference (Release 1 baseline)
A3: SRC-02 | B3: EXECUTAR_CHECKLIST_D01-D23_GRANULAR.yaml | C3: Structured corpus: 23 domains, 37 deliverables, 1125 fields
A4: SRC-03 | B4: Progama_Master_index.docx | C4: PM lifecycle taxonomy (D0+D01-D23 x PM01-13), corroborates domain list
A5: SRC-04 | B5: ecossistema_operacional.yaml | C5: Portfolio (Mxx), macroarea candidate list, PM lifecycle phases, area folder names
A6: SRC-05 | B6: GOV-SPEC-20260907-001 | C6: Upstream governance spec cited inside granular checklist (blocks B01,B02,B04,B07,B08,B09 read in full per prefill_limitations)
